Workbook

Sheet Summary
A1: TRINITY PRESBYTERIAN SCHOOL
A2: Five-Year Financial Forecast - Summary by Major Category
A3: ="Data check: "&B46 -> Data check: OK - ties to QuickBooks
A5: Fiscal year ending June 30 | B5: =Inputs!C$4 -> FY27 | C5: =Inputs!D$4 -> FY28 | D5: =Inputs!E$4 -> FY29 | E5: =Inputs!F$4 -> FY30 | F5: =Inputs!G$4 -> FY31 | G5: 5-yr CAGR
A6: Enrollment (students) | B6: =Enrollment!B21 -> 582 | C6: =Enrollment!C21 -> 591 | D6: =Enrollment!D21 -> 588 | E6: =Enrollment!E21 -> 583 | F6: =Enrollment!F21 -> 579
A7: Tuition rate increase | B7: =Inputs!C9 -> 0.04 | C7: =Inputs!D9 -> 0.05 | D7: =Inputs!E9 -> 0.045 | E7: =Inputs!F9 -> 0.045 | F7: =Inputs!G9 -> 0.04
A8: Salary increase | B8: =Inputs!C10 -> 0.025 | C8: =Inputs!D10 -> 0.03 | D8: =Inputs!E10 -> 0.03 | E8: =Inputs!F10 -> 0.03 | F8: =Inputs!G10 -> 0.03
A10: REVENUE
A11: 1 Tuition and Fees | B11: =SUMIFS('Forecast Detail'!G$8:G$400,'Forecast Detail'!$B$8:$B$400,$A11)+SUMIFS('QB Import'!$B$1:$B$600,'QB Import'!$F$1:$F$600,$A11,'QB Import'!$I$1:$I$600,"UNMAPPED") -> 8799382 | C11: =SUMIFS('Forecast Detail'!H$8:H$400,'Forecast Detail'!$B$8:$B$400,$A11)+SUMIFS('QB Import'!$B$1:$B$600,'QB Import'!$F$1:$F$600,$A11,'QB Import'!$I$1:$I$600,"UNMAPPED") -> 9300918.4 | D11: =SUMIFS('Forecast Detail'!I$8:I$400,'Forecast Detail'!$B$8:$B$400,$A11)+SUMIFS('QB Import'!$B$1:$B$600,'QB Import'!$F$1:$F$600,$A11,'QB Import'!$I$1:$I$600,"UNMAPPED") -> 9629546.3 | E11: =SUMIFS('Forecast Detail'!J$8:J$400,'Forecast Detail'!$B$8:$B$400,$A11)+SUMIFS('QB Import'!$B$1:$B$600,'QB Import'!$F$1:$F$600,$A11,'QB Import'!$I$1:$I$600,"UNMAPPED") -> 9941469.6 | F11: =SUMIFS('Forecast Detail'!K$8:K$400,'Forecast Detail'!$B$8:$B$400,$A11)+SUMIFS('QB Import'!$B$1:$B$600,'QB Import'!$F$1:$F$600,$A11,'QB Import'!$I$1:$I$600,"UNMAPPED") -> 10246937 | G11: =IF(AND(B11>0,F11>0),(F11/B11)^(1/4)-1,"") -> 0.038808452
A12: 2 Interest and Other Income | B12: =SUMIFS('Forecast Detail'!G$8:G$400,'Forecast Detail'!$B$8:$B$400,$A12)+SUMIFS('QB Import'!$B$1:$B$600,'QB Import'!$F$1:$F$600,$A12,'QB Import'!$I$1:$I$600,"UNMAPPED") -> 445000 | C12: =SUMIFS('Forecast Detail'!H$8:H$400,'Forecast Detail'!$B$8:$B$400,$A12)+SUMIFS('QB Import'!$B$1:$B$600,'QB Import'!$F$1:$F$600,$A12,'QB Import'!$I$1:$I$600,"UNMAPPED") -> 394005.03 | D12: =SUMIFS('Forecast Detail'!I$8:I$400,'Forecast Detail'!$B$8:$B$400,$A12)+SUMIFS('QB Import'!$B$1:$B$600,'QB Import'!$F$1:$F$600,$A12,'QB Import'!$I$1:$I$600,"UNMAPPED") -> 344005.03 | E12: =SUMIFS('Forecast Detail'!J$8:J$400,'Forecast Detail'!$B$8:$B$400,$A12)+SUMIFS('QB Import'!$B$1:$B$600,'QB Import'!$F$1:$F$600,$A12,'QB Import'!$I$1:$I$600,"UNMAPPED") -> 344005.03 | F12: =SUMIFS('Forecast Detail'!K$8:K$400,'Forecast Detail'!$B$8:$B$400,$A12)+SUMIFS('QB Import'!$B$1:$B$600,'QB Import'!$F$1:$F$600,$A12,'QB Import'!$I$1:$I$600,"UNMAPPED") -> 344005.03 | G12: =IF(AND(B12>0,F12>0),(F12/B12)^(1/4)-1,"") -> -0.062327464
A13: 4 Other Miscellaneous Income | B13: =SUMIFS('Forecast Detail'!G$8:G$400,'Forecast Detail'!$B$8:$B$400,$A13)+SUMIFS('QB Import'!$B$1:$B$600,'QB Import'!$F$1:$F$600,$A13,'QB Import'!$I$1:$I$600,"UNMAPPED") -> 60000 | C13: =SUMIFS('Forecast Detail'!H$8:H$400,'Forecast Detail'!$B$8:$B$400,$A13)+SUMIFS('QB Import'!$B$1:$B$600,'QB Import'!$F$1:$F$600,$A13,'QB Import'!$I$1:$I$600,"UNMAPPED") -> 60000 | D13: =SUMIFS('Forecast Detail'!I$8:I$400,'Forecast Detail'!$B$8:$B$400,$A13)+SUMIFS('QB Import'!$B$1:$B$600,'QB Import'!$F$1:$F$600,$A13,'QB Import'!$I$1:$I$600,"UNMAPPED") -> 60000 | E13: =SUMIFS('Forecast Detail'!J$8:J$400,'Forecast Detail'!$B$8:$B$400,$A13)+SUMIFS('QB Import'!$B$1:$B$600,'QB Import'!$F$1:$F$600,$A13,'QB Import'!$I$1:$I$600,"UNMAPPED") -> 60000 | F13: =SUMIFS('Forecast Detail'!K$8:K$400,'Forecast Detail'!$B$8:$B$400,$A13)+SUMIFS('QB Import'!$B$1:$B$600,'QB Import'!$F$1:$F$600,$A13,'QB Import'!$I$1:$I$600,"UNMAPPED") -> 60000 | G13: =IF(AND(B13>0,F13>0),(F13/B13)^(1/4)-1,"") -> 0
A14: 5 Athletic Income | B14: =SUMIFS('Forecast Detail'!G$8:G$400,'Forecast Detail'!$B$8:$B$400,$A14)+SUMIFS('QB Import'!$B$1:$B$600,'QB Import'!$F$1:$F$600,$A14,'QB Import'!$I$1:$I$600,"UNMAPPED") -> 0 | C14: =SUMIFS('Forecast Detail'!H$8:H$400,'Forecast Detail'!$B$8:$B$400,$A14)+SUMIFS('QB Import'!$B$1:$B$600,'QB Import'!$F$1:$F$600,$A14,'QB Import'!$I$1:$I$600,"UNMAPPED") -> 0 | D14: =SUMIFS('Forecast Detail'!I$8:I$400,'Forecast Detail'!$B$8:$B$400,$A14)+SUMIFS('QB Import'!$B$1:$B$600,'QB Import'!$F$1:$F$600,$A14,'QB Import'!$I$1:$I$600,"UNMAPPED") -> 0 | E14: =SUMIFS('Forecast Detail'!J$8:J$400,'Forecast Detail'!$B$8:$B$400,$A14)+SUMIFS('QB Import'!$B$1:$B$600,'QB Import'!$F$1:$F$600,$A14,'QB Import'!$I$1:$I$600,"UNMAPPED") -> 0 | F14: =SUMIFS('Forecast Detail'!K$8:K$400,'Forecast Detail'!$B$8:$B$400,$A14)+SUMIFS('QB Import'!$B$1:$B$600,'QB Import'!$F$1:$F$600,$A14,'QB Import'!$I$1:$I$600,"UNMAPPED") -> 0 | G14: =IF(AND(B14>0,F14>0),(F14/B14)^(1/4)-1,"")
A15: Total Revenue | B15: =SUM(B11:B14) -> 9304382 | C15: =SUM(C11:C14) -> 9754923.5 | D15: =SUM(D11:D14) -> 10033551 | E15: =SUM(E11:E14) -> 10345475 | F15: =SUM(F11:F14) -> 10650942 | G15: =IF(AND(B15>0,F15>0),(F15/B15)^(1/4)-1,"") -> 0.034368111
A17: EXPENSES
A18: 1 Salaries and Benefits | B18: =SUMIFS('Forecast Detail'!G$8:G$400,'Forecast Detail'!$B$8:$B$400,$A18)+SUMIFS('QB Import'!$B$1:$B$600,'QB Import'!$F$1:$F$600,$A18,'QB Import'!$I$1:$I$600,"UNMAPPED") -> 6253109 | C18: =SUMIFS('Forecast Detail'!H$8:H$400,'Forecast Detail'!$B$8:$B$400,$A18)+SUMIFS('QB Import'!$B$1:$B$600,'QB Import'!$F$1:$F$600,$A18,'QB Import'!$I$1:$I$600,"UNMAPPED") -> 6455524.8 | D18: =SUMIFS('Forecast Detail'!I$8:I$400,'Forecast Detail'!$B$8:$B$400,$A18)+SUMIFS('QB Import'!$B$1:$B$600,'QB Import'!$F$1:$F$600,$A18,'QB Import'!$I$1:$I$600,"UNMAPPED") -> 6653066.2 | E18: =SUMIFS('Forecast Detail'!J$8:J$400,'Forecast Detail'!$B$8:$B$400,$A18)+SUMIFS('QB Import'!$B$1:$B$600,'QB Import'!$F$1:$F$600,$A18,'QB Import'!$I$1:$I$600,"UNMAPPED") -> 6854595.5 | F18: =SUMIFS('Forecast Detail'!K$8:K$400,'Forecast Detail'!$B$8:$B$400,$A18)+SUMIFS('QB Import'!$B$1:$B$600,'QB Import'!$F$1:$F$600,$A18,'QB Import'!$I$1:$I$600,"UNMAPPED") -> 7061481.9 | G18: =IF(AND(B18>0,F18>0),(F18/B18)^(1/4)-1,"") -> 0.030860652
A19: 2 Instructional Expenses | B19: =SUMIFS('Forecast Detail'!G$8:G$400,'Forecast Detail'!$B$8:$B$400,$A19)+SUMIFS('QB Import'!$B$1:$B$600,'QB Import'!$F$1:$F$600,$A19,'QB Import'!$I$1:$I$600,"UNMAPPED") -> 252750 | C19: =SUMIFS('Forecast Detail'!H$8:H$400,'Forecast Detail'!$B$8:$B$400,$A19)+SUMIFS('QB Import'!$B$1:$B$600,'QB Import'!$F$1:$F$600,$A19,'QB Import'!$I$1:$I$600,"UNMAPPED") -> 260332.5 | D19: =SUMIFS('Forecast Detail'!I$8:I$400,'Forecast Detail'!$B$8:$B$400,$A19)+SUMIFS('QB Import'!$B$1:$B$600,'QB Import'!$F$1:$F$600,$A19,'QB Import'!$I$1:$I$600,"UNMAPPED") -> 268142.47 | E19: =SUMIFS('Forecast Detail'!J$8:J$400,'Forecast Detail'!$B$8:$B$400,$A19)+SUMIFS('QB Import'!$B$1:$B$600,'QB Import'!$F$1:$F$600,$A19,'QB Import'!$I$1:$I$600,"UNMAPPED") -> 276186.75 | F19: =SUMIFS('Forecast Detail'!K$8:K$400,'Forecast Detail'!$B$8:$B$400,$A19)+SUMIFS('QB Import'!$B$1:$B$600,'QB Import'!$F$1:$F$600,$A19,'QB Import'!$I$1:$I$600,"UNMAPPED") -> 284472.35 | G19: =IF(AND(B19>0,F19>0),(F19/B19)^(1/4)-1,"") -> 0.03
A20: 3 Operations | B20: =SUMIFS('Forecast Detail'!G$8:G$400,'Forecast Detail'!$B$8:$B$400,$A20)+SUMIFS('QB Import'!$B$1:$B$600,'QB Import'!$F$1:$F$600,$A20,'QB Import'!$I$1:$I$600,"UNMAPPED") -> 1847250 | C20: =SUMIFS('Forecast Detail'!H$8:H$400,'Forecast Detail'!$B$8:$B$400,$A20)+SUMIFS('QB Import'!$B$1:$B$600,'QB Import'!$F$1:$F$600,$A20,'QB Import'!$I$1:$I$600,"UNMAPPED") -> 1914294.8 | D20: =SUMIFS('Forecast Detail'!I$8:I$400,'Forecast Detail'!$B$8:$B$400,$A20)+SUMIFS('QB Import'!$B$1:$B$600,'QB Import'!$F$1:$F$600,$A20,'QB Import'!$I$1:$I$600,"UNMAPPED") -> 1967731.6 | E20: =SUMIFS('Forecast Detail'!J$8:J$400,'Forecast Detail'!$B$8:$B$400,$A20)+SUMIFS('QB Import'!$B$1:$B$600,'QB Import'!$F$1:$F$600,$A20,'QB Import'!$I$1:$I$600,"UNMAPPED") -> 2019910.6 | F20: =SUMIFS('Forecast Detail'!K$8:K$400,'Forecast Detail'!$B$8:$B$400,$A20)+SUMIFS('QB Import'!$B$1:$B$600,'QB Import'!$F$1:$F$600,$A20,'QB Import'!$I$1:$I$600,"UNMAPPED") -> 2074861 | G20: =IF(AND(B20>0,F20>0),(F20/B20)^(1/4)-1,"") -> 0.029475066
A21: 4 Administrative | B21: =SUMIFS('Forecast Detail'!G$8:G$400,'Forecast Detail'!$B$8:$B$400,$A21)+SUMIFS('QB Import'!$B$1:$B$600,'QB Import'!$F$1:$F$600,$A21,'QB Import'!$I$1:$I$600,"UNMAPPED") -> 778368 | C21: =SUMIFS('Forecast Detail'!H$8:H$400,'Forecast Detail'!$B$8:$B$400,$A21)+SUMIFS('QB Import'!$B$1:$B$600,'QB Import'!$F$1:$F$600,$A21,'QB Import'!$I$1:$I$600,"UNMAPPED") -> 795138.74 | D21: =SUMIFS('Forecast Detail'!I$8:I$400,'Forecast Detail'!$B$8:$B$400,$A21)+SUMIFS('QB Import'!$B$1:$B$600,'QB Import'!$F$1:$F$600,$A21,'QB Import'!$I$1:$I$600,"UNMAPPED") -> 810947.37 | E21: =SUMIFS('Forecast Detail'!J$8:J$400,'Forecast Detail'!$B$8:$B$400,$A21)+SUMIFS('QB Import'!$B$1:$B$600,'QB Import'!$F$1:$F$600,$A21,'QB Import'!$I$1:$I$600,"UNMAPPED") -> 703223.52 | F21: =SUMIFS('Forecast Detail'!K$8:K$400,'Forecast Detail'!$B$8:$B$400,$A21)+SUMIFS('QB Import'!$B$1:$B$600,'QB Import'!$F$1:$F$600,$A21,'QB Import'!$I$1:$I$600,"UNMAPPED") -> 658007.96 | G21: =IF(AND(B21>0,F21>0),(F21/B21)^(1/4)-1,"") -> -0.041125998
A22: 5 Athletic Expenses | B22: =SUMIFS('Forecast Detail'!G$8:G$400,'Forecast Detail'!$B$8:$B$400,$A22)+SUMIFS('QB Import'!$B$1:$B$600,'QB Import'!$F$1:$F$600,$A22,'QB Import'!$I$1:$I$600,"UNMAPPED") -> 171263 | C22: =SUMIFS('Forecast Detail'!H$8:H$400,'Forecast Detail'!$B$8:$B$400,$A22)+SUMIFS('QB Import'!$B$1:$B$600,'QB Import'!$F$1:$F$600,$A22,'QB Import'!$I$1:$I$600,"UNMAPPED") -> 176400.89 | D22: =SUMIFS('Forecast Detail'!I$8:I$400,'Forecast Detail'!$B$8:$B$400,$A22)+SUMIFS('QB Import'!$B$1:$B$600,'QB Import'!$F$1:$F$600,$A22,'QB Import'!$I$1:$I$600,"UNMAPPED") -> 181692.92 | E22: =SUMIFS('Forecast Detail'!J$8:J$400,'Forecast Detail'!$B$8:$B$400,$A22)+SUMIFS('QB Import'!$B$1:$B$600,'QB Import'!$F$1:$F$600,$A22,'QB Import'!$I$1:$I$600,"UNMAPPED") -> 187143.7 | F22: =SUMIFS('Forecast Detail'!K$8:K$400,'Forecast Detail'!$B$8:$B$400,$A22)+SUMIFS('QB Import'!$B$1:$B$600,'QB Import'!$F$1:$F$600,$A22,'QB Import'!$I$1:$I$600,"UNMAPPED") -> 192758.02 | G22: =IF(AND(B22>0,F22>0),(F22/B22)^(1/4)-1,"") -> 0.03
A23: Strategic Plan Initiatives (operating, net) | B23: =Inputs!E31 -> 0 | C23: =Inputs!F31 -> 50000 | D23: =Inputs!G31 -> 100000 | E23: =Inputs!H31 -> 150000 | F23: =Inputs!I31 -> 200000
A24: Total Expenses | B24: =SUM(B18:B23) -> 9302740 | C24: =SUM(C18:C23) -> 9651691.8 | D24: =SUM(D18:D23) -> 9981580.5 | E24: =SUM(E18:E23) -> 10191060 | F24: =SUM(F18:F23) -> 10471581 | G24: =IF(AND(B24>0,F24>0),(F24/B24)^(1/4)-1,"") -> 0.030031119
A26: Net Operating Revenue | B26: =B15-B24 -> 1642 | C26: =C15-C24 -> 103231.68 | D26: =D15-D24 -> 51970.772 | E26: =E15-E24 -> 154414.65 | F26: =F15-F24 -> 179360.91
A27: Other Revenue (Development) | B27: =SUMIFS('Forecast Detail'!G$8:G$400,'Forecast Detail'!$B$8:$B$400,"Other Revenue")+SUMIFS('QB Import'!$B$1:$B$600,'QB Import'!$F$1:$F$600,"Other Revenue",'QB Import'!$I$1:$I$600,"UNMAPPED") -> 0 | C27: =SUMIFS('Forecast Detail'!H$8:H$400,'Forecast Detail'!$B$8:$B$400,"Other Revenue")+SUMIFS('QB Import'!$B$1:$B$600,'QB Import'!$F$1:$F$600,"Other Revenue",'QB Import'!$I$1:$I$600,"UNMAPPED") -> 0 | D27: =SUMIFS('Forecast Detail'!I$8:I$400,'Forecast Detail'!$B$8:$B$400,"Other Revenue")+SUMIFS('QB Import'!$B$1:$B$600,'QB Import'!$F$1:$F$600,"Other Revenue",'QB Import'!$I$1:$I$600,"UNMAPPED") -> 0 | E27: =SUMIFS('Forecast Detail'!J$8:J$400,'Forecast Detail'!$B$8:$B$400,"Other Revenue")+SUMIFS('QB Import'!$B$1:$B$600,'QB Import'!$F$1:$F$600,"Other Revenue",'QB Import'!$I$1:$I$600,"UNMAPPED") -> 0 | F27: =SUMIFS('Forecast Detail'!K$8:K$400,'Forecast Detail'!$B$8:$B$400,"Other Revenue")+SUMIFS('QB Import'!$B$1:$B$600,'QB Import'!$F$1:$F$600,"Other Revenue",'QB Import'!$I$1:$I$600,"UNMAPPED") -> 0
A28: Other Expenditures (Development) | B28: =SUMIFS('Forecast Detail'!G$8:G$400,'Forecast Detail'!$B$8:$B$400,"Other Expense")+SUMIFS('QB Import'!$B$1:$B$600,'QB Import'!$F$1:$F$600,"Other Expense",'QB Import'!$I$1:$I$600,"UNMAPPED") -> 0 | C28: =SUMIFS('Forecast Detail'!H$8:H$400,'Forecast Detail'!$B$8:$B$400,"Other Expense")+SUMIFS('QB Import'!$B$1:$B$600,'QB Import'!$F$1:$F$600,"Other Expense",'QB Import'!$I$1:$I$600,"UNMAPPED") -> 0 | D28: =SUMIFS('Forecast Detail'!I$8:I$400,'Forecast Detail'!$B$8:$B$400,"Other Expense")+SUMIFS('QB Import'!$B$1:$B$600,'QB Import'!$F$1:$F$600,"Other Expense",'QB Import'!$I$1:$I$600,"UNMAPPED") -> 0 | E28: =SUMIFS('Forecast Detail'!J$8:J$400,'Forecast Detail'!$B$8:$B$400,"Other Expense")+SUMIFS('QB Import'!$B$1:$B$600,'QB Import'!$F$1:$F$600,"Other Expense",'QB Import'!$I$1:$I$600,"UNMAPPED") -> 0 | F28: =SUMIFS('Forecast Detail'!K$8:K$400,'Forecast Detail'!$B$8:$B$400,"Other Expense")+SUMIFS('QB Import'!$B$1:$B$600,'QB Import'!$F$1:$F$600,"Other Expense",'QB Import'!$I$1:$I$600,"UNMAPPED") -> 0
A29: Net Other Revenue | B29: =B27-B28 -> 0 | C29: =C27-C28 -> 0 | D29: =D27-D28 -> 0 | E29: =E27-E28 -> 0 | F29: =F27-F28 -> 0
A30: NET REVENUE (SURPLUS / DEFICIT) | B30: =B26+B29 -> 1642 | C30: =C26+C29 -> 103231.68 | D30: =D26+D29 -> 51970.772 | E30: =E26+E29 -> 154414.65 | F30: =F26+F29 -> 179360.91
A32: KEY METRICS
A33: Salaries & benefits % of total revenue | B33: =IF(B15=0,0,B18/B15) -> 0.67206065 | C33: =IF(C15=0,0,C18/C15) -> 0.66177094 | D33: =IF(D15=0,0,D18/D15) -> 0.66308189 | E33: =IF(E15=0,0,E18/E15) -> 0.66256945 | F33: =IF(F15=0,0,F18/F15) -> 0.66299129
A34: Net tuition & fees per student | B34: =IF(B6=0,0,B11/B6) -> 15119.213 | C34: =IF(C6=0,0,C11/C6) -> 15737.595 | D34: =IF(D6=0,0,D11/D6) -> 16376.779 | E34: =IF(E6=0,0,E11/E6) -> 17052.264 | F34: =IF(F6=0,0,F11/F6) -> 17697.646
A35: Net revenue margin (% of revenue) | B35: =IF(B15=0,0,B30/B15) -> 0.00017647599 | C35: =IF(C15=0,0,C30/C15) -> 0.010582521 | D35: =IF(D15=0,0,D30/D15) -> 0.0051796986 | E35: =IF(E15=0,0,E30/E15) -> 0.014925816 | F35: =IF(F15=0,0,F30/F15) -> 0.016839911
A36: Capital projects & initiatives (cash) | B36: =-'CF Summary'!B8 -> 0 | C36: =-'CF Summary'!C8 -> 0 | D36: =-'CF Summary'!D8 -> 0 | E36: =-'CF Summary'!E8 -> 0 | F36: =-'CF Summary'!F8 -> 0
A37: Ending cash & reserves | B37: ='CF Summary'!B12 -> 2379207.7 | C37: ='CF Summary'!C12 -> 2586817.6 | D37: ='CF Summary'!D12 -> 2738051 | E37: ='CF Summary'!E12 -> 2989594.7 | F37: ='CF Summary'!F12 -> 3296725.4
A38: Lowest month-end operating cash | B38: ='CF Summary'!B13 -> -31299.821 | C38: ='CF Summary'!C13 -> 131306.32 | D38: ='CF Summary'!D13 -> 238258.55 | E38: ='CF Summary'!E13 -> 427586.45 | F38: ='CF Summary'!F13 -> 653700.89
A39: Days cash on hand | B39: ='CF Summary'!B15 -> 93.350004 | C39: ='CF Summary'!C15 -> 97.826208 | D39: ='CF Summary'!D15 -> 100.12328 | E39: ='CF Summary'!E15 -> 107.07444 | F39: ='CF Summary'!F15 -> 114.91147
A41: Source: FY27 = QuickBooks budget import; FY28-FY31 = forecast per Inputs and Forecast Detail. Cash on a cash basis.
A43: IMPORT CHECKS (not printed)
A44: Revenue: import detail vs summary FY27 | B44: =SUMIFS('QB Import'!$B$1:$B$600,'QB Import'!$E$1:$E$600,"Revenue",'QB Import'!$G$1:$G$600,1)+SUMIFS('QB Import'!$B$1:$B$600,'QB Import'!$E$1:$E$600,"COGS",'QB Import'!$G$1:$G$600,1)-SUM(B11:B14) -> 0
A45: Expenses: import detail vs summary FY27 | B45: =SUMIFS('QB Import'!$B$1:$B$600,'QB Import'!$E$1:$E$600,"Expense",'QB Import'!$G$1:$G$600,1)-SUM(B18:B22) -> 0
A46: Overall status | B46: =IF(AND(ABS(B44)<1,ABS(B45)<1,ABS(B47)<1,ABS(B48)<1,B49=0,B50=0),"OK - ties to QuickBooks","CHECK - "&B49&" unmapped account(s); see rows 44-50") -> OK - ties to QuickBooks
A47: Other net: import detail vs summary FY27 | B47: =SUMIFS('QB Import'!$B$1:$B$600,'QB Import'!$E$1:$E$600,"Other Revenue",'QB Import'!$G$1:$G$600,1)-SUMIFS('QB Import'!$B$1:$B$600,'QB Import'!$E$1:$E$600,"Other Expense",'QB Import'!$G$1:$G$600,1)-B29 -> 0
A48: Net Revenue: summary FY27 vs QuickBooks 'Net Revenue' line | B48: =IF(COUNTIF('QB Import'!$D$1:$D$600,"Net Revenue")=0,0,SUMIFS('QB Import'!$B$1:$B$600,'QB Import'!$D$1:$D$600,"Net Revenue")-B30) -> 0
A49: Accounts on import not in Forecast Detail (count) | B49: =COUNTIF('QB Import'!$I$1:$I$600,"UNMAPPED") -> 0
A50: Forecast Detail rows with no method (count) | B50: =COUNTA('Forecast Detail'!$C$8:$C$400)-COUNTA('Forecast Detail'!$E$8:$E$400) -> 0

Sheet Inputs
A1: INPUTS & ASSUMPTIONS
A2: Blue-on-yellow cells are inputs. Everything else is calculated. FY27 amounts come from the QuickBooks import.
A4: Fiscal year | C4: ="FY"&TEXT(C5,"yy") -> FY27 | D4: ="FY"&TEXT(D5,"yy") -> FY28 | E4: ="FY"&TEXT(E5,"yy") -> FY29 | F4: ="FY"&TEXT(F5,"yy") -> FY30 | G4: ="FY"&TEXT(G5,"yy") -> FY31
A5: Fiscal year ending | C5: 46568 | D5: =EOMONTH(C5,12) -> 46934 | E5: =EOMONTH(D5,12) -> 47299 | F5: =EOMONTH(E5,12) -> 47664 | G5: =EOMONTH(F5,12) -> 48029
A6: Fiscal year starting | C6: =EOMONTH(C5,-12)+1 -> 46204 | D6: =EOMONTH(D5,-12)+1 -> 46569 | E6: =EOMONTH(E5,-12)+1 -> 46935 | F6: =EOMONTH(F5,-12)+1 -> 47300 | G6: =EOMONTH(G5,-12)+1 -> 47665
A8: Growth assumptions
A9: Tuition rate increase % | C9: 0.04 | D9: 0.05 | E9: 0.045 | F9: 0.045 | G9: 0.04 | H9: FY27 shown for reference; rates already set in the budget
A10: Salary increase % | C10: 0.025 | D10: 0.03 | E10: 0.03 | F10: 0.03 | G10: 0.03 | H10: Applies to lines using the 'Salary' method
A11: Benefits cost increase % (medical, dental) | C11: 0.03 | D11: 0.03 | E11: 0.03 | F11: 0.03 | G11: 0.03 | H11: Lines using the 'Benefits' method
A12: General inflation % | C12: 0.03 | D12: 0.03 | E12: 0.03 | F12: 0.03 | G12: 0.03 | H12: Lines using 'Inflation' and 'Per Student'
A13: Yield on interest-earning balances % | D13: 0.014 | E13: 0.014 | F13: 0.014 | G13: 0.014 | H13: Applied to prior year-end balances; 'Reserve Yield' method
A14: Final mortgage payment date | C14: 47422 | H14: Lines using the 'Debt' method stop after this month
A15: Months of debt service paid in fiscal year | C15: =MAX(0,MIN(12,(YEAR($C$14)-YEAR(C6))*12+MONTH($C$14)-MONTH(C6)+1)) -> 12 | D15: =MAX(0,MIN(12,(YEAR($C$14)-YEAR(D6))*12+MONTH($C$14)-MONTH(D6)+1)) -> 12 | E15: =MAX(0,MIN(12,(YEAR($C$14)-YEAR(E6))*12+MONTH($C$14)-MONTH(E6)+1)) -> 12 | F15: =MAX(0,MIN(12,(YEAR($C$14)-YEAR(F6))*12+MONTH($C$14)-MONTH(F6)+1)) -> 4 | G15: =MAX(0,MIN(12,(YEAR($C$14)-YEAR(G6))*12+MONTH($C$14)-MONTH(G6)+1)) -> 0
A16: Interest-earning balance at prior year-end | D16: =$D$60+SUM($C$48:C48) -> 2071787.9 | E16: =$D$60+SUM($C$48:D48) -> 2071787.9 | F16: =$D$60+SUM($C$48:E48) -> 2071787.9 | G16: =$D$60+SUM($C$48:F48) -> 2071787.9 | H16: Opening earning balances + reserve funding to date
A18: Strategic plan initiatives (Operating = flows through the P&L; Capital = cash only, no P&L)
A19: Initiative | B19: Type | C19: On? (Y/N) | D19: Spend month (0=even, 1=Jul) | E19: ="Cost "&C$4 -> Cost FY27 | F19: ="Cost "&D$4 -> Cost FY28 | G19: ="Cost "&E$4 -> Cost FY29 | H19: ="Cost "&F$4 -> Cost FY30 | I19: ="Cost "&G$4 -> Cost FY31 | J19: ="Offset "&C$4 -> Offset FY27 | K19: ="Offset "&D$4 -> Offset FY28 | L19: ="Offset "&E$4 -> Offset FY29 | M19: ="Offset "&F$4 -> Offset FY30 | N19: ="Offset "&G$4 -> Offset FY31
A20: Additional Lower School teacher (per prior model: +$50k/yr) | B20: Operating | C20: Y | D20: 0 | E20: 0 | F20: 50000 | G20: 100000 | H20: 150000 | I20: 200000 | J20: 0 | K20: 0 | L20: 0 | M20: 0 | N20: 0
A21: Lower School reconfiguration (enter cost) | B21: Capital | C21: Y | D21: 0 | E21: 0 | F21: 0 | G21: 0 | H21: 0 | I21: 0 | J21: 0 | K21: 0 | L21: 0 | M21: 0 | N21: 0
A31: Operating initiatives - net cost to P&L | E31: =SUMPRODUCT(($B$20:$B$29="Operating")*($C$20:$C$29="Y")*(E$20:E$29-J$20:J$29)) -> 0 | F31: =SUMPRODUCT(($B$20:$B$29="Operating")*($C$20:$C$29="Y")*(F$20:F$29-K$20:K$29)) -> 50000 | G31: =SUMPRODUCT(($B$20:$B$29="Operating")*($C$20:$C$29="Y")*(G$20:G$29-L$20:L$29)) -> 100000 | H31: =SUMPRODUCT(($B$20:$B$29="Operating")*($C$20:$C$29="Y")*(H$20:H$29-M$20:M$29)) -> 150000 | I31: =SUMPRODUCT(($B$20:$B$29="Operating")*($C$20:$C$29="Y")*(I$20:I$29-N$20:N$29)) -> 200000
A32: Capital initiatives - net cash cost | E32: =SUMPRODUCT(($B$20:$B$29="Capital")*($C$20:$C$29="Y")*(E$20:E$29-J$20:J$29)) -> 0 | F32: =SUMPRODUCT(($B$20:$B$29="Capital")*($C$20:$C$29="Y")*(F$20:F$29-K$20:K$29)) -> 0 | G32: =SUMPRODUCT(($B$20:$B$29="Capital")*($C$20:$C$29="Y")*(G$20:G$29-L$20:L$29)) -> 0 | H32: =SUMPRODUCT(($B$20:$B$29="Capital")*($C$20:$C$29="Y")*(H$20:H$29-M$20:M$29)) -> 0 | I32: =SUMPRODUCT(($B$20:$B$29="Capital")*($C$20:$C$29="Y")*(I$20:I$29-N$20:N$29)) -> 0
A34: Capital projects & equipment (cash only; outside the operating P&L)
A35: Project | B35: Spend month (0=even, 1=Jul) | C35: =C$4 -> FY27 | D35: =D$4 -> FY28 | E35: =E$4 -> FY29 | F35: =F$4 -> FY30 | G35: =G$4 -> FY31
A36: Example: roof replacement | B36: 0
B37: 0
B38: 0
B39: 0
B40: 0
B41: 0
A42: Total capital projects | C42: =SUM(C36:C41) -> 0 | D42: =SUM(D36:D41) -> 0 | E42: =SUM(E36:E41) -> 0 | F42: =SUM(F36:F41) -> 0 | G42: =SUM(G36:G41) -> 0
A44: Reserve funding (transfer from operating cash to reserves; cash-neutral overall)
A45: Transfer | B45: Month (0=even, 1=Jul) | C45: =C$4 -> FY27 | D45: =D$4 -> FY28 | E45: =E$4 -> FY29 | F45: =F$4 -> FY30 | G45: =G$4 -> FY31
A46: Operating reserve funding | B46: 12 | C46: 0 | D46: 0 | E46: 0 | F46: 0 | G46: 0
A47: Repair & replacement (R&R) reserve funding | B47: 12 | C47: 0 | D47: 0 | E47: 0 | F47: 0 | G47: 0
A48: Total reserve funding | C48: =SUM(C46:C47) -> 0 | D48: =SUM(D46:D47) -> 0 | E48: =SUM(E46:E47) -> 0 | F48: =SUM(F46:F47) -> 0 | G48: =SUM(G46:G47) -> 0
A50: Opening cash & reserve balances
A51: Balances as of (start of FY27 = 6/30/2026 recommended) | B51: 46203
A52: Account | B52: Available for operations? (Y/N) | C52: Earns interest? (Y/N) | D52: Balance
A53: Operating Account | B53: Y | C53: N | D53: 134596.05 | E53: Balances seeded from the 1/31/26 figures in the old model - UPDATE.
A54: Contingency | B54: N | C54: Y | D54: 441027.78
A55: S4K | B55: N | C55: Y | D55: 167658.2
A56: PPP Reserve Account | B56: Y | C56: Y | D56: 1029181.8
A57: Development Account | B57: N | C57: Y | D57: 433920.19
A58: Operating cash available (opening) | D58: =SUMIF(B53:B57,"Y",D53:D57) -> 1163777.8
A59: Reserves & restricted (opening) | D59: =SUMIF(B53:B57,"N",D53:D57) -> 1042606.2
A60: Interest-earning balances (opening) | D60: =SUMIF(C53:C57,"Y",D53:D57) -> 2071787.9
A62: Tuition payment plans (drives monthly cash receipts)
A63: Plan | B63: Families | C63: % of tuition
A64: Plan A - 1 annual payment (June 30) | B64: 94 | C64: =B64/SUM($B$64:$B$66) -> 0.16347826
A65: Plan B - 4 payments (May/Aug/Nov/Feb) | B65: 96 | C65: =B65/SUM($B$64:$B$66) -> 0.16695652
A66: Plan C - 12 monthly payments (May-April), incl. S4K & employees | B66: 385 | C66: =B66/SUM($B$64:$B$66) -> 0.66956522
A67: Total families in plans | B67: =SUM(B64:B66) -> 575
A69: Payment schedule: % of a plan's annual tuition received in each period
A70: Plan | B70: Prior May | C70: Prior Jun | D70: Jul | E70: Aug | F70: Sep | G70: Oct | H70: Nov | I70: Dec | J70: Jan | K70: Feb | L70: Mar | M70: Apr | N70: May | O70: Jun | P70: Total
A71: Plan A | B71: 0 | C71: 1 | D71: 0 | E71: 0 | F71: 0 | G71: 0 | H71: 0 | I71: 0 | J71: 0 | K71: 0 | L71: 0 | M71: 0 | N71: 0 | O71: 0 | P71: =SUM(B71:O71) -> 1
A72: Plan B | B72: 0.25 | C72: 0 | D72: 0 | E72: 0.25 | F72: 0 | G72: 0 | H72: 0.25 | I72: 0 | J72: 0 | K72: 0.25 | L72: 0 | M72: 0 | N72: 0 | O72: 0 | P72: =SUM(B72:O72) -> 1
A73: Plan C | B73: 0.083333333 | C73: 0.083333333 | D73: 0.083333333 | E73: 0.083333333 | F73: 0.083333333 | G73: 0.083333333 | H73: 0.083333333 | I73: 0.083333333 | J73: 0.083333333 | K73: 0.083333333 | L73: 0.083333333 | M73: 0.083333333 | N73: 0 | O73: 0 | P73: =SUM(B73:O73) -> 1
A74: Cash timing profiles: % of a fiscal year's amount received/paid in each period (used by Forecast Detail column F)
A75: Profile | B75: Prior May | C75: Prior Jun | D75: Jul | E75: Aug | F75: Sep | G75: Oct | H75: Nov | I75: Dec | J75: Jan | K75: Feb | L75: Mar | M75: Apr | N75: May | O75: Jun | P75: Total
A76: Tuition Plan | B76: =SUMPRODUCT($C$64:$C$66,B71:B73) -> 0.097536232 | C76: =SUMPRODUCT($C$64:$C$66,C71:C73) -> 0.21927536 | D76: =SUMPRODUCT($C$64:$C$66,D71:D73) -> 0.055797101 | E76: =SUMPRODUCT($C$64:$C$66,E71:E73) -> 0.097536232 | F76: =SUMPRODUCT($C$64:$C$66,F71:F73) -> 0.055797101 | G76: =SUMPRODUCT($C$64:$C$66,G71:G73) -> 0.055797101 | H76: =SUMPRODUCT($C$64:$C$66,H71:H73) -> 0.097536232 | I76: =SUMPRODUCT($C$64:$C$66,I71:I73) -> 0.055797101 | ... O76: =SUMPRODUCT($C$64:$C$66,O71:O73) -> 0 | P76: =SUM(B76:O76) -> 1
A77: Even | B77: 0 | C77: 0 | D77: 0.083333333 | E77: 0.083333333 | F77: 0.083333333 | G77: 0.083333333 | H77: 0.083333333 | I77: 0.083333333 | J77: 0.083333333 | K77: 0.083333333 | L77: 0.083333333 | M77: 0.083333333 | N77: 0.083333333 | O77: 0.083333333 | P77: =SUM(B77:O77) -> 1
A78: Jul Lump | B78: 0 | C78: 0 | D78: 1 | E78: 0 | F78: 0 | G78: 0 | H78: 0 | I78: 0 | J78: 0 | K78: 0 | L78: 0 | M78: 0 | N78: 0 | O78: 0 | P78: =SUM(B78:O78) -> 1
A79: Custom A | B79: 0 | C79: 0 | D79: 0 | E79: 0 | F79: 0 | G79: 0.5 | H79: 0 | I79: 0 | J79: 0 | K79: 0 | L79: 0.5 | M79: 0 | N79: 0 | O79: 0 | P79: =SUM(B79:O79) -> 1
A80: Custom B | B80: 0 | C80: 0 | D80: 0 | E80: 0 | F80: 0 | G80: 0 | H80: 0 | I80: 0 | J80: 0 | K80: 0 | L80: 0 | M80: 0 | N80: 0 | O80: 1 | P80: =SUM(B80:O80) -> 1
A81: Profile rows must total 100%
A83: Prior-year actuals & trend recommendation (see Actuals Import and Trend tabs)
A84: Actuals slot (paste export on Actuals Import) | C84: FY ending (e.g. 2026)
A85: Slot 1 (oldest): paste at A1 on Actuals Import | H85: Enter the fiscal year (ending June 30) of each pasted export, oldest to newest. Blank = slot unused.
A86: Slot 2 (next): paste at J1 on Actuals Import
A87: Slot 3 (next): paste at S1 on Actuals Import
A88: Slot 4 (next): paste at AB1 on Actuals Import
A89: Slot 5 (newest): paste at AK1 on Actuals Import
A90: Default recommendation method | C90: Linear Trend | H90: Last Actual / Average / Linear Trend / Growth (override per line on Trend tab)
A91: Round recommendation to nearest $ | C91: 100
A92: Flag lines that differ from FY27 budget by more than | C92: 0.1

Sheet Enrollment
A1: ENROLLMENT & TUITION RATES
A2: FY27 enrollment and rates are inputs. Later years roll each grade forward: prior grade x retention + new students.
A3: Enrollment by grade
A4: Grade | B4: =Inputs!C$4 -> FY27 | C4: =Inputs!D$4 -> FY28 | D4: =Inputs!E$4 -> FY29 | E4: =Inputs!F$4 -> FY30 | F4: =Inputs!G$4 -> FY31
A5: K-3 (5 day) | B5: 21 | C5: =C49 -> 20 | D5: =D49 -> 20 | E5: =E49 -> 20 | F5: =F49 -> 20
A6: K-3 (3 day) | B6: 4 | C6: =C50 -> 4 | D6: =D50 -> 4 | E6: =E50 -> 4 | F6: =F50 -> 4
A7: K-4 | B7: 44 | C7: =ROUND((B5+B6)*$B51+C51,0) -> 37 | D7: =ROUND((C5+C6)*$B51+D51,0) -> 36 | E7: =ROUND((D5+D6)*$B51+E51,0) -> 36 | F7: =ROUND((E5+E6)*$B51+F51,0) -> 36
A8: K5 | B8: 53 | C8: =ROUND(B7*$B52+C52,0) -> 45 | D8: =ROUND(C7*$B52+D52,0) -> 39 | E8: =ROUND(D7*$B52+E52,0) -> 38 | F8: =ROUND(E7*$B52+F52,0) -> 38
A9: 1st | B9: 45 | C9: =ROUND(B8*$B53+C53,0) -> 53 | D9: =ROUND(C8*$B53+D53,0) -> 45 | E9: =ROUND(D8*$B53+E53,0) -> 39 | F9: =ROUND(E8*$B53+F53,0) -> 38
A10: 2nd | B10: 37 | C10: =ROUND(B9*$B54+C54,0) -> 44 | D10: =ROUND(C9*$B54+D54,0) -> 52 | E10: =ROUND(D9*$B54+E54,0) -> 44 | F10: =ROUND(E9*$B54+F54,0) -> 38
A11: 3rd | B11: 33 | C11: =ROUND(B10*$B55+C55,0) -> 37 | D11: =ROUND(C10*$B55+D55,0) -> 43 | E11: =ROUND(D10*$B55+E55,0) -> 51 | F11: =ROUND(E10*$B55+F55,0) -> 43
A12: 4th | B12: 36 | C12: =ROUND(B11*$B56+C56,0) -> 33 | D12: =ROUND(C11*$B56+D56,0) -> 37 | E12: =ROUND(D11*$B56+E56,0) -> 42 | F12: =ROUND(E11*$B56+F56,0) -> 50
A13: 5th | B13: 36 | C13: =ROUND(B12*$B57+C57,0) -> 36 | D13: =ROUND(C12*$B57+D57,0) -> 33 | E13: =ROUND(D12*$B57+E57,0) -> 37 | F13: =ROUND(E12*$B57+F57,0) -> 41
A14: 6th | B14: 40 | C14: =ROUND(B13*$B58+C58,0) -> 39 | D14: =ROUND(C13*$B58+D58,0) -> 39 | E14: =ROUND(D13*$B58+E58,0) -> 36 | F14: =ROUND(E13*$B58+F58,0) -> 40
A15: 7th | B15: 34 | C15: =ROUND(B14*$B59+C59,0) -> 40 | D15: =ROUND(C14*$B59+D59,0) -> 39 | E15: =ROUND(D14*$B59+E59,0) -> 39 | F15: =ROUND(E14*$B59+F59,0) -> 37
A16: 8th | B16: 37 | C16: =ROUND(B15*$B60+C60,0) -> 35 | D16: =ROUND(C15*$B60+D60,0) -> 40 | E16: =ROUND(D15*$B60+E60,0) -> 39 | F16: =ROUND(E15*$B60+F60,0) -> 39
A17: 9th | B17: 45 | C17: =ROUND(B16*$B61+C61,0) -> 40 | D17: =ROUND(C16*$B61+D61,0) -> 38 | E17: =ROUND(D16*$B61+E61,0) -> 42 | F17: =ROUND(E16*$B61+F61,0) -> 41
A18: 10th | B18: 44 | C18: =ROUND(B17*$B62+C62,0) -> 44 | D18: =ROUND(C17*$B62+D62,0) -> 39 | E18: =ROUND(D17*$B62+E62,0) -> 37 | F18: =ROUND(E17*$B62+F62,0) -> 41
A19: 11th | B19: 43 | C19: =ROUND(B18*$B63+C63,0) -> 43 | D19: =ROUND(C18*$B63+D63,0) -> 43 | E19: =ROUND(D18*$B63+E63,0) -> 38 | F19: =ROUND(E18*$B63+F63,0) -> 37
A20: 12th | B20: 30 | C20: =ROUND(B19*$B64+C64,0) -> 41 | D20: =ROUND(C19*$B64+D64,0) -> 41 | E20: =ROUND(D19*$B64+E64,0) -> 41 | F20: =ROUND(E19*$B64+F64,0) -> 36
A21: Total enrollment | B21: =SUM(B5:B20) -> 582 | C21: =SUM(C5:C20) -> 591 | D21: =SUM(D5:D20) -> 588 | E21: =SUM(E5:E20) -> 583 | F21: =SUM(F5:F20) -> 579
A22: Change vs prior year | C22: =C21-B21 -> 9 | D22: =D21-C21 -> -3 | E22: =E21-D21 -> -5 | F22: =F21-E21 -> -4
A23: Tuition potential (enrollment x rate) | B23: =SUMPRODUCT(B5:B20,B29:B44) -> 9315096.2 | C23: =SUMPRODUCT(C5:C20,C29:C44) -> 10018178 | D23: =SUMPRODUCT(D5:D20,D29:D44) -> 10433240 | E23: =SUMPRODUCT(E5:E20,E29:E44) -> 10806025 | F23: =SUMPRODUCT(F5:F20,F29:F44) -> 11170544
A24: Tuition index (FY27 = 1.000) | B24: =B23/$B$23 -> 1 | C24: =C23/$B$23 -> 1.0754776 | D24: =D23/$B$23 -> 1.1200357 | E24: =E23/$B$23 -> 1.1600551 | F24: =F23/$B$23 -> 1.1991872
A25: Average rate per student | B25: =B23/B21 -> 16005.32 | C25: =C23/C21 -> 16951.231 | D25: =D23/D21 -> 17743.606 | E25: =E23/E21 -> 18535.206 | F25: =F23/F21 -> 19292.822
A27: Tuition rate by grade (before discounts)
A28: Grade | B28: =Inputs!C$4 -> FY27 | C28: =Inputs!D$4 -> FY28 | D28: =Inputs!E$4 -> FY29 | E28: =Inputs!F$4 -> FY30 | F28: =Inputs!G$4 -> FY31
A29: K-3 (5 day) | B29: 8958.56 | C29: =B29*(1+Inputs!D$9) -> 9406.488 | D29: =C29*(1+Inputs!E$9) -> 9829.78 | E29: =D29*(1+Inputs!F$9) -> 10272.12 | F29: =E29*(1+Inputs!G$9) -> 10683.005
A30: K-3 (3 day) (rate not in old model - enter) | B30: 5400 | C30: =B30*(1+Inputs!D$9) -> 5670 | D30: =C30*(1+Inputs!E$9) -> 5925.15 | E30: =D30*(1+Inputs!F$9) -> 6191.7818 | F30: =E30*(1+Inputs!G$9) -> 6439.453
A31: K-4 | B31: 10510.24 | C31: =B31*(1+Inputs!D$9) -> 11035.752 | D31: =C31*(1+Inputs!E$9) -> 11532.361 | E31: =D31*(1+Inputs!F$9) -> 12051.317 | F31: =E31*(1+Inputs!G$9) -> 12533.37
A32: K5 | B32: 13198.64 | C32: =B32*(1+Inputs!D$9) -> 13858.572 | D32: =C32*(1+Inputs!E$9) -> 14482.208 | E32: =D32*(1+Inputs!F$9) -> 15133.907 | F32: =E32*(1+Inputs!G$9) -> 15739.263
A33: 1st | B33: 15895.36 | C33: =B33*(1+Inputs!D$9) -> 16690.128 | D33: =C33*(1+Inputs!E$9) -> 17441.184 | E33: =D33*(1+Inputs!F$9) -> 18226.037 | F33: =E33*(1+Inputs!G$9) -> 18955.079
A34: 2nd | B34: 15895.36 | C34: =B34*(1+Inputs!D$9) -> 16690.128 | D34: =C34*(1+Inputs!E$9) -> 17441.184 | E34: =D34*(1+Inputs!F$9) -> 18226.037 | F34: =E34*(1+Inputs!G$9) -> 18955.079
A35: 3rd | B35: 15895.36 | C35: =B35*(1+Inputs!D$9) -> 16690.128 | D35: =C35*(1+Inputs!E$9) -> 17441.184 | E35: =D35*(1+Inputs!F$9) -> 18226.037 | F35: =E35*(1+Inputs!G$9) -> 18955.079
A36: 4th | B36: 16672.24 | C36: =B36*(1+Inputs!D$9) -> 17505.852 | D36: =C36*(1+Inputs!E$9) -> 18293.615 | E36: =D36*(1+Inputs!F$9) -> 19116.828 | F36: =E36*(1+Inputs!G$9) -> 19881.501
A37: 5th | B37: 16672.24 | C37: =B37*(1+Inputs!D$9) -> 17505.852 | D37: =C37*(1+Inputs!E$9) -> 18293.615 | E37: =D37*(1+Inputs!F$9) -> 19116.828 | F37: =E37*(1+Inputs!G$9) -> 19881.501
A38: 6th | B38: 17899.44 | C38: =B38*(1+Inputs!D$9) -> 18794.412 | D38: =C38*(1+Inputs!E$9) -> 19640.161 | E38: =D38*(1+Inputs!F$9) -> 20523.968 | F38: =E38*(1+Inputs!G$9) -> 21344.926
A39: 7th | B39: 17899.44 | C39: =B39*(1+Inputs!D$9) -> 18794.412 | D39: =C39*(1+Inputs!E$9) -> 19640.161 | E39: =D39*(1+Inputs!F$9) -> 20523.968 | F39: =E39*(1+Inputs!G$9) -> 21344.926
A40: 8th | B40: 17899.44 | C40: =B40*(1+Inputs!D$9) -> 18794.412 | D40: =C40*(1+Inputs!E$9) -> 19640.161 | E40: =D40*(1+Inputs!F$9) -> 20523.968 | F40: =E40*(1+Inputs!G$9) -> 21344.926
... A44: 12th | B44: 18075.2 | C44: =B44*(1+Inputs!D$9) -> 18978.96 | D44: =C44*(1+Inputs!E$9) -> 19833.013 | E44: =D44*(1+Inputs!F$9) -> 20725.499 | F44: =E44*(1+Inputs!G$9) -> 21554.519
A47: Roll-forward assumptions
A48: Grade | B48: Retention into grade | C48: ="New students "&Inputs!D$4 -> New students FY28 | D48: ="New students "&Inputs!E$4 -> New students FY29 | E48: ="New students "&Inputs!F$4 -> New students FY30 | F48: ="New students "&Inputs!G$4 -> New students FY31
A49: K-3 (5 day) | B49: n/a | C49: 20 | D49: 20 | E49: 20 | F49: 20
A50: K-3 (3 day) | B50: n/a | C50: 4 | D50: 4 | E50: 4 | F50: 4
A51: K-4 | B51: 0.96 | C51: 13 | D51: 13 | E51: 13 | F51: 13
A52: K5 | B52: 0.96 | C52: 3 | D52: 3 | E52: 3 | F52: 3
A53: 1st | B53: 0.96 | C53: 2 | D53: 2 | E53: 2 | F53: 2
A54: 2nd | B54: 0.96 | C54: 1 | D54: 1 | E54: 1 | F54: 1
A55: 3rd | B55: 0.96 | C55: 1 | D55: 1 | E55: 1 | F55: 1
A56: 4th | B56: 0.96 | C56: 1 | D56: 1 | E56: 1 | F56: 1
A57: 5th | B57: 0.96 | C57: 1 | D57: 1 | E57: 1 | F57: 1
A58: 6th | B58: 0.96 | C58: 4 | D58: 4 | E58: 4 | F58: 4
A59: 7th | B59: 0.96 | C59: 2 | D59: 2 | E59: 2 | F59: 2
A60: 8th | B60: 0.96 | C60: 2 | D60: 2 | E60: 2 | F60: 2
A61: 9th | B61: 0.96 | C61: 4 | D61: 4 | E61: 4 | F61: 4
A62: 10th | B62: 0.96 | C62: 1 | D62: 1 | E62: 1 | F62: 1
... A64: 12th | B64: 0.96 | C64: 0 | D64: 0 | E64: 0 | F64: 0
A66: K-4 is fed by both K-3 programs. Retention is the share of the prior grade that advances; new students are additions.

Sheet Forecast Detail
A1: FORECAST DETAIL - by QuickBooks account
A2: FY27 = QuickBooks budget import. Choose a forecast method per line (column E). Use 'Manual' + columns L:O to type amounts directly.
D4: Total enrollment | G4: =Enrollment!B21 -> 582 | H4: =Enrollment!C21 -> 591 | I4: =Enrollment!D21 -> 588 | J4: =Enrollment!E21 -> 583 | K4: =Enrollment!F21 -> 579
D5: Tuition index | G5: =Enrollment!B24 -> 1 | H5: =Enrollment!C24 -> 1.0754776 | I5: =Enrollment!D24 -> 1.1200357 | J5: =Enrollment!E24 -> 1.1600551 | K5: =Enrollment!F24 -> 1.1991872
D6: Salary-method lines total | G6: =SUMIF($E$8:$E$400,"Salary",G$8:G$400) -> 5098000 | H6: =G6*(1+Inputs!D$10) -> 5250940 | I6: =H6*(1+Inputs!E$10) -> 5408468.2 | J6: =I6*(1+Inputs!F$10) -> 5570722.2 | K6: =J6*(1+Inputs!G$10) -> 5737843.9
A7: Type | B7: Major Category | C7: Key | D7: Description | E7: Method | F7: Cash Timing | G7: =Inputs!C$4 -> FY27 | H7: =Inputs!D$4 -> FY28 | I7: =Inputs!E$4 -> FY29 | J7: =Inputs!F$4 -> FY30 | K7: =Inputs!G$4 -> FY31 | L7: ="Manual "&Inputs!D$4 -> Manual FY28 | M7: ="Manual "&Inputs!E$4 -> Manual FY29 | N7: ="Manual "&Inputs!F$4 -> Manual FY30 | O7: ="Manual "&Inputs!G$4 -> Manual FY31
A8: Revenue | B8: 1 Tuition and Fees | C8: 400186 | D8: 400186 Tuition Income | E8: Tuition Index | F8: Tuition Plan | G8: =SUMIFS('QB Import'!$B$1:$B$600,'QB Import'!$H$1:$H$600,$C8,'QB Import'!$G$1:$G$600,1) -> 7858980 | H8: =IF($E8="Manual",L8,IF($E8="Flat",G8,IF($E8="Inflation",G8*(1+Inputs!D$12),IF($E8="Salary",G8*(1+Inputs!D$10),IF($E8="Benefits",G8*(1+Inputs!D$11),IF($E8="Per Student",G8*H$4/G$4*(1+Inputs!D$12),IF($E8="Enrollment",G8*H$4/G$4,IF($E8="Tuition Index",G8*H$5/G$5,IF($E8="% of Salaries",IF($G$6=0,0,$G8/$G$6*H$6),IF($E8="Debt",$G8*Inputs!D$15/12,IF($E8="Reserve Yield",Inputs!D$13*Inputs!D$16,IF($E8="Trend",IF(ISNUMBER(Trend!$Q47),Trend!$Q47,G8),G8)))))))))))) -> 8452157.2 | I8: =IF($E8="Manual",M8,IF($E8="Flat",H8,IF($E8="Inflation",H8*(1+Inputs!E$12),IF($E8="Salary",H8*(1+Inputs!E$10),IF($E8="Benefits",H8*(1+Inputs!E$11),IF($E8="Per Student",H8*I$4/H$4*(1+Inputs!E$12),IF($E8="Enrollment",H8*I$4/H$4,IF($E8="Tuition Index",H8*I$5/H$5,IF($E8="% of Salaries",IF($G$6=0,0,$G8/$G$6*I$6),IF($E8="Debt",$G8*Inputs!E$15/12,IF($E8="Reserve Yield",Inputs!E$13*Inputs!E$16,IF($E8="Trend",H8*(1+Inputs!E$12),H8)))))))))))) -> 8802338.1 | J8: =IF($E8="Manual",N8,IF($E8="Flat",I8,IF($E8="Inflation",I8*(1+Inputs!F$12),IF($E8="Salary",I8*(1+Inputs!F$10),IF($E8="Benefits",I8*(1+Inputs!F$11),IF($E8="Per Student",I8*J$4/I$4*(1+Inputs!F$12),IF($E8="Enrollment",I8*J$4/I$4,IF($E8="Tuition Index",I8*J$5/I$5,IF($E8="% of Salaries",IF($G$6=0,0,$G8/$G$6*J$6),IF($E8="Debt",$G8*Inputs!F$15/12,IF($E8="Reserve Yield",Inputs!F$13*Inputs!F$16,IF($E8="Trend",I8*(1+Inputs!F$12),I8)))))))))))) -> 9116849.9 | K8: =IF($E8="Manual",O8,IF($E8="Flat",J8,IF($E8="Inflation",J8*(1+Inputs!G$12),IF($E8="Salary",J8*(1+Inputs!G$10),IF($E8="Benefits",J8*(1+Inputs!G$11),IF($E8="Per Student",J8*K$4/J$4*(1+Inputs!G$12),IF($E8="Enrollment",J8*K$4/J$4,IF($E8="Tuition Index",J8*K$5/J$5,IF($E8="% of Salaries",IF($G$6=0,0,$G8/$G$6*K$6),IF($E8="Debt",$G8*Inputs!G$15/12,IF($E8="Reserve Yield",Inputs!G$13*Inputs!G$16,IF($E8="Trend",J8*(1+Inputs!G$12),J8)))))))))))) -> 9424388.2
A9: Revenue | B9: 1 Tuition and Fees | C9: 400187 | D9: 400187 Scholarship for Kids Tuition | E9: Manual | F9: Tuition Plan | G9: =SUMIFS('QB Import'!$B$1:$B$600,'QB Import'!$H$1:$H$600,$C9,'QB Import'!$G$1:$G$600,1) -> 410000 | H9: =IF($E9="Manual",L9,IF($E9="Flat",G9,IF($E9="Inflation",G9*(1+Inputs!D$12),IF($E9="Salary",G9*(1+Inputs!D$10),IF($E9="Benefits",G9*(1+Inputs!D$11),IF($E9="Per Student",G9*H$4/G$4*(1+Inputs!D$12),IF($E9="Enrollment",G9*H$4/G$4,IF($E9="Tuition Index",G9*H$5/G$5,IF($E9="% of Salaries",IF($G$6=0,0,$G9/$G$6*H$6),IF($E9="Debt",$G9*Inputs!D$15/12,IF($E9="Reserve Yield",Inputs!D$13*Inputs!D$16,IF($E9="Trend",IF(ISNUMBER(Trend!$Q48),Trend!$Q48,G9),G9)))))))))))) -> 380000 | I9: =IF($E9="Manual",M9,IF($E9="Flat",H9,IF($E9="Inflation",H9*(1+Inputs!E$12),IF($E9="Salary",H9*(1+Inputs!E$10),IF($E9="Benefits",H9*(1+Inputs!E$11),IF($E9="Per Student",H9*I$4/H$4*(1+Inputs!E$12),IF($E9="Enrollment",H9*I$4/H$4,IF($E9="Tuition Index",H9*I$5/H$5,IF($E9="% of Salaries",IF($G$6=0,0,$G9/$G$6*I$6),IF($E9="Debt",$G9*Inputs!E$15/12,IF($E9="Reserve Yield",Inputs!E$13*Inputs!E$16,IF($E9="Trend",H9*(1+Inputs!E$12),H9)))))))))))) -> 360000 | J9: =IF($E9="Manual",N9,IF($E9="Flat",I9,IF($E9="Inflation",I9*(1+Inputs!F$12),IF($E9="Salary",I9*(1+Inputs!F$10),IF($E9="Benefits",I9*(1+Inputs!F$11),IF($E9="Per Student",I9*J$4/I$4*(1+Inputs!F$12),IF($E9="Enrollment",I9*J$4/I$4,IF($E9="Tuition Index",I9*J$5/I$5,IF($E9="% of Salaries",IF($G$6=0,0,$G9/$G$6*J$6),IF($E9="Debt",$G9*Inputs!F$15/12,IF($E9="Reserve Yield",Inputs!F$13*Inputs!F$16,IF($E9="Trend",I9*(1+Inputs!F$12),I9)))))))))))) -> 360000 | K9: =IF($E9="Manual",O9,IF($E9="Flat",J9,IF($E9="Inflation",J9*(1+Inputs!G$12),IF($E9="Salary",J9*(1+Inputs!G$10),IF($E9="Benefits",J9*(1+Inputs!G$11),IF($E9="Per Student",J9*K$4/J$4*(1+Inputs!G$12),IF($E9="Enrollment",J9*K$4/J$4,IF($E9="Tuition Index",J9*K$5/J$5,IF($E9="% of Salaries",IF($G$6=0,0,$G9/$G$6*K$6),IF($E9="Debt",$G9*Inputs!G$15/12,IF($E9="Reserve Yield",Inputs!G$13*Inputs!G$16,IF($E9="Trend",J9*(1+Inputs!G$12),J9)))))))))))) -> 360000 | L9: 380000 | M9: 360000 | N9: 360000 | O9: 360000
A10: Revenue | B10: 1 Tuition and Fees | C10: 400188 | D10: 400188 Choose Act Tuition | E10: Flat | F10: Tuition Plan | G10: =SUMIFS('QB Import'!$B$1:$B$600,'QB Import'!$H$1:$H$600,$C10,'QB Import'!$G$1:$G$600,1) -> 616000 | H10: =IF($E10="Manual",L10,IF($E10="Flat",G10,IF($E10="Inflation",G10*(1+Inputs!D$12),IF($E10="Salary",G10*(1+Inputs!D$10),IF($E10="Benefits",G10*(1+Inputs!D$11),IF($E10="Per Student",G10*H$4/G$4*(1+Inputs!D$12),IF($E10="Enrollment",G10*H$4/G$4,IF($E10="Tuition Index",G10*H$5/G$5,IF($E10="% of Salaries",IF($G$6=0,0,$G10/$G$6*H$6),IF($E10="Debt",$G10*Inputs!D$15/12,IF($E10="Reserve Yield",Inputs!D$13*Inputs!D$16,IF($E10="Trend",IF(ISNUMBER(Trend!$Q49),Trend!$Q49,G10),G10)))))))))))) -> 616000 | I10: =IF($E10="Manual",M10,IF($E10="Flat",H10,IF($E10="Inflation",H10*(1+Inputs!E$12),IF($E10="Salary",H10*(1+Inputs!E$10),IF($E10="Benefits",H10*(1+Inputs!E$11),IF($E10="Per Student",H10*I$4/H$4*(1+Inputs!E$12),IF($E10="Enrollment",H10*I$4/H$4,IF($E10="Tuition Index",H10*I$5/H$5,IF($E10="% of Salaries",IF($G$6=0,0,$G10/$G$6*I$6),IF($E10="Debt",$G10*Inputs!E$15/12,IF($E10="Reserve Yield",Inputs!E$13*Inputs!E$16,IF($E10="Trend",H10*(1+Inputs!E$12),H10)))))))))))) -> 616000 | J10: =IF($E10="Manual",N10,IF($E10="Flat",I10,IF($E10="Inflation",I10*(1+Inputs!F$12),IF($E10="Salary",I10*(1+Inputs!F$10),IF($E10="Benefits",I10*(1+Inputs!F$11),IF($E10="Per Student",I10*J$4/I$4*(1+Inputs!F$12),IF($E10="Enrollment",I10*J$4/I$4,IF($E10="Tuition Index",I10*J$5/I$5,IF($E10="% of Salaries",IF($G$6=0,0,$G10/$G$6*J$6),IF($E10="Debt",$G10*Inputs!F$15/12,IF($E10="Reserve Yield",Inputs!F$13*Inputs!F$16,IF($E10="Trend",I10*(1+Inputs!F$12),I10)))))))))))) -> 616000 | K10: =IF($E10="Manual",O10,IF($E10="Flat",J10,IF($E10="Inflation",J10*(1+Inputs!G$12),IF($E10="Salary",J10*(1+Inputs!G$10),IF($E10="Benefits",J10*(1+Inputs!G$11),IF($E10="Per Student",J10*K$4/J$4*(1+Inputs!G$12),IF($E10="Enrollment",J10*K$4/J$4,IF($E10="Tuition Index",J10*K$5/J$5,IF($E10="% of Salaries",IF($G$6=0,0,$G10/$G$6*K$6),IF($E10="Debt",$G10*Inputs!G$15/12,IF($E10="Reserve Yield",Inputs!G$13*Inputs!G$16,IF($E10="Trend",J10*(1+Inputs!G$12),J10)))))))))))) -> 616000
A11: Revenue | B11: 1 Tuition and Fees | C11: 400189 | D11: 400189 AOSF Tuition | E11: Flat | F11: Tuition Plan | G11: =SUMIFS('QB Import'!$B$1:$B$600,'QB Import'!$H$1:$H$600,$C11,'QB Import'!$G$1:$G$600,1) -> 0 | H11: =IF($E11="Manual",L11,IF($E11="Flat",G11,IF($E11="Inflation",G11*(1+Inputs!D$12),IF($E11="Salary",G11*(1+Inputs!D$10),IF($E11="Benefits",G11*(1+Inputs!D$11),IF($E11="Per Student",G11*H$4/G$4*(1+Inputs!D$12),IF($E11="Enrollment",G11*H$4/G$4,IF($E11="Tuition Index",G11*H$5/G$5,IF($E11="% of Salaries",IF($G$6=0,0,$G11/$G$6*H$6),IF($E11="Debt",$G11*Inputs!D$15/12,IF($E11="Reserve Yield",Inputs!D$13*Inputs!D$16,IF($E11="Trend",IF(ISNUMBER(Trend!$Q50),Trend!$Q50,G11),G11)))))))))))) -> 0 | I11: =IF($E11="Manual",M11,IF($E11="Flat",H11,IF($E11="Inflation",H11*(1+Inputs!E$12),IF($E11="Salary",H11*(1+Inputs!E$10),IF($E11="Benefits",H11*(1+Inputs!E$11),IF($E11="Per Student",H11*I$4/H$4*(1+Inputs!E$12),IF($E11="Enrollment",H11*I$4/H$4,IF($E11="Tuition Index",H11*I$5/H$5,IF($E11="% of Salaries",IF($G$6=0,0,$G11/$G$6*I$6),IF($E11="Debt",$G11*Inputs!E$15/12,IF($E11="Reserve Yield",Inputs!E$13*Inputs!E$16,IF($E11="Trend",H11*(1+Inputs!E$12),H11)))))))))))) -> 0 | J11: =IF($E11="Manual",N11,IF($E11="Flat",I11,IF($E11="Inflation",I11*(1+Inputs!F$12),IF($E11="Salary",I11*(1+Inputs!F$10),IF($E11="Benefits",I11*(1+Inputs!F$11),IF($E11="Per Student",I11*J$4/I$4*(1+Inputs!F$12),IF($E11="Enrollment",I11*J$4/I$4,IF($E11="Tuition Index",I11*J$5/I$5,IF($E11="% of Salaries",IF($G$6=0,0,$G11/$G$6*J$6),IF($E11="Debt",$G11*Inputs!F$15/12,IF($E11="Reserve Yield",Inputs!F$13*Inputs!F$16,IF($E11="Trend",I11*(1+Inputs!F$12),I11)))))))))))) -> 0 | K11: =IF($E11="Manual",O11,IF($E11="Flat",J11,IF($E11="Inflation",J11*(1+Inputs!G$12),IF($E11="Salary",J11*(1+Inputs!G$10),IF($E11="Benefits",J11*(1+Inputs!G$11),IF($E11="Per Student",J11*K$4/J$4*(1+Inputs!G$12),IF($E11="Enrollment",J11*K$4/J$4,IF($E11="Tuition Index",J11*K$5/J$5,IF($E11="% of Salaries",IF($G$6=0,0,$G11/$G$6*K$6),IF($E11="Debt",$G11*Inputs!G$15/12,IF($E11="Reserve Yield",Inputs!G$13*Inputs!G$16,IF($E11="Trend",J11*(1+Inputs!G$12),J11)))))))))))) -> 0
A12: Revenue | B12: 1 Tuition and Fees | C12: 400180 | D12: 400180 Building Fees | E12: Manual | F12: Jul Lump | G12: =SUMIFS('QB Import'!$B$1:$B$600,'QB Import'!$H$1:$H$600,$C12,'QB Import'!$G$1:$G$600,1) -> 35000 | H12: =IF($E12="Manual",L12,IF($E12="Flat",G12,IF($E12="Inflation",G12*(1+Inputs!D$12),IF($E12="Salary",G12*(1+Inputs!D$10),IF($E12="Benefits",G12*(1+Inputs!D$11),IF($E12="Per Student",G12*H$4/G$4*(1+Inputs!D$12),IF($E12="Enrollment",G12*H$4/G$4,IF($E12="Tuition Index",G12*H$5/G$5,IF($E12="% of Salaries",IF($G$6=0,0,$G12/$G$6*H$6),IF($E12="Debt",$G12*Inputs!D$15/12,IF($E12="Reserve Yield",Inputs!D$13*Inputs!D$16,IF($E12="Trend",IF(ISNUMBER(Trend!$Q51),Trend!$Q51,G12),G12)))))))))))) -> 0 | I12: =IF($E12="Manual",M12,IF($E12="Flat",H12,IF($E12="Inflation",H12*(1+Inputs!E$12),IF($E12="Salary",H12*(1+Inputs!E$10),IF($E12="Benefits",H12*(1+Inputs!E$11),IF($E12="Per Student",H12*I$4/H$4*(1+Inputs!E$12),IF($E12="Enrollment",H12*I$4/H$4,IF($E12="Tuition Index",H12*I$5/H$5,IF($E12="% of Salaries",IF($G$6=0,0,$G12/$G$6*I$6),IF($E12="Debt",$G12*Inputs!E$15/12,IF($E12="Reserve Yield",Inputs!E$13*Inputs!E$16,IF($E12="Trend",H12*(1+Inputs!E$12),H12)))))))))))) -> 0 | J12: =IF($E12="Manual",N12,IF($E12="Flat",I12,IF($E12="Inflation",I12*(1+Inputs!F$12),IF($E12="Salary",I12*(1+Inputs!F$10),IF($E12="Benefits",I12*(1+Inputs!F$11),IF($E12="Per Student",I12*J$4/I$4*(1+Inputs!F$12),IF($E12="Enrollment",I12*J$4/I$4,IF($E12="Tuition Index",I12*J$5/I$5,IF($E12="% of Salaries",IF($G$6=0,0,$G12/$G$6*J$6),IF($E12="Debt",$G12*Inputs!F$15/12,IF($E12="Reserve Yield",Inputs!F$13*Inputs!F$16,IF($E12="Trend",I12*(1+Inputs!F$12),I12)))))))))))) -> 0 | K12: =IF($E12="Manual",O12,IF($E12="Flat",J12,IF($E12="Inflation",J12*(1+Inputs!G$12),IF($E12="Salary",J12*(1+Inputs!G$10),IF($E12="Benefits",J12*(1+Inputs!G$11),IF($E12="Per Student",J12*K$4/J$4*(1+Inputs!G$12),IF($E12="Enrollment",J12*K$4/J$4,IF($E12="Tuition Index",J12*K$5/J$5,IF($E12="% of Salaries",IF($G$6=0,0,$G12/$G$6*K$6),IF($E12="Debt",$G12*Inputs!G$15/12,IF($E12="Reserve Yield",Inputs!G$13*Inputs!G$16,IF($E12="Trend",J12*(1+Inputs!G$12),J12)))))))))))) -> 0 | L12: 0 | M12: 0 | N12: 0 | O12: 0
A13: Revenue | B13: 1 Tuition and Fees | C13: 400181 | D13: 400181 Enrollment Fees | E13: Enrollment | F13: Jul Lump | G13: =SUMIFS('QB Import'!$B$1:$B$600,'QB Import'!$H$1:$H$600,$C13,'QB Import'!$G$1:$G$600,1) -> 162300 | H13: =IF($E13="Manual",L13,IF($E13="Flat",G13,IF($E13="Inflation",G13*(1+Inputs!D$12),IF($E13="Salary",G13*(1+Inputs!D$10),IF($E13="Benefits",G13*(1+Inputs!D$11),IF($E13="Per Student",G13*H$4/G$4*(1+Inputs!D$12),IF($E13="Enrollment",G13*H$4/G$4,IF($E13="Tuition Index",G13*H$5/G$5,IF($E13="% of Salaries",IF($G$6=0,0,$G13/$G$6*H$6),IF($E13="Debt",$G13*Inputs!D$15/12,IF($E13="Reserve Yield",Inputs!D$13*Inputs!D$16,IF($E13="Trend",IF(ISNUMBER(Trend!$Q52),Trend!$Q52,G13),G13)))))))))))) -> 164809.79 | I13: =IF($E13="Manual",M13,IF($E13="Flat",H13,IF($E13="Inflation",H13*(1+Inputs!E$12),IF($E13="Salary",H13*(1+Inputs!E$10),IF($E13="Benefits",H13*(1+Inputs!E$11),IF($E13="Per Student",H13*I$4/H$4*(1+Inputs!E$12),IF($E13="Enrollment",H13*I$4/H$4,IF($E13="Tuition Index",H13*I$5/H$5,IF($E13="% of Salaries",IF($G$6=0,0,$G13/$G$6*I$6),IF($E13="Debt",$G13*Inputs!E$15/12,IF($E13="Reserve Yield",Inputs!E$13*Inputs!E$16,IF($E13="Trend",H13*(1+Inputs!E$12),H13)))))))))))) -> 163973.2 | J13: =IF($E13="Manual",N13,IF($E13="Flat",I13,IF($E13="Inflation",I13*(1+Inputs!F$12),IF($E13="Salary",I13*(1+Inputs!F$10),IF($E13="Benefits",I13*(1+Inputs!F$11),IF($E13="Per Student",I13*J$4/I$4*(1+Inputs!F$12),IF($E13="Enrollment",I13*J$4/I$4,IF($E13="Tuition Index",I13*J$5/I$5,IF($E13="% of Salaries",IF($G$6=0,0,$G13/$G$6*J$6),IF($E13="Debt",$G13*Inputs!F$15/12,IF($E13="Reserve Yield",Inputs!F$13*Inputs!F$16,IF($E13="Trend",I13*(1+Inputs!F$12),I13)))))))))))) -> 162578.87 | K13: =IF($E13="Manual",O13,IF($E13="Flat",J13,IF($E13="Inflation",J13*(1+Inputs!G$12),IF($E13="Salary",J13*(1+Inputs!G$10),IF($E13="Benefits",J13*(1+Inputs!G$11),IF($E13="Per Student",J13*K$4/J$4*(1+Inputs!G$12),IF($E13="Enrollment",J13*K$4/J$4,IF($E13="Tuition Index",J13*K$5/J$5,IF($E13="% of Salaries",IF($G$6=0,0,$G13/$G$6*K$6),IF($E13="Debt",$G13*Inputs!G$15/12,IF($E13="Reserve Yield",Inputs!G$13*Inputs!G$16,IF($E13="Trend",J13*(1+Inputs!G$12),J13)))))))))))) -> 161463.4
A14: Revenue | B14: 1 Tuition and Fees | C14: 400183 | D14: 400183 Tuition Insurance Income | E14: Enrollment | F14: Tuition Plan | G14: =SUMIFS('QB Import'!$B$1:$B$600,'QB Import'!$H$1:$H$600,$C14,'QB Import'!$G$1:$G$600,1) -> 139000 | H14: =IF($E14="Manual",L14,IF($E14="Flat",G14,IF($E14="Inflation",G14*(1+Inputs!D$12),IF($E14="Salary",G14*(1+Inputs!D$10),IF($E14="Benefits",G14*(1+Inputs!D$11),IF($E14="Per Student",G14*H$4/G$4*(1+Inputs!D$12),IF($E14="Enrollment",G14*H$4/G$4,IF($E14="Tuition Index",G14*H$5/G$5,IF($E14="% of Salaries",IF($G$6=0,0,$G14/$G$6*H$6),IF($E14="Debt",$G14*Inputs!D$15/12,IF($E14="Reserve Yield",Inputs!D$13*Inputs!D$16,IF($E14="Trend",IF(ISNUMBER(Trend!$Q53),Trend!$Q53,G14),G14)))))))))))) -> 141149.48 | I14: =IF($E14="Manual",M14,IF($E14="Flat",H14,IF($E14="Inflation",H14*(1+Inputs!E$12),IF($E14="Salary",H14*(1+Inputs!E$10),IF($E14="Benefits",H14*(1+Inputs!E$11),IF($E14="Per Student",H14*I$4/H$4*(1+Inputs!E$12),IF($E14="Enrollment",H14*I$4/H$4,IF($E14="Tuition Index",H14*I$5/H$5,IF($E14="% of Salaries",IF($G$6=0,0,$G14/$G$6*I$6),IF($E14="Debt",$G14*Inputs!E$15/12,IF($E14="Reserve Yield",Inputs!E$13*Inputs!E$16,IF($E14="Trend",H14*(1+Inputs!E$12),H14)))))))))))) -> 140432.99 | J14: =IF($E14="Manual",N14,IF($E14="Flat",I14,IF($E14="Inflation",I14*(1+Inputs!F$12),IF($E14="Salary",I14*(1+Inputs!F$10),IF($E14="Benefits",I14*(1+Inputs!F$11),IF($E14="Per Student",I14*J$4/I$4*(1+Inputs!F$12),IF($E14="Enrollment",I14*J$4/I$4,IF($E14="Tuition Index",I14*J$5/I$5,IF($E14="% of Salaries",IF($G$6=0,0,$G14/$G$6*J$6),IF($E14="Debt",$G14*Inputs!F$15/12,IF($E14="Reserve Yield",Inputs!F$13*Inputs!F$16,IF($E14="Trend",I14*(1+Inputs!F$12),I14)))))))))))) -> 139238.83 | K14: =IF($E14="Manual",O14,IF($E14="Flat",J14,IF($E14="Inflation",J14*(1+Inputs!G$12),IF($E14="Salary",J14*(1+Inputs!G$10),IF($E14="Benefits",J14*(1+Inputs!G$11),IF($E14="Per Student",J14*K$4/J$4*(1+Inputs!G$12),IF($E14="Enrollment",J14*K$4/J$4,IF($E14="Tuition Index",J14*K$5/J$5,IF($E14="% of Salaries",IF($G$6=0,0,$G14/$G$6*K$6),IF($E14="Debt",$G14*Inputs!G$15/12,IF($E14="Reserve Yield",Inputs!G$13*Inputs!G$16,IF($E14="Trend",J14*(1+Inputs!G$12),J14)))))))))))) -> 138283.51
A15: Revenue | B15: 1 Tuition and Fees | C15: 400184 | D15: 400184 Application Fees | E15: Flat | F15: Jul Lump | G15: =SUMIFS('QB Import'!$B$1:$B$600,'QB Import'!$H$1:$H$600,$C15,'QB Import'!$G$1:$G$600,1) -> 0 | H15: =IF($E15="Manual",L15,IF($E15="Flat",G15,IF($E15="Inflation",G15*(1+Inputs!D$12),IF($E15="Salary",G15*(1+Inputs!D$10),IF($E15="Benefits",G15*(1+Inputs!D$11),IF($E15="Per Student",G15*H$4/G$4*(1+Inputs!D$12),IF($E15="Enrollment",G15*H$4/G$4,IF($E15="Tuition Index",G15*H$5/G$5,IF($E15="% of Salaries",IF($G$6=0,0,$G15/$G$6*H$6),IF($E15="Debt",$G15*Inputs!D$15/12,IF($E15="Reserve Yield",Inputs!D$13*Inputs!D$16,IF($E15="Trend",IF(ISNUMBER(Trend!$Q54),Trend!$Q54,G15),G15)))))))))))) -> 0 | I15: =IF($E15="Manual",M15,IF($E15="Flat",H15,IF($E15="Inflation",H15*(1+Inputs!E$12),IF($E15="Salary",H15*(1+Inputs!E$10),IF($E15="Benefits",H15*(1+Inputs!E$11),IF($E15="Per Student",H15*I$4/H$4*(1+Inputs!E$12),IF($E15="Enrollment",H15*I$4/H$4,IF($E15="Tuition Index",H15*I$5/H$5,IF($E15="% of Salaries",IF($G$6=0,0,$G15/$G$6*I$6),IF($E15="Debt",$G15*Inputs!E$15/12,IF($E15="Reserve Yield",Inputs!E$13*Inputs!E$16,IF($E15="Trend",H15*(1+Inputs!E$12),H15)))))))))))) -> 0 | J15: =IF($E15="Manual",N15,IF($E15="Flat",I15,IF($E15="Inflation",I15*(1+Inputs!F$12),IF($E15="Salary",I15*(1+Inputs!F$10),IF($E15="Benefits",I15*(1+Inputs!F$11),IF($E15="Per Student",I15*J$4/I$4*(1+Inputs!F$12),IF($E15="Enrollment",I15*J$4/I$4,IF($E15="Tuition Index",I15*J$5/I$5,IF($E15="% of Salaries",IF($G$6=0,0,$G15/$G$6*J$6),IF($E15="Debt",$G15*Inputs!F$15/12,IF($E15="Reserve Yield",Inputs!F$13*Inputs!F$16,IF($E15="Trend",I15*(1+Inputs!F$12),I15)))))))))))) -> 0 | K15: =IF($E15="Manual",O15,IF($E15="Flat",J15,IF($E15="Inflation",J15*(1+Inputs!G$12),IF($E15="Salary",J15*(1+Inputs!G$10),IF($E15="Benefits",J15*(1+Inputs!G$11),IF($E15="Per Student",J15*K$4/J$4*(1+Inputs!G$12),IF($E15="Enrollment",J15*K$4/J$4,IF($E15="Tuition Index",J15*K$5/J$5,IF($E15="% of Salaries",IF($G$6=0,0,$G15/$G$6*K$6),IF($E15="Debt",$G15*Inputs!G$15/12,IF($E15="Reserve Yield",Inputs!G$13*Inputs!G$16,IF($E15="Trend",J15*(1+Inputs!G$12),J15)))))))))))) -> 0
A16: Revenue | B16: 1 Tuition and Fees | C16: 400185 | D16: 400185 Enrollment Fee Waived - Alumni Credit | E16: Flat | F16: Jul Lump | G16: =SUMIFS('QB Import'!$B$1:$B$600,'QB Import'!$H$1:$H$600,$C16,'QB Import'!$G$1:$G$600,1) -> 0 | H16: =IF($E16="Manual",L16,IF($E16="Flat",G16,IF($E16="Inflation",G16*(1+Inputs!D$12),IF($E16="Salary",G16*(1+Inputs!D$10),IF($E16="Benefits",G16*(1+Inputs!D$11),IF($E16="Per Student",G16*H$4/G$4*(1+Inputs!D$12),IF($E16="Enrollment",G16*H$4/G$4,IF($E16="Tuition Index",G16*H$5/G$5,IF($E16="% of Salaries",IF($G$6=0,0,$G16/$G$6*H$6),IF($E16="Debt",$G16*Inputs!D$15/12,IF($E16="Reserve Yield",Inputs!D$13*Inputs!D$16,IF($E16="Trend",IF(ISNUMBER(Trend!$Q55),Trend!$Q55,G16),G16)))))))))))) -> 0 | I16: =IF($E16="Manual",M16,IF($E16="Flat",H16,IF($E16="Inflation",H16*(1+Inputs!E$12),IF($E16="Salary",H16*(1+Inputs!E$10),IF($E16="Benefits",H16*(1+Inputs!E$11),IF($E16="Per Student",H16*I$4/H$4*(1+Inputs!E$12),IF($E16="Enrollment",H16*I$4/H$4,IF($E16="Tuition Index",H16*I$5/H$5,IF($E16="% of Salaries",IF($G$6=0,0,$G16/$G$6*I$6),IF($E16="Debt",$G16*Inputs!E$15/12,IF($E16="Reserve Yield",Inputs!E$13*Inputs!E$16,IF($E16="Trend",H16*(1+Inputs!E$12),H16)))))))))))) -> 0 | J16: =IF($E16="Manual",N16,IF($E16="Flat",I16,IF($E16="Inflation",I16*(1+Inputs!F$12),IF($E16="Salary",I16*(1+Inputs!F$10),IF($E16="Benefits",I16*(1+Inputs!F$11),IF($E16="Per Student",I16*J$4/I$4*(1+Inputs!F$12),IF($E16="Enrollment",I16*J$4/I$4,IF($E16="Tuition Index",I16*J$5/I$5,IF($E16="% of Salaries",IF($G$6=0,0,$G16/$G$6*J$6),IF($E16="Debt",$G16*Inputs!F$15/12,IF($E16="Reserve Yield",Inputs!F$13*Inputs!F$16,IF($E16="Trend",I16*(1+Inputs!F$12),I16)))))))))))) -> 0 | K16: =IF($E16="Manual",O16,IF($E16="Flat",J16,IF($E16="Inflation",J16*(1+Inputs!G$12),IF($E16="Salary",J16*(1+Inputs!G$10),IF($E16="Benefits",J16*(1+Inputs!G$11),IF($E16="Per Student",J16*K$4/J$4*(1+Inputs!G$12),IF($E16="Enrollment",J16*K$4/J$4,IF($E16="Tuition Index",J16*K$5/J$5,IF($E16="% of Salaries",IF($G$6=0,0,$G16/$G$6*K$6),IF($E16="Debt",$G16*Inputs!G$15/12,IF($E16="Reserve Yield",Inputs!G$13*Inputs!G$16,IF($E16="Trend",J16*(1+Inputs!G$12),J16)))))))))))) -> 0
A17: Revenue | B17: 1 Tuition and Fees | C17: 400199 | D17: 400199 Fee - Tuition Discount | E17: Flat | F17: Jul Lump | G17: =SUMIFS('QB Import'!$B$1:$B$600,'QB Import'!$H$1:$H$600,$C17,'QB Import'!$G$1:$G$600,1) -> 0 | H17: =IF($E17="Manual",L17,IF($E17="Flat",G17,IF($E17="Inflation",G17*(1+Inputs!D$12),IF($E17="Salary",G17*(1+Inputs!D$10),IF($E17="Benefits",G17*(1+Inputs!D$11),IF($E17="Per Student",G17*H$4/G$4*(1+Inputs!D$12),IF($E17="Enrollment",G17*H$4/G$4,IF($E17="Tuition Index",G17*H$5/G$5,IF($E17="% of Salaries",IF($G$6=0,0,$G17/$G$6*H$6),IF($E17="Debt",$G17*Inputs!D$15/12,IF($E17="Reserve Yield",Inputs!D$13*Inputs!D$16,IF($E17="Trend",IF(ISNUMBER(Trend!$Q56),Trend!$Q56,G17),G17)))))))))))) -> 0 | I17: =IF($E17="Manual",M17,IF($E17="Flat",H17,IF($E17="Inflation",H17*(1+Inputs!E$12),IF($E17="Salary",H17*(1+Inputs!E$10),IF($E17="Benefits",H17*(1+Inputs!E$11),IF($E17="Per Student",H17*I$4/H$4*(1+Inputs!E$12),IF($E17="Enrollment",H17*I$4/H$4,IF($E17="Tuition Index",H17*I$5/H$5,IF($E17="% of Salaries",IF($G$6=0,0,$G17/$G$6*I$6),IF($E17="Debt",$G17*Inputs!E$15/12,IF($E17="Reserve Yield",Inputs!E$13*Inputs!E$16,IF($E17="Trend",H17*(1+Inputs!E$12),H17)))))))))))) -> 0 | J17: =IF($E17="Manual",N17,IF($E17="Flat",I17,IF($E17="Inflation",I17*(1+Inputs!F$12),IF($E17="Salary",I17*(1+Inputs!F$10),IF($E17="Benefits",I17*(1+Inputs!F$11),IF($E17="Per Student",I17*J$4/I$4*(1+Inputs!F$12),IF($E17="Enrollment",I17*J$4/I$4,IF($E17="Tuition Index",I17*J$5/I$5,IF($E17="% of Salaries",IF($G$6=0,0,$G17/$G$6*J$6),IF($E17="Debt",$G17*Inputs!F$15/12,IF($E17="Reserve Yield",Inputs!F$13*Inputs!F$16,IF($E17="Trend",I17*(1+Inputs!F$12),I17)))))))))))) -> 0 | K17: =IF($E17="Manual",O17,IF($E17="Flat",J17,IF($E17="Inflation",J17*(1+Inputs!G$12),IF($E17="Salary",J17*(1+Inputs!G$10),IF($E17="Benefits",J17*(1+Inputs!G$11),IF($E17="Per Student",J17*K$4/J$4*(1+Inputs!G$12),IF($E17="Enrollment",J17*K$4/J$4,IF($E17="Tuition Index",J17*K$5/J$5,IF($E17="% of Salaries",IF($G$6=0,0,$G17/$G$6*K$6),IF($E17="Debt",$G17*Inputs!G$15/12,IF($E17="Reserve Yield",Inputs!G$13*Inputs!G$16,IF($E17="Trend",J17*(1+Inputs!G$12),J17)))))))))))) -> 0
A18: Revenue | B18: 1 Tuition and Fees | C18: 400201 | D18: 400201 Referral Fee - Tuition Discount | E18: Flat | F18: Jul Lump | G18: =SUMIFS('QB Import'!$B$1:$B$600,'QB Import'!$H$1:$H$600,$C18,'QB Import'!$G$1:$G$600,1) -> 0 | H18: =IF($E18="Manual",L18,IF($E18="Flat",G18,IF($E18="Inflation",G18*(1+Inputs!D$12),IF($E18="Salary",G18*(1+Inputs!D$10),IF($E18="Benefits",G18*(1+Inputs!D$11),IF($E18="Per Student",G18*H$4/G$4*(1+Inputs!D$12),IF($E18="Enrollment",G18*H$4/G$4,IF($E18="Tuition Index",G18*H$5/G$5,IF($E18="% of Salaries",IF($G$6=0,0,$G18/$G$6*H$6),IF($E18="Debt",$G18*Inputs!D$15/12,IF($E18="Reserve Yield",Inputs!D$13*Inputs!D$16,IF($E18="Trend",IF(ISNUMBER(Trend!$Q57),Trend!$Q57,G18),G18)))))))))))) -> 0 | I18: =IF($E18="Manual",M18,IF($E18="Flat",H18,IF($E18="Inflation",H18*(1+Inputs!E$12),IF($E18="Salary",H18*(1+Inputs!E$10),IF($E18="Benefits",H18*(1+Inputs!E$11),IF($E18="Per Student",H18*I$4/H$4*(1+Inputs!E$12),IF($E18="Enrollment",H18*I$4/H$4,IF($E18="Tuition Index",H18*I$5/H$5,IF($E18="% of Salaries",IF($G$6=0,0,$G18/$G$6*I$6),IF($E18="Debt",$G18*Inputs!E$15/12,IF($E18="Reserve Yield",Inputs!E$13*Inputs!E$16,IF($E18="Trend",H18*(1+Inputs!E$12),H18)))))))))))) -> 0 | J18: =IF($E18="Manual",N18,IF($E18="Flat",I18,IF($E18="Inflation",I18*(1+Inputs!F$12),IF($E18="Salary",I18*(1+Inputs!F$10),IF($E18="Benefits",I18*(1+Inputs!F$11),IF($E18="Per Student",I18*J$4/I$4*(1+Inputs!F$12),IF($E18="Enrollment",I18*J$4/I$4,IF($E18="Tuition Index",I18*J$5/I$5,IF($E18="% of Salaries",IF($G$6=0,0,$G18/$G$6*J$6),IF($E18="Debt",$G18*Inputs!F$15/12,IF($E18="Reserve Yield",Inputs!F$13*Inputs!F$16,IF($E18="Trend",I18*(1+Inputs!F$12),I18)))))))))))) -> 0 | K18: =IF($E18="Manual",O18,IF($E18="Flat",J18,IF($E18="Inflation",J18*(1+Inputs!G$12),IF($E18="Salary",J18*(1+Inputs!G$10),IF($E18="Benefits",J18*(1+Inputs!G$11),IF($E18="Per Student",J18*K$4/J$4*(1+Inputs!G$12),IF($E18="Enrollment",J18*K$4/J$4,IF($E18="Tuition Index",J18*K$5/J$5,IF($E18="% of Salaries",IF($G$6=0,0,$G18/$G$6*K$6),IF($E18="Debt",$G18*Inputs!G$15/12,IF($E18="Reserve Yield",Inputs!G$13*Inputs!G$16,IF($E18="Trend",J18*(1+Inputs!G$12),J18)))))))))))) -> 0
A19: Revenue | B19: 1 Tuition and Fees | C19: 400126 | D19: 400126 Late Fees | E19: Manual | F19: Even | G19: =SUMIFS('QB Import'!$B$1:$B$600,'QB Import'!$H$1:$H$600,$C19,'QB Import'!$G$1:$G$600,1) -> 9300 | H19: =IF($E19="Manual",L19,IF($E19="Flat",G19,IF($E19="Inflation",G19*(1+Inputs!D$12),IF($E19="Salary",G19*(1+Inputs!D$10),IF($E19="Benefits",G19*(1+Inputs!D$11),IF($E19="Per Student",G19*H$4/G$4*(1+Inputs!D$12),IF($E19="Enrollment",G19*H$4/G$4,IF($E19="Tuition Index",G19*H$5/G$5,IF($E19="% of Salaries",IF($G$6=0,0,$G19/$G$6*H$6),IF($E19="Debt",$G19*Inputs!D$15/12,IF($E19="Reserve Yield",Inputs!D$13*Inputs!D$16,IF($E19="Trend",IF(ISNUMBER(Trend!$Q58),Trend!$Q58,G19),G19)))))))))))) -> 3000 | I19: =IF($E19="Manual",M19,IF($E19="Flat",H19,IF($E19="Inflation",H19*(1+Inputs!E$12),IF($E19="Salary",H19*(1+Inputs!E$10),IF($E19="Benefits",H19*(1+Inputs!E$11),IF($E19="Per Student",H19*I$4/H$4*(1+Inputs!E$12),IF($E19="Enrollment",H19*I$4/H$4,IF($E19="Tuition Index",H19*I$5/H$5,IF($E19="% of Salaries",IF($G$6=0,0,$G19/$G$6*I$6),IF($E19="Debt",$G19*Inputs!E$15/12,IF($E19="Reserve Yield",Inputs!E$13*Inputs!E$16,IF($E19="Trend",H19*(1+Inputs!E$12),H19)))))))))))) -> 3000 | J19: =IF($E19="Manual",N19,IF($E19="Flat",I19,IF($E19="Inflation",I19*(1+Inputs!F$12),IF($E19="Salary",I19*(1+Inputs!F$10),IF($E19="Benefits",I19*(1+Inputs!F$11),IF($E19="Per Student",I19*J$4/I$4*(1+Inputs!F$12),IF($E19="Enrollment",I19*J$4/I$4,IF($E19="Tuition Index",I19*J$5/I$5,IF($E19="% of Salaries",IF($G$6=0,0,$G19/$G$6*J$6),IF($E19="Debt",$G19*Inputs!F$15/12,IF($E19="Reserve Yield",Inputs!F$13*Inputs!F$16,IF($E19="Trend",I19*(1+Inputs!F$12),I19)))))))))))) -> 3000 | K19: =IF($E19="Manual",O19,IF($E19="Flat",J19,IF($E19="Inflation",J19*(1+Inputs!G$12),IF($E19="Salary",J19*(1+Inputs!G$10),IF($E19="Benefits",J19*(1+Inputs!G$11),IF($E19="Per Student",J19*K$4/J$4*(1+Inputs!G$12),IF($E19="Enrollment",J19*K$4/J$4,IF($E19="Tuition Index",J19*K$5/J$5,IF($E19="% of Salaries",IF($G$6=0,0,$G19/$G$6*K$6),IF($E19="Debt",$G19*Inputs!G$15/12,IF($E19="Reserve Yield",Inputs!G$13*Inputs!G$16,IF($E19="Trend",J19*(1+Inputs!G$12),J19)))))))))))) -> 3000 | L19: 3000 | M19: 3000 | N19: 3000 | O19: 3000
A20: Revenue | B20: 1 Tuition and Fees | C20: 400127 | D20: 400127 Waived Late Fees | E20: Flat | F20: Even | G20: =SUMIFS('QB Import'!$B$1:$B$600,'QB Import'!$H$1:$H$600,$C20,'QB Import'!$G$1:$G$600,1) -> 0 | H20: =IF($E20="Manual",L20,IF($E20="Flat",G20,IF($E20="Inflation",G20*(1+Inputs!D$12),IF($E20="Salary",G20*(1+Inputs!D$10),IF($E20="Benefits",G20*(1+Inputs!D$11),IF($E20="Per Student",G20*H$4/G$4*(1+Inputs!D$12),IF($E20="Enrollment",G20*H$4/G$4,IF($E20="Tuition Index",G20*H$5/G$5,IF($E20="% of Salaries",IF($G$6=0,0,$G20/$G$6*H$6),IF($E20="Debt",$G20*Inputs!D$15/12,IF($E20="Reserve Yield",Inputs!D$13*Inputs!D$16,IF($E20="Trend",IF(ISNUMBER(Trend!$Q59),Trend!$Q59,G20),G20)))))))))))) -> 0 | I20: =IF($E20="Manual",M20,IF($E20="Flat",H20,IF($E20="Inflation",H20*(1+Inputs!E$12),IF($E20="Salary",H20*(1+Inputs!E$10),IF($E20="Benefits",H20*(1+Inputs!E$11),IF($E20="Per Student",H20*I$4/H$4*(1+Inputs!E$12),IF($E20="Enrollment",H20*I$4/H$4,IF($E20="Tuition Index",H20*I$5/H$5,IF($E20="% of Salaries",IF($G$6=0,0,$G20/$G$6*I$6),IF($E20="Debt",$G20*Inputs!E$15/12,IF($E20="Reserve Yield",Inputs!E$13*Inputs!E$16,IF($E20="Trend",H20*(1+Inputs!E$12),H20)))))))))))) -> 0 | J20: =IF($E20="Manual",N20,IF($E20="Flat",I20,IF($E20="Inflation",I20*(1+Inputs!F$12),IF($E20="Salary",I20*(1+Inputs!F$10),IF($E20="Benefits",I20*(1+Inputs!F$11),IF($E20="Per Student",I20*J$4/I$4*(1+Inputs!F$12),IF($E20="Enrollment",I20*J$4/I$4,IF($E20="Tuition Index",I20*J$5/I$5,IF($E20="% of Salaries",IF($G$6=0,0,$G20/$G$6*J$6),IF($E20="Debt",$G20*Inputs!F$15/12,IF($E20="Reserve Yield",Inputs!F$13*Inputs!F$16,IF($E20="Trend",I20*(1+Inputs!F$12),I20)))))))))))) -> 0 | K20: =IF($E20="Manual",O20,IF($E20="Flat",J20,IF($E20="Inflation",J20*(1+Inputs!G$12),IF($E20="Salary",J20*(1+Inputs!G$10),IF($E20="Benefits",J20*(1+Inputs!G$11),IF($E20="Per Student",J20*K$4/J$4*(1+Inputs!G$12),IF($E20="Enrollment",J20*K$4/J$4,IF($E20="Tuition Index",J20*K$5/J$5,IF($E20="% of Salaries",IF($G$6=0,0,$G20/$G$6*K$6),IF($E20="Debt",$G20*Inputs!G$15/12,IF($E20="Reserve Yield",Inputs!G$13*Inputs!G$16,IF($E20="Trend",J20*(1+Inputs!G$12),J20)))))))))))) -> 0
A21: Revenue | B21: 1 Tuition and Fees | C21: 400128 | D21: 400128 Late Fees - Past Due Accounts | E21: Flat | F21: Even | G21: =SUMIFS('QB Import'!$B$1:$B$600,'QB Import'!$H$1:$H$600,$C21,'QB Import'!$G$1:$G$600,1) -> 0 | H21: =IF($E21="Manual",L21,IF($E21="Flat",G21,IF($E21="Inflation",G21*(1+Inputs!D$12),IF($E21="Salary",G21*(1+Inputs!D$10),IF($E21="Benefits",G21*(1+Inputs!D$11),IF($E21="Per Student",G21*H$4/G$4*(1+Inputs!D$12),IF($E21="Enrollment",G21*H$4/G$4,IF($E21="Tuition Index",G21*H$5/G$5,IF($E21="% of Salaries",IF($G$6=0,0,$G21/$G$6*H$6),IF($E21="Debt",$G21*Inputs!D$15/12,IF($E21="Reserve Yield",Inputs!D$13*Inputs!D$16,IF($E21="Trend",IF(ISNUMBER(Trend!$Q60),Trend!$Q60,G21),G21)))))))))))) -> 0 | I21: =IF($E21="Manual",M21,IF($E21="Flat",H21,IF($E21="Inflation",H21*(1+Inputs!E$12),IF($E21="Salary",H21*(1+Inputs!E$10),IF($E21="Benefits",H21*(1+Inputs!E$11),IF($E21="Per Student",H21*I$4/H$4*(1+Inputs!E$12),IF($E21="Enrollment",H21*I$4/H$4,IF($E21="Tuition Index",H21*I$5/H$5,IF($E21="% of Salaries",IF($G$6=0,0,$G21/$G$6*I$6),IF($E21="Debt",$G21*Inputs!E$15/12,IF($E21="Reserve Yield",Inputs!E$13*Inputs!E$16,IF($E21="Trend",H21*(1+Inputs!E$12),H21)))))))))))) -> 0 | J21: =IF($E21="Manual",N21,IF($E21="Flat",I21,IF($E21="Inflation",I21*(1+Inputs!F$12),IF($E21="Salary",I21*(1+Inputs!F$10),IF($E21="Benefits",I21*(1+Inputs!F$11),IF($E21="Per Student",I21*J$4/I$4*(1+Inputs!F$12),IF($E21="Enrollment",I21*J$4/I$4,IF($E21="Tuition Index",I21*J$5/I$5,IF($E21="% of Salaries",IF($G$6=0,0,$G21/$G$6*J$6),IF($E21="Debt",$G21*Inputs!F$15/12,IF($E21="Reserve Yield",Inputs!F$13*Inputs!F$16,IF($E21="Trend",I21*(1+Inputs!F$12),I21)))))))))))) -> 0 | K21: =IF($E21="Manual",O21,IF($E21="Flat",J21,IF($E21="Inflation",J21*(1+Inputs!G$12),IF($E21="Salary",J21*(1+Inputs!G$10),IF($E21="Benefits",J21*(1+Inputs!G$11),IF($E21="Per Student",J21*K$4/J$4*(1+Inputs!G$12),IF($E21="Enrollment",J21*K$4/J$4,IF($E21="Tuition Index",J21*K$5/J$5,IF($E21="% of Salaries",IF($G$6=0,0,$G21/$G$6*K$6),IF($E21="Debt",$G21*Inputs!G$15/12,IF($E21="Reserve Yield",Inputs!G$13*Inputs!G$16,IF($E21="Trend",J21*(1+Inputs!G$12),J21)))))))))))) -> 0
A22: Revenue | B22: 1 Tuition and Fees | C22: 400193 | D22: 400193 Pastoral Discount | E22: Flat | F22: Tuition Plan | G22: =SUMIFS('QB Import'!$B$1:$B$600,'QB Import'!$H$1:$H$600,$C22,'QB Import'!$G$1:$G$600,1) -> -16070 | H22: =IF($E22="Manual",L22,IF($E22="Flat",G22,IF($E22="Inflation",G22*(1+Inputs!D$12),IF($E22="Salary",G22*(1+Inputs!D$10),IF($E22="Benefits",G22*(1+Inputs!D$11),IF($E22="Per Student",G22*H$4/G$4*(1+Inputs!D$12),IF($E22="Enrollment",G22*H$4/G$4,IF($E22="Tuition Index",G22*H$5/G$5,IF($E22="% of Salaries",IF($G$6=0,0,$G22/$G$6*H$6),IF($E22="Debt",$G22*Inputs!D$15/12,IF($E22="Reserve Yield",Inputs!D$13*Inputs!D$16,IF($E22="Trend",IF(ISNUMBER(Trend!$Q61),Trend!$Q61,G22),G22)))))))))))) -> -16070 | I22: =IF($E22="Manual",M22,IF($E22="Flat",H22,IF($E22="Inflation",H22*(1+Inputs!E$12),IF($E22="Salary",H22*(1+Inputs!E$10),IF($E22="Benefits",H22*(1+Inputs!E$11),IF($E22="Per Student",H22*I$4/H$4*(1+Inputs!E$12),IF($E22="Enrollment",H22*I$4/H$4,IF($E22="Tuition Index",H22*I$5/H$5,IF($E22="% of Salaries",IF($G$6=0,0,$G22/$G$6*I$6),IF($E22="Debt",$G22*Inputs!E$15/12,IF($E22="Reserve Yield",Inputs!E$13*Inputs!E$16,IF($E22="Trend",H22*(1+Inputs!E$12),H22)))))))))))) -> -16070 | J22: =IF($E22="Manual",N22,IF($E22="Flat",I22,IF($E22="Inflation",I22*(1+Inputs!F$12),IF($E22="Salary",I22*(1+Inputs!F$10),IF($E22="Benefits",I22*(1+Inputs!F$11),IF($E22="Per Student",I22*J$4/I$4*(1+Inputs!F$12),IF($E22="Enrollment",I22*J$4/I$4,IF($E22="Tuition Index",I22*J$5/I$5,IF($E22="% of Salaries",IF($G$6=0,0,$G22/$G$6*J$6),IF($E22="Debt",$G22*Inputs!F$15/12,IF($E22="Reserve Yield",Inputs!F$13*Inputs!F$16,IF($E22="Trend",I22*(1+Inputs!F$12),I22)))))))))))) -> -16070 | K22: =IF($E22="Manual",O22,IF($E22="Flat",J22,IF($E22="Inflation",J22*(1+Inputs!G$12),IF($E22="Salary",J22*(1+Inputs!G$10),IF($E22="Benefits",J22*(1+Inputs!G$11),IF($E22="Per Student",J22*K$4/J$4*(1+Inputs!G$12),IF($E22="Enrollment",J22*K$4/J$4,IF($E22="Tuition Index",J22*K$5/J$5,IF($E22="% of Salaries",IF($G$6=0,0,$G22/$G$6*K$6),IF($E22="Debt",$G22*Inputs!G$15/12,IF($E22="Reserve Yield",Inputs!G$13*Inputs!G$16,IF($E22="Trend",J22*(1+Inputs!G$12),J22)))))))))))) -> -16070
A23: Revenue | B23: 1 Tuition and Fees | C23: 400194 | D23: 400194 Grace Based Financial Assistance | E23: Manual | F23: Tuition Plan | G23: =SUMIFS('QB Import'!$B$1:$B$600,'QB Import'!$H$1:$H$600,$C23,'QB Import'!$G$1:$G$600,1) -> -300000 | H23: =IF($E23="Manual",L23,IF($E23="Flat",G23,IF($E23="Inflation",G23*(1+Inputs!D$12),IF($E23="Salary",G23*(1+Inputs!D$10),IF($E23="Benefits",G23*(1+Inputs!D$11),IF($E23="Per Student",G23*H$4/G$4*(1+Inputs!D$12),IF($E23="Enrollment",G23*H$4/G$4,IF($E23="Tuition Index",G23*H$5/G$5,IF($E23="% of Salaries",IF($G$6=0,0,$G23/$G$6*H$6),IF($E23="Debt",$G23*Inputs!D$15/12,IF($E23="Reserve Yield",Inputs!D$13*Inputs!D$16,IF($E23="Trend",IF(ISNUMBER(Trend!$Q62),Trend!$Q62,G23),G23)))))))))))) -> -325000 | I23: =IF($E23="Manual",M23,IF($E23="Flat",H23,IF($E23="Inflation",H23*(1+Inputs!E$12),IF($E23="Salary",H23*(1+Inputs!E$10),IF($E23="Benefits",H23*(1+Inputs!E$11),IF($E23="Per Student",H23*I$4/H$4*(1+Inputs!E$12),IF($E23="Enrollment",H23*I$4/H$4,IF($E23="Tuition Index",H23*I$5/H$5,IF($E23="% of Salaries",IF($G$6=0,0,$G23/$G$6*I$6),IF($E23="Debt",$G23*Inputs!E$15/12,IF($E23="Reserve Yield",Inputs!E$13*Inputs!E$16,IF($E23="Trend",H23*(1+Inputs!E$12),H23)))))))))))) -> -325000 | J23: =IF($E23="Manual",N23,IF($E23="Flat",I23,IF($E23="Inflation",I23*(1+Inputs!F$12),IF($E23="Salary",I23*(1+Inputs!F$10),IF($E23="Benefits",I23*(1+Inputs!F$11),IF($E23="Per Student",I23*J$4/I$4*(1+Inputs!F$12),IF($E23="Enrollment",I23*J$4/I$4,IF($E23="Tuition Index",I23*J$5/I$5,IF($E23="% of Salaries",IF($G$6=0,0,$G23/$G$6*J$6),IF($E23="Debt",$G23*Inputs!F$15/12,IF($E23="Reserve Yield",Inputs!F$13*Inputs!F$16,IF($E23="Trend",I23*(1+Inputs!F$12),I23)))))))))))) -> -325000 | K23: =IF($E23="Manual",O23,IF($E23="Flat",J23,IF($E23="Inflation",J23*(1+Inputs!G$12),IF($E23="Salary",J23*(1+Inputs!G$10),IF($E23="Benefits",J23*(1+Inputs!G$11),IF($E23="Per Student",J23*K$4/J$4*(1+Inputs!G$12),IF($E23="Enrollment",J23*K$4/J$4,IF($E23="Tuition Index",J23*K$5/J$5,IF($E23="% of Salaries",IF($G$6=0,0,$G23/$G$6*K$6),IF($E23="Debt",$G23*Inputs!G$15/12,IF($E23="Reserve Yield",Inputs!G$13*Inputs!G$16,IF($E23="Trend",J23*(1+Inputs!G$12),J23)))))))))))) -> -325000 | L23: -325000 | M23: -325000 | N23: -325000 | O23: -325000
A24: Revenue | B24: 1 Tuition and Fees | C24: 400195 | D24: 400195 Multi-Child Discounts | E24: Flat | F24: Tuition Plan | G24: =SUMIFS('QB Import'!$B$1:$B$600,'QB Import'!$H$1:$H$600,$C24,'QB Import'!$G$1:$G$600,1) -> -49675 | H24: =IF($E24="Manual",L24,IF($E24="Flat",G24,IF($E24="Inflation",G24*(1+Inputs!D$12),IF($E24="Salary",G24*(1+Inputs!D$10),IF($E24="Benefits",G24*(1+Inputs!D$11),IF($E24="Per Student",G24*H$4/G$4*(1+Inputs!D$12),IF($E24="Enrollment",G24*H$4/G$4,IF($E24="Tuition Index",G24*H$5/G$5,IF($E24="% of Salaries",IF($G$6=0,0,$G24/$G$6*H$6),IF($E24="Debt",$G24*Inputs!D$15/12,IF($E24="Reserve Yield",Inputs!D$13*Inputs!D$16,IF($E24="Trend",IF(ISNUMBER(Trend!$Q63),Trend!$Q63,G24),G24)))))))))))) -> -49675 | I24: =IF($E24="Manual",M24,IF($E24="Flat",H24,IF($E24="Inflation",H24*(1+Inputs!E$12),IF($E24="Salary",H24*(1+Inputs!E$10),IF($E24="Benefits",H24*(1+Inputs!E$11),IF($E24="Per Student",H24*I$4/H$4*(1+Inputs!E$12),IF($E24="Enrollment",H24*I$4/H$4,IF($E24="Tuition Index",H24*I$5/H$5,IF($E24="% of Salaries",IF($G$6=0,0,$G24/$G$6*I$6),IF($E24="Debt",$G24*Inputs!E$15/12,IF($E24="Reserve Yield",Inputs!E$13*Inputs!E$16,IF($E24="Trend",H24*(1+Inputs!E$12),H24)))))))))))) -> -49675 | J24: =IF($E24="Manual",N24,IF($E24="Flat",I24,IF($E24="Inflation",I24*(1+Inputs!F$12),IF($E24="Salary",I24*(1+Inputs!F$10),IF($E24="Benefits",I24*(1+Inputs!F$11),IF($E24="Per Student",I24*J$4/I$4*(1+Inputs!F$12),IF($E24="Enrollment",I24*J$4/I$4,IF($E24="Tuition Index",I24*J$5/I$5,IF($E24="% of Salaries",IF($G$6=0,0,$G24/$G$6*J$6),IF($E24="Debt",$G24*Inputs!F$15/12,IF($E24="Reserve Yield",Inputs!F$13*Inputs!F$16,IF($E24="Trend",I24*(1+Inputs!F$12),I24)))))))))))) -> -49675 | K24: =IF($E24="Manual",O24,IF($E24="Flat",J24,IF($E24="Inflation",J24*(1+Inputs!G$12),IF($E24="Salary",J24*(1+Inputs!G$10),IF($E24="Benefits",J24*(1+Inputs!G$11),IF($E24="Per Student",J24*K$4/J$4*(1+Inputs!G$12),IF($E24="Enrollment",J24*K$4/J$4,IF($E24="Tuition Index",J24*K$5/J$5,IF($E24="% of Salaries",IF($G$6=0,0,$G24/$G$6*K$6),IF($E24="Debt",$G24*Inputs!G$15/12,IF($E24="Reserve Yield",Inputs!G$13*Inputs!G$16,IF($E24="Trend",J24*(1+Inputs!G$12),J24)))))))))))) -> -49675
A25: Revenue | B25: 1 Tuition and Fees | C25: 400196 | D25: 400196 Military Discount | E25: Flat | F25: Tuition Plan | G25: =SUMIFS('QB Import'!$B$1:$B$600,'QB Import'!$H$1:$H$600,$C25,'QB Import'!$G$1:$G$600,1) -> -65453 | H25: =IF($E25="Manual",L25,IF($E25="Flat",G25,IF($E25="Inflation",G25*(1+Inputs!D$12),IF($E25="Salary",G25*(1+Inputs!D$10),IF($E25="Benefits",G25*(1+Inputs!D$11),IF($E25="Per Student",G25*H$4/G$4*(1+Inputs!D$12),IF($E25="Enrollment",G25*H$4/G$4,IF($E25="Tuition Index",G25*H$5/G$5,IF($E25="% of Salaries",IF($G$6=0,0,$G25/$G$6*H$6),IF($E25="Debt",$G25*Inputs!D$15/12,IF($E25="Reserve Yield",Inputs!D$13*Inputs!D$16,IF($E25="Trend",IF(ISNUMBER(Trend!$Q64),Trend!$Q64,G25),G25)))))))))))) -> -65453 | I25: =IF($E25="Manual",M25,IF($E25="Flat",H25,IF($E25="Inflation",H25*(1+Inputs!E$12),IF($E25="Salary",H25*(1+Inputs!E$10),IF($E25="Benefits",H25*(1+Inputs!E$11),IF($E25="Per Student",H25*I$4/H$4*(1+Inputs!E$12),IF($E25="Enrollment",H25*I$4/H$4,IF($E25="Tuition Index",H25*I$5/H$5,IF($E25="% of Salaries",IF($G$6=0,0,$G25/$G$6*I$6),IF($E25="Debt",$G25*Inputs!E$15/12,IF($E25="Reserve Yield",Inputs!E$13*Inputs!E$16,IF($E25="Trend",H25*(1+Inputs!E$12),H25)))))))))))) -> -65453 | J25: =IF($E25="Manual",N25,IF($E25="Flat",I25,IF($E25="Inflation",I25*(1+Inputs!F$12),IF($E25="Salary",I25*(1+Inputs!F$10),IF($E25="Benefits",I25*(1+Inputs!F$11),IF($E25="Per Student",I25*J$4/I$4*(1+Inputs!F$12),IF($E25="Enrollment",I25*J$4/I$4,IF($E25="Tuition Index",I25*J$5/I$5,IF($E25="% of Salaries",IF($G$6=0,0,$G25/$G$6*J$6),IF($E25="Debt",$G25*Inputs!F$15/12,IF($E25="Reserve Yield",Inputs!F$13*Inputs!F$16,IF($E25="Trend",I25*(1+Inputs!F$12),I25)))))))))))) -> -65453 | K25: =IF($E25="Manual",O25,IF($E25="Flat",J25,IF($E25="Inflation",J25*(1+Inputs!G$12),IF($E25="Salary",J25*(1+Inputs!G$10),IF($E25="Benefits",J25*(1+Inputs!G$11),IF($E25="Per Student",J25*K$4/J$4*(1+Inputs!G$12),IF($E25="Enrollment",J25*K$4/J$4,IF($E25="Tuition Index",J25*K$5/J$5,IF($E25="% of Salaries",IF($G$6=0,0,$G25/$G$6*K$6),IF($E25="Debt",$G25*Inputs!G$15/12,IF($E25="Reserve Yield",Inputs!G$13*Inputs!G$16,IF($E25="Trend",J25*(1+Inputs!G$12),J25)))))))))))) -> -65453
A26: Revenue | B26: 2 Interest and Other Income | C26: 400133 | D26: 400133 Cat Quest Revenue | E26: Flat | F26: Even | G26: =SUMIFS('QB Import'!$B$1:$B$600,'QB Import'!$H$1:$H$600,$C26,'QB Import'!$G$1:$G$600,1) -> 145000 | H26: =IF($E26="Manual",L26,IF($E26="Flat",G26,IF($E26="Inflation",G26*(1+Inputs!D$12),IF($E26="Salary",G26*(1+Inputs!D$10),IF($E26="Benefits",G26*(1+Inputs!D$11),IF($E26="Per Student",G26*H$4/G$4*(1+Inputs!D$12),IF($E26="Enrollment",G26*H$4/G$4,IF($E26="Tuition Index",G26*H$5/G$5,IF($E26="% of Salaries",IF($G$6=0,0,$G26/$G$6*H$6),IF($E26="Debt",$G26*Inputs!D$15/12,IF($E26="Reserve Yield",Inputs!D$13*Inputs!D$16,IF($E26="Trend",IF(ISNUMBER(Trend!$Q65),Trend!$Q65,G26),G26)))))))))))) -> 145000 | I26: =IF($E26="Manual",M26,IF($E26="Flat",H26,IF($E26="Inflation",H26*(1+Inputs!E$12),IF($E26="Salary",H26*(1+Inputs!E$10),IF($E26="Benefits",H26*(1+Inputs!E$11),IF($E26="Per Student",H26*I$4/H$4*(1+Inputs!E$12),IF($E26="Enrollment",H26*I$4/H$4,IF($E26="Tuition Index",H26*I$5/H$5,IF($E26="% of Salaries",IF($G$6=0,0,$G26/$G$6*I$6),IF($E26="Debt",$G26*Inputs!E$15/12,IF($E26="Reserve Yield",Inputs!E$13*Inputs!E$16,IF($E26="Trend",H26*(1+Inputs!E$12),H26)))))))))))) -> 145000 | J26: =IF($E26="Manual",N26,IF($E26="Flat",I26,IF($E26="Inflation",I26*(1+Inputs!F$12),IF($E26="Salary",I26*(1+Inputs!F$10),IF($E26="Benefits",I26*(1+Inputs!F$11),IF($E26="Per Student",I26*J$4/I$4*(1+Inputs!F$12),IF($E26="Enrollment",I26*J$4/I$4,IF($E26="Tuition Index",I26*J$5/I$5,IF($E26="% of Salaries",IF($G$6=0,0,$G26/$G$6*J$6),IF($E26="Debt",$G26*Inputs!F$15/12,IF($E26="Reserve Yield",Inputs!F$13*Inputs!F$16,IF($E26="Trend",I26*(1+Inputs!F$12),I26)))))))))))) -> 145000 | K26: =IF($E26="Manual",O26,IF($E26="Flat",J26,IF($E26="Inflation",J26*(1+Inputs!G$12),IF($E26="Salary",J26*(1+Inputs!G$10),IF($E26="Benefits",J26*(1+Inputs!G$11),IF($E26="Per Student",J26*K$4/J$4*(1+Inputs!G$12),IF($E26="Enrollment",J26*K$4/J$4,IF($E26="Tuition Index",J26*K$5/J$5,IF($E26="% of Salaries",IF($G$6=0,0,$G26/$G$6*K$6),IF($E26="Debt",$G26*Inputs!G$15/12,IF($E26="Reserve Yield",Inputs!G$13*Inputs!G$16,IF($E26="Trend",J26*(1+Inputs!G$12),J26)))))))))))) -> 145000
A27: Revenue | B27: 2 Interest and Other Income | C27: 400134 | D27: 400134 Summer Quest Income | E27: Flat | F27: Even | G27: =SUMIFS('QB Import'!$B$1:$B$600,'QB Import'!$H$1:$H$600,$C27,'QB Import'!$G$1:$G$600,1) -> 0 | H27: =IF($E27="Manual",L27,IF($E27="Flat",G27,IF($E27="Inflation",G27*(1+Inputs!D$12),IF($E27="Salary",G27*(1+Inputs!D$10),IF($E27="Benefits",G27*(1+Inputs!D$11),IF($E27="Per Student",G27*H$4/G$4*(1+Inputs!D$12),IF($E27="Enrollment",G27*H$4/G$4,IF($E27="Tuition Index",G27*H$5/G$5,IF($E27="% of Salaries",IF($G$6=0,0,$G27/$G$6*H$6),IF($E27="Debt",$G27*Inputs!D$15/12,IF($E27="Reserve Yield",Inputs!D$13*Inputs!D$16,IF($E27="Trend",IF(ISNUMBER(Trend!$Q66),Trend!$Q66,G27),G27)))))))))))) -> 0 | I27: =IF($E27="Manual",M27,IF($E27="Flat",H27,IF($E27="Inflation",H27*(1+Inputs!E$12),IF($E27="Salary",H27*(1+Inputs!E$10),IF($E27="Benefits",H27*(1+Inputs!E$11),IF($E27="Per Student",H27*I$4/H$4*(1+Inputs!E$12),IF($E27="Enrollment",H27*I$4/H$4,IF($E27="Tuition Index",H27*I$5/H$5,IF($E27="% of Salaries",IF($G$6=0,0,$G27/$G$6*I$6),IF($E27="Debt",$G27*Inputs!E$15/12,IF($E27="Reserve Yield",Inputs!E$13*Inputs!E$16,IF($E27="Trend",H27*(1+Inputs!E$12),H27)))))))))))) -> 0 | J27: =IF($E27="Manual",N27,IF($E27="Flat",I27,IF($E27="Inflation",I27*(1+Inputs!F$12),IF($E27="Salary",I27*(1+Inputs!F$10),IF($E27="Benefits",I27*(1+Inputs!F$11),IF($E27="Per Student",I27*J$4/I$4*(1+Inputs!F$12),IF($E27="Enrollment",I27*J$4/I$4,IF($E27="Tuition Index",I27*J$5/I$5,IF($E27="% of Salaries",IF($G$6=0,0,$G27/$G$6*J$6),IF($E27="Debt",$G27*Inputs!F$15/12,IF($E27="Reserve Yield",Inputs!F$13*Inputs!F$16,IF($E27="Trend",I27*(1+Inputs!F$12),I27)))))))))))) -> 0 | K27: =IF($E27="Manual",O27,IF($E27="Flat",J27,IF($E27="Inflation",J27*(1+Inputs!G$12),IF($E27="Salary",J27*(1+Inputs!G$10),IF($E27="Benefits",J27*(1+Inputs!G$11),IF($E27="Per Student",J27*K$4/J$4*(1+Inputs!G$12),IF($E27="Enrollment",J27*K$4/J$4,IF($E27="Tuition Index",J27*K$5/J$5,IF($E27="% of Salaries",IF($G$6=0,0,$G27/$G$6*K$6),IF($E27="Debt",$G27*Inputs!G$15/12,IF($E27="Reserve Yield",Inputs!G$13*Inputs!G$16,IF($E27="Trend",J27*(1+Inputs!G$12),J27)))))))))))) -> 0
A28: Revenue | B28: 2 Interest and Other Income | C28: 400197 | D28: 400197 Cat Quest Expenses (Contra) | E28: Flat | F28: Even | G28: =SUMIFS('QB Import'!$B$1:$B$600,'QB Import'!$H$1:$H$600,$C28,'QB Import'!$G$1:$G$600,1) -> -95000 | H28: =IF($E28="Manual",L28,IF($E28="Flat",G28,IF($E28="Inflation",G28*(1+Inputs!D$12),IF($E28="Salary",G28*(1+Inputs!D$10),IF($E28="Benefits",G28*(1+Inputs!D$11),IF($E28="Per Student",G28*H$4/G$4*(1+Inputs!D$12),IF($E28="Enrollment",G28*H$4/G$4,IF($E28="Tuition Index",G28*H$5/G$5,IF($E28="% of Salaries",IF($G$6=0,0,$G28/$G$6*H$6),IF($E28="Debt",$G28*Inputs!D$15/12,IF($E28="Reserve Yield",Inputs!D$13*Inputs!D$16,IF($E28="Trend",IF(ISNUMBER(Trend!$Q67),Trend!$Q67,G28),G28)))))))))))) -> -95000 | I28: =IF($E28="Manual",M28,IF($E28="Flat",H28,IF($E28="Inflation",H28*(1+Inputs!E$12),IF($E28="Salary",H28*(1+Inputs!E$10),IF($E28="Benefits",H28*(1+Inputs!E$11),IF($E28="Per Student",H28*I$4/H$4*(1+Inputs!E$12),IF($E28="Enrollment",H28*I$4/H$4,IF($E28="Tuition Index",H28*I$5/H$5,IF($E28="% of Salaries",IF($G$6=0,0,$G28/$G$6*I$6),IF($E28="Debt",$G28*Inputs!E$15/12,IF($E28="Reserve Yield",Inputs!E$13*Inputs!E$16,IF($E28="Trend",H28*(1+Inputs!E$12),H28)))))))))))) -> -95000 | J28: =IF($E28="Manual",N28,IF($E28="Flat",I28,IF($E28="Inflation",I28*(1+Inputs!F$12),IF($E28="Salary",I28*(1+Inputs!F$10),IF($E28="Benefits",I28*(1+Inputs!F$11),IF($E28="Per Student",I28*J$4/I$4*(1+Inputs!F$12),IF($E28="Enrollment",I28*J$4/I$4,IF($E28="Tuition Index",I28*J$5/I$5,IF($E28="% of Salaries",IF($G$6=0,0,$G28/$G$6*J$6),IF($E28="Debt",$G28*Inputs!F$15/12,IF($E28="Reserve Yield",Inputs!F$13*Inputs!F$16,IF($E28="Trend",I28*(1+Inputs!F$12),I28)))))))))))) -> -95000 | K28: =IF($E28="Manual",O28,IF($E28="Flat",J28,IF($E28="Inflation",J28*(1+Inputs!G$12),IF($E28="Salary",J28*(1+Inputs!G$10),IF($E28="Benefits",J28*(1+Inputs!G$11),IF($E28="Per Student",J28*K$4/J$4*(1+Inputs!G$12),IF($E28="Enrollment",J28*K$4/J$4,IF($E28="Tuition Index",J28*K$5/J$5,IF($E28="% of Salaries",IF($G$6=0,0,$G28/$G$6*K$6),IF($E28="Debt",$G28*Inputs!G$15/12,IF($E28="Reserve Yield",Inputs!G$13*Inputs!G$16,IF($E28="Trend",J28*(1+Inputs!G$12),J28)))))))))))) -> -95000
A29: Revenue | B29: 2 Interest and Other Income | C29: 400198 | D29: 400198 Summer Cat Quest Expenses (Contra) | E29: Flat | F29: Even | G29: =SUMIFS('QB Import'!$B$1:$B$600,'QB Import'!$H$1:$H$600,$C29,'QB Import'!$G$1:$G$600,1) -> 0 | H29: =IF($E29="Manual",L29,IF($E29="Flat",G29,IF($E29="Inflation",G29*(1+Inputs!D$12),IF($E29="Salary",G29*(1+Inputs!D$10),IF($E29="Benefits",G29*(1+Inputs!D$11),IF($E29="Per Student",G29*H$4/G$4*(1+Inputs!D$12),IF($E29="Enrollment",G29*H$4/G$4,IF($E29="Tuition Index",G29*H$5/G$5,IF($E29="% of Salaries",IF($G$6=0,0,$G29/$G$6*H$6),IF($E29="Debt",$G29*Inputs!D$15/12,IF($E29="Reserve Yield",Inputs!D$13*Inputs!D$16,IF($E29="Trend",IF(ISNUMBER(Trend!$Q68),Trend!$Q68,G29),G29)))))))))))) -> 0 | I29: =IF($E29="Manual",M29,IF($E29="Flat",H29,IF($E29="Inflation",H29*(1+Inputs!E$12),IF($E29="Salary",H29*(1+Inputs!E$10),IF($E29="Benefits",H29*(1+Inputs!E$11),IF($E29="Per Student",H29*I$4/H$4*(1+Inputs!E$12),IF($E29="Enrollment",H29*I$4/H$4,IF($E29="Tuition Index",H29*I$5/H$5,IF($E29="% of Salaries",IF($G$6=0,0,$G29/$G$6*I$6),IF($E29="Debt",$G29*Inputs!E$15/12,IF($E29="Reserve Yield",Inputs!E$13*Inputs!E$16,IF($E29="Trend",H29*(1+Inputs!E$12),H29)))))))))))) -> 0 | J29: =IF($E29="Manual",N29,IF($E29="Flat",I29,IF($E29="Inflation",I29*(1+Inputs!F$12),IF($E29="Salary",I29*(1+Inputs!F$10),IF($E29="Benefits",I29*(1+Inputs!F$11),IF($E29="Per Student",I29*J$4/I$4*(1+Inputs!F$12),IF($E29="Enrollment",I29*J$4/I$4,IF($E29="Tuition Index",I29*J$5/I$5,IF($E29="% of Salaries",IF($G$6=0,0,$G29/$G$6*J$6),IF($E29="Debt",$G29*Inputs!F$15/12,IF($E29="Reserve Yield",Inputs!F$13*Inputs!F$16,IF($E29="Trend",I29*(1+Inputs!F$12),I29)))))))))))) -> 0 | K29: =IF($E29="Manual",O29,IF($E29="Flat",J29,IF($E29="Inflation",J29*(1+Inputs!G$12),IF($E29="Salary",J29*(1+Inputs!G$10),IF($E29="Benefits",J29*(1+Inputs!G$11),IF($E29="Per Student",J29*K$4/J$4*(1+Inputs!G$12),IF($E29="Enrollment",J29*K$4/J$4,IF($E29="Tuition Index",J29*K$5/J$5,IF($E29="% of Salaries",IF($G$6=0,0,$G29/$G$6*K$6),IF($E29="Debt",$G29*Inputs!G$15/12,IF($E29="Reserve Yield",Inputs!G$13*Inputs!G$16,IF($E29="Trend",J29*(1+Inputs!G$12),J29)))))))))))) -> 0
A30: Revenue | B30: 2 Interest and Other Income | C30: 400080 | D30: 400080 Contribution from Charitable Trust | E30: Flat | F30: Jul Lump | G30: =SUMIFS('QB Import'!$B$1:$B$600,'QB Import'!$H$1:$H$600,$C30,'QB Import'!$G$1:$G$600,1) -> 60000 | H30: =IF($E30="Manual",L30,IF($E30="Flat",G30,IF($E30="Inflation",G30*(1+Inputs!D$12),IF($E30="Salary",G30*(1+Inputs!D$10),IF($E30="Benefits",G30*(1+Inputs!D$11),IF($E30="Per Student",G30*H$4/G$4*(1+Inputs!D$12),IF($E30="Enrollment",G30*H$4/G$4,IF($E30="Tuition Index",G30*H$5/G$5,IF($E30="% of Salaries",IF($G$6=0,0,$G30/$G$6*H$6),IF($E30="Debt",$G30*Inputs!D$15/12,IF($E30="Reserve Yield",Inputs!D$13*Inputs!D$16,IF($E30="Trend",IF(ISNUMBER(Trend!$Q69),Trend!$Q69,G30),G30)))))))))))) -> 60000 | I30: =IF($E30="Manual",M30,IF($E30="Flat",H30,IF($E30="Inflation",H30*(1+Inputs!E$12),IF($E30="Salary",H30*(1+Inputs!E$10),IF($E30="Benefits",H30*(1+Inputs!E$11),IF($E30="Per Student",H30*I$4/H$4*(1+Inputs!E$12),IF($E30="Enrollment",H30*I$4/H$4,IF($E30="Tuition Index",H30*I$5/H$5,IF($E30="% of Salaries",IF($G$6=0,0,$G30/$G$6*I$6),IF($E30="Debt",$G30*Inputs!E$15/12,IF($E30="Reserve Yield",Inputs!E$13*Inputs!E$16,IF($E30="Trend",H30*(1+Inputs!E$12),H30)))))))))))) -> 60000 | J30: =IF($E30="Manual",N30,IF($E30="Flat",I30,IF($E30="Inflation",I30*(1+Inputs!F$12),IF($E30="Salary",I30*(1+Inputs!F$10),IF($E30="Benefits",I30*(1+Inputs!F$11),IF($E30="Per Student",I30*J$4/I$4*(1+Inputs!F$12),IF($E30="Enrollment",I30*J$4/I$4,IF($E30="Tuition Index",I30*J$5/I$5,IF($E30="% of Salaries",IF($G$6=0,0,$G30/$G$6*J$6),IF($E30="Debt",$G30*Inputs!F$15/12,IF($E30="Reserve Yield",Inputs!F$13*Inputs!F$16,IF($E30="Trend",I30*(1+Inputs!F$12),I30)))))))))))) -> 60000 | K30: =IF($E30="Manual",O30,IF($E30="Flat",J30,IF($E30="Inflation",J30*(1+Inputs!G$12),IF($E30="Salary",J30*(1+Inputs!G$10),IF($E30="Benefits",J30*(1+Inputs!G$11),IF($E30="Per Student",J30*K$4/J$4*(1+Inputs!G$12),IF($E30="Enrollment",J30*K$4/J$4,IF($E30="Tuition Index",J30*K$5/J$5,IF($E30="% of Salaries",IF($G$6=0,0,$G30/$G$6*K$6),IF($E30="Debt",$G30*Inputs!G$15/12,IF($E30="Reserve Yield",Inputs!G$13*Inputs!G$16,IF($E30="Trend",J30*(1+Inputs!G$12),J30)))))))))))) -> 60000
A31: Revenue | B31: 2 Interest and Other Income | C31: 400081 | D31: 400081 Scholarship Income Charitable Trust | E31: Flat | F31: Jul Lump | G31: =SUMIFS('QB Import'!$B$1:$B$600,'QB Import'!$H$1:$H$600,$C31,'QB Import'!$G$1:$G$600,1) -> 0 | H31: =IF($E31="Manual",L31,IF($E31="Flat",G31,IF($E31="Inflation",G31*(1+Inputs!D$12),IF($E31="Salary",G31*(1+Inputs!D$10),IF($E31="Benefits",G31*(1+Inputs!D$11),IF($E31="Per Student",G31*H$4/G$4*(1+Inputs!D$12),IF($E31="Enrollment",G31*H$4/G$4,IF($E31="Tuition Index",G31*H$5/G$5,IF($E31="% of Salaries",IF($G$6=0,0,$G31/$G$6*H$6),IF($E31="Debt",$G31*Inputs!D$15/12,IF($E31="Reserve Yield",Inputs!D$13*Inputs!D$16,IF($E31="Trend",IF(ISNUMBER(Trend!$Q70),Trend!$Q70,G31),G31)))))))))))) -> 0 | I31: =IF($E31="Manual",M31,IF($E31="Flat",H31,IF($E31="Inflation",H31*(1+Inputs!E$12),IF($E31="Salary",H31*(1+Inputs!E$10),IF($E31="Benefits",H31*(1+Inputs!E$11),IF($E31="Per Student",H31*I$4/H$4*(1+Inputs!E$12),IF($E31="Enrollment",H31*I$4/H$4,IF($E31="Tuition Index",H31*I$5/H$5,IF($E31="% of Salaries",IF($G$6=0,0,$G31/$G$6*I$6),IF($E31="Debt",$G31*Inputs!E$15/12,IF($E31="Reserve Yield",Inputs!E$13*Inputs!E$16,IF($E31="Trend",H31*(1+Inputs!E$12),H31)))))))))))) -> 0 | J31: =IF($E31="Manual",N31,IF($E31="Flat",I31,IF($E31="Inflation",I31*(1+Inputs!F$12),IF($E31="Salary",I31*(1+Inputs!F$10),IF($E31="Benefits",I31*(1+Inputs!F$11),IF($E31="Per Student",I31*J$4/I$4*(1+Inputs!F$12),IF($E31="Enrollment",I31*J$4/I$4,IF($E31="Tuition Index",I31*J$5/I$5,IF($E31="% of Salaries",IF($G$6=0,0,$G31/$G$6*J$6),IF($E31="Debt",$G31*Inputs!F$15/12,IF($E31="Reserve Yield",Inputs!F$13*Inputs!F$16,IF($E31="Trend",I31*(1+Inputs!F$12),I31)))))))))))) -> 0 | K31: =IF($E31="Manual",O31,IF($E31="Flat",J31,IF($E31="Inflation",J31*(1+Inputs!G$12),IF($E31="Salary",J31*(1+Inputs!G$10),IF($E31="Benefits",J31*(1+Inputs!G$11),IF($E31="Per Student",J31*K$4/J$4*(1+Inputs!G$12),IF($E31="Enrollment",J31*K$4/J$4,IF($E31="Tuition Index",J31*K$5/J$5,IF($E31="% of Salaries",IF($G$6=0,0,$G31/$G$6*K$6),IF($E31="Debt",$G31*Inputs!G$15/12,IF($E31="Reserve Yield",Inputs!G$13*Inputs!G$16,IF($E31="Trend",J31*(1+Inputs!G$12),J31)))))))))))) -> 0
A32: Revenue | B32: 2 Interest and Other Income | C32: 400084 | D32: 400084 Trinity Church Contribution | E32: Flat | F32: Jul Lump | G32: =SUMIFS('QB Import'!$B$1:$B$600,'QB Import'!$H$1:$H$600,$C32,'QB Import'!$G$1:$G$600,1) -> 55000 | H32: =IF($E32="Manual",L32,IF($E32="Flat",G32,IF($E32="Inflation",G32*(1+Inputs!D$12),IF($E32="Salary",G32*(1+Inputs!D$10),IF($E32="Benefits",G32*(1+Inputs!D$11),IF($E32="Per Student",G32*H$4/G$4*(1+Inputs!D$12),IF($E32="Enrollment",G32*H$4/G$4,IF($E32="Tuition Index",G32*H$5/G$5,IF($E32="% of Salaries",IF($G$6=0,0,$G32/$G$6*H$6),IF($E32="Debt",$G32*Inputs!D$15/12,IF($E32="Reserve Yield",Inputs!D$13*Inputs!D$16,IF($E32="Trend",IF(ISNUMBER(Trend!$Q71),Trend!$Q71,G32),G32)))))))))))) -> 55000 | I32: =IF($E32="Manual",M32,IF($E32="Flat",H32,IF($E32="Inflation",H32*(1+Inputs!E$12),IF($E32="Salary",H32*(1+Inputs!E$10),IF($E32="Benefits",H32*(1+Inputs!E$11),IF($E32="Per Student",H32*I$4/H$4*(1+Inputs!E$12),IF($E32="Enrollment",H32*I$4/H$4,IF($E32="Tuition Index",H32*I$5/H$5,IF($E32="% of Salaries",IF($G$6=0,0,$G32/$G$6*I$6),IF($E32="Debt",$G32*Inputs!E$15/12,IF($E32="Reserve Yield",Inputs!E$13*Inputs!E$16,IF($E32="Trend",H32*(1+Inputs!E$12),H32)))))))))))) -> 55000 | J32: =IF($E32="Manual",N32,IF($E32="Flat",I32,IF($E32="Inflation",I32*(1+Inputs!F$12),IF($E32="Salary",I32*(1+Inputs!F$10),IF($E32="Benefits",I32*(1+Inputs!F$11),IF($E32="Per Student",I32*J$4/I$4*(1+Inputs!F$12),IF($E32="Enrollment",I32*J$4/I$4,IF($E32="Tuition Index",I32*J$5/I$5,IF($E32="% of Salaries",IF($G$6=0,0,$G32/$G$6*J$6),IF($E32="Debt",$G32*Inputs!F$15/12,IF($E32="Reserve Yield",Inputs!F$13*Inputs!F$16,IF($E32="Trend",I32*(1+Inputs!F$12),I32)))))))))))) -> 55000 | K32: =IF($E32="Manual",O32,IF($E32="Flat",J32,IF($E32="Inflation",J32*(1+Inputs!G$12),IF($E32="Salary",J32*(1+Inputs!G$10),IF($E32="Benefits",J32*(1+Inputs!G$11),IF($E32="Per Student",J32*K$4/J$4*(1+Inputs!G$12),IF($E32="Enrollment",J32*K$4/J$4,IF($E32="Tuition Index",J32*K$5/J$5,IF($E32="% of Salaries",IF($G$6=0,0,$G32/$G$6*K$6),IF($E32="Debt",$G32*Inputs!G$15/12,IF($E32="Reserve Yield",Inputs!G$13*Inputs!G$16,IF($E32="Trend",J32*(1+Inputs!G$12),J32)))))))))))) -> 55000
A33: Revenue | B33: 2 Interest and Other Income | C33: 400191 | D33: 400191 Corporate Sponsors - General Fund Contribution | E33: Manual | F33: Jul Lump | G33: =SUMIFS('QB Import'!$B$1:$B$600,'QB Import'!$H$1:$H$600,$C33,'QB Import'!$G$1:$G$600,1) -> 100000 | H33: =IF($E33="Manual",L33,IF($E33="Flat",G33,IF($E33="Inflation",G33*(1+Inputs!D$12),IF($E33="Salary",G33*(1+Inputs!D$10),IF($E33="Benefits",G33*(1+Inputs!D$11),IF($E33="Per Student",G33*H$4/G$4*(1+Inputs!D$12),IF($E33="Enrollment",G33*H$4/G$4,IF($E33="Tuition Index",G33*H$5/G$5,IF($E33="% of Salaries",IF($G$6=0,0,$G33/$G$6*H$6),IF($E33="Debt",$G33*Inputs!D$15/12,IF($E33="Reserve Yield",Inputs!D$13*Inputs!D$16,IF($E33="Trend",IF(ISNUMBER(Trend!$Q72),Trend!$Q72,G33),G33)))))))))))) -> 50000 | I33: =IF($E33="Manual",M33,IF($E33="Flat",H33,IF($E33="Inflation",H33*(1+Inputs!E$12),IF($E33="Salary",H33*(1+Inputs!E$10),IF($E33="Benefits",H33*(1+Inputs!E$11),IF($E33="Per Student",H33*I$4/H$4*(1+Inputs!E$12),IF($E33="Enrollment",H33*I$4/H$4,IF($E33="Tuition Index",H33*I$5/H$5,IF($E33="% of Salaries",IF($G$6=0,0,$G33/$G$6*I$6),IF($E33="Debt",$G33*Inputs!E$15/12,IF($E33="Reserve Yield",Inputs!E$13*Inputs!E$16,IF($E33="Trend",H33*(1+Inputs!E$12),H33)))))))))))) -> 0 | J33: =IF($E33="Manual",N33,IF($E33="Flat",I33,IF($E33="Inflation",I33*(1+Inputs!F$12),IF($E33="Salary",I33*(1+Inputs!F$10),IF($E33="Benefits",I33*(1+Inputs!F$11),IF($E33="Per Student",I33*J$4/I$4*(1+Inputs!F$12),IF($E33="Enrollment",I33*J$4/I$4,IF($E33="Tuition Index",I33*J$5/I$5,IF($E33="% of Salaries",IF($G$6=0,0,$G33/$G$6*J$6),IF($E33="Debt",$G33*Inputs!F$15/12,IF($E33="Reserve Yield",Inputs!F$13*Inputs!F$16,IF($E33="Trend",I33*(1+Inputs!F$12),I33)))))))))))) -> 0 | K33: =IF($E33="Manual",O33,IF($E33="Flat",J33,IF($E33="Inflation",J33*(1+Inputs!G$12),IF($E33="Salary",J33*(1+Inputs!G$10),IF($E33="Benefits",J33*(1+Inputs!G$11),IF($E33="Per Student",J33*K$4/J$4*(1+Inputs!G$12),IF($E33="Enrollment",J33*K$4/J$4,IF($E33="Tuition Index",J33*K$5/J$5,IF($E33="% of Salaries",IF($G$6=0,0,$G33/$G$6*K$6),IF($E33="Debt",$G33*Inputs!G$15/12,IF($E33="Reserve Yield",Inputs!G$13*Inputs!G$16,IF($E33="Trend",J33*(1+Inputs!G$12),J33)))))))))))) -> 0 | L33: 50000 | M33: 0 | N33: 0 | O33: 0
A34: Revenue | B34: 2 Interest and Other Income | C34: 400192 | D34: 400192 Annual Fund Unrestricted-General Fund Contribution | E34: Flat | F34: Jul Lump | G34: =SUMIFS('QB Import'!$B$1:$B$600,'QB Import'!$H$1:$H$600,$C34,'QB Import'!$G$1:$G$600,1) -> 150000 | H34: =IF($E34="Manual",L34,IF($E34="Flat",G34,IF($E34="Inflation",G34*(1+Inputs!D$12),IF($E34="Salary",G34*(1+Inputs!D$10),IF($E34="Benefits",G34*(1+Inputs!D$11),IF($E34="Per Student",G34*H$4/G$4*(1+Inputs!D$12),IF($E34="Enrollment",G34*H$4/G$4,IF($E34="Tuition Index",G34*H$5/G$5,IF($E34="% of Salaries",IF($G$6=0,0,$G34/$G$6*H$6),IF($E34="Debt",$G34*Inputs!D$15/12,IF($E34="Reserve Yield",Inputs!D$13*Inputs!D$16,IF($E34="Trend",IF(ISNUMBER(Trend!$Q73),Trend!$Q73,G34),G34)))))))))))) -> 150000 | I34: =IF($E34="Manual",M34,IF($E34="Flat",H34,IF($E34="Inflation",H34*(1+Inputs!E$12),IF($E34="Salary",H34*(1+Inputs!E$10),IF($E34="Benefits",H34*(1+Inputs!E$11),IF($E34="Per Student",H34*I$4/H$4*(1+Inputs!E$12),IF($E34="Enrollment",H34*I$4/H$4,IF($E34="Tuition Index",H34*I$5/H$5,IF($E34="% of Salaries",IF($G$6=0,0,$G34/$G$6*I$6),IF($E34="Debt",$G34*Inputs!E$15/12,IF($E34="Reserve Yield",Inputs!E$13*Inputs!E$16,IF($E34="Trend",H34*(1+Inputs!E$12),H34)))))))))))) -> 150000 | J34: =IF($E34="Manual",N34,IF($E34="Flat",I34,IF($E34="Inflation",I34*(1+Inputs!F$12),IF($E34="Salary",I34*(1+Inputs!F$10),IF($E34="Benefits",I34*(1+Inputs!F$11),IF($E34="Per Student",I34*J$4/I$4*(1+Inputs!F$12),IF($E34="Enrollment",I34*J$4/I$4,IF($E34="Tuition Index",I34*J$5/I$5,IF($E34="% of Salaries",IF($G$6=0,0,$G34/$G$6*J$6),IF($E34="Debt",$G34*Inputs!F$15/12,IF($E34="Reserve Yield",Inputs!F$13*Inputs!F$16,IF($E34="Trend",I34*(1+Inputs!F$12),I34)))))))))))) -> 150000 | K34: =IF($E34="Manual",O34,IF($E34="Flat",J34,IF($E34="Inflation",J34*(1+Inputs!G$12),IF($E34="Salary",J34*(1+Inputs!G$10),IF($E34="Benefits",J34*(1+Inputs!G$11),IF($E34="Per Student",J34*K$4/J$4*(1+Inputs!G$12),IF($E34="Enrollment",J34*K$4/J$4,IF($E34="Tuition Index",J34*K$5/J$5,IF($E34="% of Salaries",IF($G$6=0,0,$G34/$G$6*K$6),IF($E34="Debt",$G34*Inputs!G$15/12,IF($E34="Reserve Yield",Inputs!G$13*Inputs!G$16,IF($E34="Trend",J34*(1+Inputs!G$12),J34)))))))))))) -> 150000
A35: Revenue | B35: 2 Interest and Other Income | C35: 400124 | D35: 400124 Interest Income Reserve Acct Synovus | E35: Reserve Yield | F35: Even | G35: =SUMIFS('QB Import'!$B$1:$B$600,'QB Import'!$H$1:$H$600,$C35,'QB Import'!$G$1:$G$600,1) -> 30000 | H35: =IF($E35="Manual",L35,IF($E35="Flat",G35,IF($E35="Inflation",G35*(1+Inputs!D$12),IF($E35="Salary",G35*(1+Inputs!D$10),IF($E35="Benefits",G35*(1+Inputs!D$11),IF($E35="Per Student",G35*H$4/G$4*(1+Inputs!D$12),IF($E35="Enrollment",G35*H$4/G$4,IF($E35="Tuition Index",G35*H$5/G$5,IF($E35="% of Salaries",IF($G$6=0,0,$G35/$G$6*H$6),IF($E35="Debt",$G35*Inputs!D$15/12,IF($E35="Reserve Yield",Inputs!D$13*Inputs!D$16,IF($E35="Trend",IF(ISNUMBER(Trend!$Q74),Trend!$Q74,G35),G35)))))))))))) -> 29005.031 | I35: =IF($E35="Manual",M35,IF($E35="Flat",H35,IF($E35="Inflation",H35*(1+Inputs!E$12),IF($E35="Salary",H35*(1+Inputs!E$10),IF($E35="Benefits",H35*(1+Inputs!E$11),IF($E35="Per Student",H35*I$4/H$4*(1+Inputs!E$12),IF($E35="Enrollment",H35*I$4/H$4,IF($E35="Tuition Index",H35*I$5/H$5,IF($E35="% of Salaries",IF($G$6=0,0,$G35/$G$6*I$6),IF($E35="Debt",$G35*Inputs!E$15/12,IF($E35="Reserve Yield",Inputs!E$13*Inputs!E$16,IF($E35="Trend",H35*(1+Inputs!E$12),H35)))))))))))) -> 29005.031 | J35: =IF($E35="Manual",N35,IF($E35="Flat",I35,IF($E35="Inflation",I35*(1+Inputs!F$12),IF($E35="Salary",I35*(1+Inputs!F$10),IF($E35="Benefits",I35*(1+Inputs!F$11),IF($E35="Per Student",I35*J$4/I$4*(1+Inputs!F$12),IF($E35="Enrollment",I35*J$4/I$4,IF($E35="Tuition Index",I35*J$5/I$5,IF($E35="% of Salaries",IF($G$6=0,0,$G35/$G$6*J$6),IF($E35="Debt",$G35*Inputs!F$15/12,IF($E35="Reserve Yield",Inputs!F$13*Inputs!F$16,IF($E35="Trend",I35*(1+Inputs!F$12),I35)))))))))))) -> 29005.031 | K35: =IF($E35="Manual",O35,IF($E35="Flat",J35,IF($E35="Inflation",J35*(1+Inputs!G$12),IF($E35="Salary",J35*(1+Inputs!G$10),IF($E35="Benefits",J35*(1+Inputs!G$11),IF($E35="Per Student",J35*K$4/J$4*(1+Inputs!G$12),IF($E35="Enrollment",J35*K$4/J$4,IF($E35="Tuition Index",J35*K$5/J$5,IF($E35="% of Salaries",IF($G$6=0,0,$G35/$G$6*K$6),IF($E35="Debt",$G35*Inputs!G$15/12,IF($E35="Reserve Yield",Inputs!G$13*Inputs!G$16,IF($E35="Trend",J35*(1+Inputs!G$12),J35)))))))))))) -> 29005.031
A36: Revenue | B36: 2 Interest and Other Income | C36: 400125 | D36: 400125 Interest Income Contingency Synovus | E36: Flat | F36: Even | G36: =SUMIFS('QB Import'!$B$1:$B$600,'QB Import'!$H$1:$H$600,$C36,'QB Import'!$G$1:$G$600,1) -> 0 | H36: =IF($E36="Manual",L36,IF($E36="Flat",G36,IF($E36="Inflation",G36*(1+Inputs!D$12),IF($E36="Salary",G36*(1+Inputs!D$10),IF($E36="Benefits",G36*(1+Inputs!D$11),IF($E36="Per Student",G36*H$4/G$4*(1+Inputs!D$12),IF($E36="Enrollment",G36*H$4/G$4,IF($E36="Tuition Index",G36*H$5/G$5,IF($E36="% of Salaries",IF($G$6=0,0,$G36/$G$6*H$6),IF($E36="Debt",$G36*Inputs!D$15/12,IF($E36="Reserve Yield",Inputs!D$13*Inputs!D$16,IF($E36="Trend",IF(ISNUMBER(Trend!$Q75),Trend!$Q75,G36),G36)))))))))))) -> 0 | I36: =IF($E36="Manual",M36,IF($E36="Flat",H36,IF($E36="Inflation",H36*(1+Inputs!E$12),IF($E36="Salary",H36*(1+Inputs!E$10),IF($E36="Benefits",H36*(1+Inputs!E$11),IF($E36="Per Student",H36*I$4/H$4*(1+Inputs!E$12),IF($E36="Enrollment",H36*I$4/H$4,IF($E36="Tuition Index",H36*I$5/H$5,IF($E36="% of Salaries",IF($G$6=0,0,$G36/$G$6*I$6),IF($E36="Debt",$G36*Inputs!E$15/12,IF($E36="Reserve Yield",Inputs!E$13*Inputs!E$16,IF($E36="Trend",H36*(1+Inputs!E$12),H36)))))))))))) -> 0 | J36: =IF($E36="Manual",N36,IF($E36="Flat",I36,IF($E36="Inflation",I36*(1+Inputs!F$12),IF($E36="Salary",I36*(1+Inputs!F$10),IF($E36="Benefits",I36*(1+Inputs!F$11),IF($E36="Per Student",I36*J$4/I$4*(1+Inputs!F$12),IF($E36="Enrollment",I36*J$4/I$4,IF($E36="Tuition Index",I36*J$5/I$5,IF($E36="% of Salaries",IF($G$6=0,0,$G36/$G$6*J$6),IF($E36="Debt",$G36*Inputs!F$15/12,IF($E36="Reserve Yield",Inputs!F$13*Inputs!F$16,IF($E36="Trend",I36*(1+Inputs!F$12),I36)))))))))))) -> 0 | K36: =IF($E36="Manual",O36,IF($E36="Flat",J36,IF($E36="Inflation",J36*(1+Inputs!G$12),IF($E36="Salary",J36*(1+Inputs!G$10),IF($E36="Benefits",J36*(1+Inputs!G$11),IF($E36="Per Student",J36*K$4/J$4*(1+Inputs!G$12),IF($E36="Enrollment",J36*K$4/J$4,IF($E36="Tuition Index",J36*K$5/J$5,IF($E36="% of Salaries",IF($G$6=0,0,$G36/$G$6*K$6),IF($E36="Debt",$G36*Inputs!G$15/12,IF($E36="Reserve Yield",Inputs!G$13*Inputs!G$16,IF($E36="Trend",J36*(1+Inputs!G$12),J36)))))))))))) -> 0
A37: Revenue | B37: 2 Interest and Other Income | C37: 400182 | D37: 400182 Scholarship for Kids Interest Income | E37: Flat | F37: Even | G37: =SUMIFS('QB Import'!$B$1:$B$600,'QB Import'!$H$1:$H$600,$C37,'QB Import'!$G$1:$G$600,1) -> 0 | H37: =IF($E37="Manual",L37,IF($E37="Flat",G37,IF($E37="Inflation",G37*(1+Inputs!D$12),IF($E37="Salary",G37*(1+Inputs!D$10),IF($E37="Benefits",G37*(1+Inputs!D$11),IF($E37="Per Student",G37*H$4/G$4*(1+Inputs!D$12),IF($E37="Enrollment",G37*H$4/G$4,IF($E37="Tuition Index",G37*H$5/G$5,IF($E37="% of Salaries",IF($G$6=0,0,$G37/$G$6*H$6),IF($E37="Debt",$G37*Inputs!D$15/12,IF($E37="Reserve Yield",Inputs!D$13*Inputs!D$16,IF($E37="Trend",IF(ISNUMBER(Trend!$Q76),Trend!$Q76,G37),G37)))))))))))) -> 0 | I37: =IF($E37="Manual",M37,IF($E37="Flat",H37,IF($E37="Inflation",H37*(1+Inputs!E$12),IF($E37="Salary",H37*(1+Inputs!E$10),IF($E37="Benefits",H37*(1+Inputs!E$11),IF($E37="Per Student",H37*I$4/H$4*(1+Inputs!E$12),IF($E37="Enrollment",H37*I$4/H$4,IF($E37="Tuition Index",H37*I$5/H$5,IF($E37="% of Salaries",IF($G$6=0,0,$G37/$G$6*I$6),IF($E37="Debt",$G37*Inputs!E$15/12,IF($E37="Reserve Yield",Inputs!E$13*Inputs!E$16,IF($E37="Trend",H37*(1+Inputs!E$12),H37)))))))))))) -> 0 | J37: =IF($E37="Manual",N37,IF($E37="Flat",I37,IF($E37="Inflation",I37*(1+Inputs!F$12),IF($E37="Salary",I37*(1+Inputs!F$10),IF($E37="Benefits",I37*(1+Inputs!F$11),IF($E37="Per Student",I37*J$4/I$4*(1+Inputs!F$12),IF($E37="Enrollment",I37*J$4/I$4,IF($E37="Tuition Index",I37*J$5/I$5,IF($E37="% of Salaries",IF($G$6=0,0,$G37/$G$6*J$6),IF($E37="Debt",$G37*Inputs!F$15/12,IF($E37="Reserve Yield",Inputs!F$13*Inputs!F$16,IF($E37="Trend",I37*(1+Inputs!F$12),I37)))))))))))) -> 0 | K37: =IF($E37="Manual",O37,IF($E37="Flat",J37,IF($E37="Inflation",J37*(1+Inputs!G$12),IF($E37="Salary",J37*(1+Inputs!G$10),IF($E37="Benefits",J37*(1+Inputs!G$11),IF($E37="Per Student",J37*K$4/J$4*(1+Inputs!G$12),IF($E37="Enrollment",J37*K$4/J$4,IF($E37="Tuition Index",J37*K$5/J$5,IF($E37="% of Salaries",IF($G$6=0,0,$G37/$G$6*K$6),IF($E37="Debt",$G37*Inputs!G$15/12,IF($E37="Reserve Yield",Inputs!G$13*Inputs!G$16,IF($E37="Trend",J37*(1+Inputs!G$12),J37)))))))))))) -> 0
A38: Revenue | B38: 4 Other Miscellaneous Income | C38: 4 Other Miscellaneous Income | D38: 4 Other Miscellaneous Income | E38: Flat | F38: Even | G38: =SUMIFS('QB Import'!$B$1:$B$600,'QB Import'!$H$1:$H$600,$C38,'QB Import'!$G$1:$G$600,1) -> 60000 | H38: =IF($E38="Manual",L38,IF($E38="Flat",G38,IF($E38="Inflation",G38*(1+Inputs!D$12),IF($E38="Salary",G38*(1+Inputs!D$10),IF($E38="Benefits",G38*(1+Inputs!D$11),IF($E38="Per Student",G38*H$4/G$4*(1+Inputs!D$12),IF($E38="Enrollment",G38*H$4/G$4,IF($E38="Tuition Index",G38*H$5/G$5,IF($E38="% of Salaries",IF($G$6=0,0,$G38/$G$6*H$6),IF($E38="Debt",$G38*Inputs!D$15/12,IF($E38="Reserve Yield",Inputs!D$13*Inputs!D$16,IF($E38="Trend",IF(ISNUMBER(Trend!$Q77),Trend!$Q77,G38),G38)))))))))))) -> 60000 | I38: =IF($E38="Manual",M38,IF($E38="Flat",H38,IF($E38="Inflation",H38*(1+Inputs!E$12),IF($E38="Salary",H38*(1+Inputs!E$10),IF($E38="Benefits",H38*(1+Inputs!E$11),IF($E38="Per Student",H38*I$4/H$4*(1+Inputs!E$12),IF($E38="Enrollment",H38*I$4/H$4,IF($E38="Tuition Index",H38*I$5/H$5,IF($E38="% of Salaries",IF($G$6=0,0,$G38/$G$6*I$6),IF($E38="Debt",$G38*Inputs!E$15/12,IF($E38="Reserve Yield",Inputs!E$13*Inputs!E$16,IF($E38="Trend",H38*(1+Inputs!E$12),H38)))))))))))) -> 60000 | J38: =IF($E38="Manual",N38,IF($E38="Flat",I38,IF($E38="Inflation",I38*(1+Inputs!F$12),IF($E38="Salary",I38*(1+Inputs!F$10),IF($E38="Benefits",I38*(1+Inputs!F$11),IF($E38="Per Student",I38*J$4/I$4*(1+Inputs!F$12),IF($E38="Enrollment",I38*J$4/I$4,IF($E38="Tuition Index",I38*J$5/I$5,IF($E38="% of Salaries",IF($G$6=0,0,$G38/$G$6*J$6),IF($E38="Debt",$G38*Inputs!F$15/12,IF($E38="Reserve Yield",Inputs!F$13*Inputs!F$16,IF($E38="Trend",I38*(1+Inputs!F$12),I38)))))))))))) -> 60000 | K38: =IF($E38="Manual",O38,IF($E38="Flat",J38,IF($E38="Inflation",J38*(1+Inputs!G$12),IF($E38="Salary",J38*(1+Inputs!G$10),IF($E38="Benefits",J38*(1+Inputs!G$11),IF($E38="Per Student",J38*K$4/J$4*(1+Inputs!G$12),IF($E38="Enrollment",J38*K$4/J$4,IF($E38="Tuition Index",J38*K$5/J$5,IF($E38="% of Salaries",IF($G$6=0,0,$G38/$G$6*K$6),IF($E38="Debt",$G38*Inputs!G$15/12,IF($E38="Reserve Yield",Inputs!G$13*Inputs!G$16,IF($E38="Trend",J38*(1+Inputs!G$12),J38)))))))))))) -> 60000
A39: Revenue | B39: 4 Other Miscellaneous Income | C39: 400027 | D39: 400027 Contingency Income Athletic Playoffs | E39: Flat | F39: Even | G39: =SUMIFS('QB Import'!$B$1:$B$600,'QB Import'!$H$1:$H$600,$C39,'QB Import'!$G$1:$G$600,1) -> 0 | H39: =IF($E39="Manual",L39,IF($E39="Flat",G39,IF($E39="Inflation",G39*(1+Inputs!D$12),IF($E39="Salary",G39*(1+Inputs!D$10),IF($E39="Benefits",G39*(1+Inputs!D$11),IF($E39="Per Student",G39*H$4/G$4*(1+Inputs!D$12),IF($E39="Enrollment",G39*H$4/G$4,IF($E39="Tuition Index",G39*H$5/G$5,IF($E39="% of Salaries",IF($G$6=0,0,$G39/$G$6*H$6),IF($E39="Debt",$G39*Inputs!D$15/12,IF($E39="Reserve Yield",Inputs!D$13*Inputs!D$16,IF($E39="Trend",IF(ISNUMBER(Trend!$Q78),Trend!$Q78,G39),G39)))))))))))) -> 0 | I39: =IF($E39="Manual",M39,IF($E39="Flat",H39,IF($E39="Inflation",H39*(1+Inputs!E$12),IF($E39="Salary",H39*(1+Inputs!E$10),IF($E39="Benefits",H39*(1+Inputs!E$11),IF($E39="Per Student",H39*I$4/H$4*(1+Inputs!E$12),IF($E39="Enrollment",H39*I$4/H$4,IF($E39="Tuition Index",H39*I$5/H$5,IF($E39="% of Salaries",IF($G$6=0,0,$G39/$G$6*I$6),IF($E39="Debt",$G39*Inputs!E$15/12,IF($E39="Reserve Yield",Inputs!E$13*Inputs!E$16,IF($E39="Trend",H39*(1+Inputs!E$12),H39)))))))))))) -> 0 | J39: =IF($E39="Manual",N39,IF($E39="Flat",I39,IF($E39="Inflation",I39*(1+Inputs!F$12),IF($E39="Salary",I39*(1+Inputs!F$10),IF($E39="Benefits",I39*(1+Inputs!F$11),IF($E39="Per Student",I39*J$4/I$4*(1+Inputs!F$12),IF($E39="Enrollment",I39*J$4/I$4,IF($E39="Tuition Index",I39*J$5/I$5,IF($E39="% of Salaries",IF($G$6=0,0,$G39/$G$6*J$6),IF($E39="Debt",$G39*Inputs!F$15/12,IF($E39="Reserve Yield",Inputs!F$13*Inputs!F$16,IF($E39="Trend",I39*(1+Inputs!F$12),I39)))))))))))) -> 0 | K39: =IF($E39="Manual",O39,IF($E39="Flat",J39,IF($E39="Inflation",J39*(1+Inputs!G$12),IF($E39="Salary",J39*(1+Inputs!G$10),IF($E39="Benefits",J39*(1+Inputs!G$11),IF($E39="Per Student",J39*K$4/J$4*(1+Inputs!G$12),IF($E39="Enrollment",J39*K$4/J$4,IF($E39="Tuition Index",J39*K$5/J$5,IF($E39="% of Salaries",IF($G$6=0,0,$G39/$G$6*K$6),IF($E39="Debt",$G39*Inputs!G$15/12,IF($E39="Reserve Yield",Inputs!G$13*Inputs!G$16,IF($E39="Trend",J39*(1+Inputs!G$12),J39)))))))))))) -> 0
A40: Revenue | B40: 4 Other Miscellaneous Income | C40: 400082 | D40: 400082 Grant Income | E40: Flat | F40: Even | G40: =SUMIFS('QB Import'!$B$1:$B$600,'QB Import'!$H$1:$H$600,$C40,'QB Import'!$G$1:$G$600,1) -> 0 | H40: =IF($E40="Manual",L40,IF($E40="Flat",G40,IF($E40="Inflation",G40*(1+Inputs!D$12),IF($E40="Salary",G40*(1+Inputs!D$10),IF($E40="Benefits",G40*(1+Inputs!D$11),IF($E40="Per Student",G40*H$4/G$4*(1+Inputs!D$12),IF($E40="Enrollment",G40*H$4/G$4,IF($E40="Tuition Index",G40*H$5/G$5,IF($E40="% of Salaries",IF($G$6=0,0,$G40/$G$6*H$6),IF($E40="Debt",$G40*Inputs!D$15/12,IF($E40="Reserve Yield",Inputs!D$13*Inputs!D$16,IF($E40="Trend",IF(ISNUMBER(Trend!$Q79),Trend!$Q79,G40),G40)))))))))))) -> 0 | I40: =IF($E40="Manual",M40,IF($E40="Flat",H40,IF($E40="Inflation",H40*(1+Inputs!E$12),IF($E40="Salary",H40*(1+Inputs!E$10),IF($E40="Benefits",H40*(1+Inputs!E$11),IF($E40="Per Student",H40*I$4/H$4*(1+Inputs!E$12),IF($E40="Enrollment",H40*I$4/H$4,IF($E40="Tuition Index",H40*I$5/H$5,IF($E40="% of Salaries",IF($G$6=0,0,$G40/$G$6*I$6),IF($E40="Debt",$G40*Inputs!E$15/12,IF($E40="Reserve Yield",Inputs!E$13*Inputs!E$16,IF($E40="Trend",H40*(1+Inputs!E$12),H40)))))))))))) -> 0 | J40: =IF($E40="Manual",N40,IF($E40="Flat",I40,IF($E40="Inflation",I40*(1+Inputs!F$12),IF($E40="Salary",I40*(1+Inputs!F$10),IF($E40="Benefits",I40*(1+Inputs!F$11),IF($E40="Per Student",I40*J$4/I$4*(1+Inputs!F$12),IF($E40="Enrollment",I40*J$4/I$4,IF($E40="Tuition Index",I40*J$5/I$5,IF($E40="% of Salaries",IF($G$6=0,0,$G40/$G$6*J$6),IF($E40="Debt",$G40*Inputs!F$15/12,IF($E40="Reserve Yield",Inputs!F$13*Inputs!F$16,IF($E40="Trend",I40*(1+Inputs!F$12),I40)))))))))))) -> 0 | K40: =IF($E40="Manual",O40,IF($E40="Flat",J40,IF($E40="Inflation",J40*(1+Inputs!G$12),IF($E40="Salary",J40*(1+Inputs!G$10),IF($E40="Benefits",J40*(1+Inputs!G$11),IF($E40="Per Student",J40*K$4/J$4*(1+Inputs!G$12),IF($E40="Enrollment",J40*K$4/J$4,IF($E40="Tuition Index",J40*K$5/J$5,IF($E40="% of Salaries",IF($G$6=0,0,$G40/$G$6*K$6),IF($E40="Debt",$G40*Inputs!G$15/12,IF($E40="Reserve Yield",Inputs!G$13*Inputs!G$16,IF($E40="Trend",J40*(1+Inputs!G$12),J40)))))))))))) -> 0
A41: Revenue | B41: 4 Other Miscellaneous Income | C41: 400132 | D41: 400132 Facility Rental/Usage Income | E41: Flat | F41: Even | G41: =SUMIFS('QB Import'!$B$1:$B$600,'QB Import'!$H$1:$H$600,$C41,'QB Import'!$G$1:$G$600,1) -> 0 | H41: =IF($E41="Manual",L41,IF($E41="Flat",G41,IF($E41="Inflation",G41*(1+Inputs!D$12),IF($E41="Salary",G41*(1+Inputs!D$10),IF($E41="Benefits",G41*(1+Inputs!D$11),IF($E41="Per Student",G41*H$4/G$4*(1+Inputs!D$12),IF($E41="Enrollment",G41*H$4/G$4,IF($E41="Tuition Index",G41*H$5/G$5,IF($E41="% of Salaries",IF($G$6=0,0,$G41/$G$6*H$6),IF($E41="Debt",$G41*Inputs!D$15/12,IF($E41="Reserve Yield",Inputs!D$13*Inputs!D$16,IF($E41="Trend",IF(ISNUMBER(Trend!$Q80),Trend!$Q80,G41),G41)))))))))))) -> 0 | I41: =IF($E41="Manual",M41,IF($E41="Flat",H41,IF($E41="Inflation",H41*(1+Inputs!E$12),IF($E41="Salary",H41*(1+Inputs!E$10),IF($E41="Benefits",H41*(1+Inputs!E$11),IF($E41="Per Student",H41*I$4/H$4*(1+Inputs!E$12),IF($E41="Enrollment",H41*I$4/H$4,IF($E41="Tuition Index",H41*I$5/H$5,IF($E41="% of Salaries",IF($G$6=0,0,$G41/$G$6*I$6),IF($E41="Debt",$G41*Inputs!E$15/12,IF($E41="Reserve Yield",Inputs!E$13*Inputs!E$16,IF($E41="Trend",H41*(1+Inputs!E$12),H41)))))))))))) -> 0 | J41: =IF($E41="Manual",N41,IF($E41="Flat",I41,IF($E41="Inflation",I41*(1+Inputs!F$12),IF($E41="Salary",I41*(1+Inputs!F$10),IF($E41="Benefits",I41*(1+Inputs!F$11),IF($E41="Per Student",I41*J$4/I$4*(1+Inputs!F$12),IF($E41="Enrollment",I41*J$4/I$4,IF($E41="Tuition Index",I41*J$5/I$5,IF($E41="% of Salaries",IF($G$6=0,0,$G41/$G$6*J$6),IF($E41="Debt",$G41*Inputs!F$15/12,IF($E41="Reserve Yield",Inputs!F$13*Inputs!F$16,IF($E41="Trend",I41*(1+Inputs!F$12),I41)))))))))))) -> 0 | K41: =IF($E41="Manual",O41,IF($E41="Flat",J41,IF($E41="Inflation",J41*(1+Inputs!G$12),IF($E41="Salary",J41*(1+Inputs!G$10),IF($E41="Benefits",J41*(1+Inputs!G$11),IF($E41="Per Student",J41*K$4/J$4*(1+Inputs!G$12),IF($E41="Enrollment",J41*K$4/J$4,IF($E41="Tuition Index",J41*K$5/J$5,IF($E41="% of Salaries",IF($G$6=0,0,$G41/$G$6*K$6),IF($E41="Debt",$G41*Inputs!G$15/12,IF($E41="Reserve Yield",Inputs!G$13*Inputs!G$16,IF($E41="Trend",J41*(1+Inputs!G$12),J41)))))))))))) -> 0
A42: Revenue | B42: 4 Other Miscellaneous Income | C42: 400143 | D42: 400143 Speech Therapy Fees | E42: Flat | F42: Even | G42: =SUMIFS('QB Import'!$B$1:$B$600,'QB Import'!$H$1:$H$600,$C42,'QB Import'!$G$1:$G$600,1) -> 0 | H42: =IF($E42="Manual",L42,IF($E42="Flat",G42,IF($E42="Inflation",G42*(1+Inputs!D$12),IF($E42="Salary",G42*(1+Inputs!D$10),IF($E42="Benefits",G42*(1+Inputs!D$11),IF($E42="Per Student",G42*H$4/G$4*(1+Inputs!D$12),IF($E42="Enrollment",G42*H$4/G$4,IF($E42="Tuition Index",G42*H$5/G$5,IF($E42="% of Salaries",IF($G$6=0,0,$G42/$G$6*H$6),IF($E42="Debt",$G42*Inputs!D$15/12,IF($E42="Reserve Yield",Inputs!D$13*Inputs!D$16,IF($E42="Trend",IF(ISNUMBER(Trend!$Q81),Trend!$Q81,G42),G42)))))))))))) -> 0 | I42: =IF($E42="Manual",M42,IF($E42="Flat",H42,IF($E42="Inflation",H42*(1+Inputs!E$12),IF($E42="Salary",H42*(1+Inputs!E$10),IF($E42="Benefits",H42*(1+Inputs!E$11),IF($E42="Per Student",H42*I$4/H$4*(1+Inputs!E$12),IF($E42="Enrollment",H42*I$4/H$4,IF($E42="Tuition Index",H42*I$5/H$5,IF($E42="% of Salaries",IF($G$6=0,0,$G42/$G$6*I$6),IF($E42="Debt",$G42*Inputs!E$15/12,IF($E42="Reserve Yield",Inputs!E$13*Inputs!E$16,IF($E42="Trend",H42*(1+Inputs!E$12),H42)))))))))))) -> 0 | J42: =IF($E42="Manual",N42,IF($E42="Flat",I42,IF($E42="Inflation",I42*(1+Inputs!F$12),IF($E42="Salary",I42*(1+Inputs!F$10),IF($E42="Benefits",I42*(1+Inputs!F$11),IF($E42="Per Student",I42*J$4/I$4*(1+Inputs!F$12),IF($E42="Enrollment",I42*J$4/I$4,IF($E42="Tuition Index",I42*J$5/I$5,IF($E42="% of Salaries",IF($G$6=0,0,$G42/$G$6*J$6),IF($E42="Debt",$G42*Inputs!F$15/12,IF($E42="Reserve Yield",Inputs!F$13*Inputs!F$16,IF($E42="Trend",I42*(1+Inputs!F$12),I42)))))))))))) -> 0 | K42: =IF($E42="Manual",O42,IF($E42="Flat",J42,IF($E42="Inflation",J42*(1+Inputs!G$12),IF($E42="Salary",J42*(1+Inputs!G$10),IF($E42="Benefits",J42*(1+Inputs!G$11),IF($E42="Per Student",J42*K$4/J$4*(1+Inputs!G$12),IF($E42="Enrollment",J42*K$4/J$4,IF($E42="Tuition Index",J42*K$5/J$5,IF($E42="% of Salaries",IF($G$6=0,0,$G42/$G$6*K$6),IF($E42="Debt",$G42*Inputs!G$15/12,IF($E42="Reserve Yield",Inputs!G$13*Inputs!G$16,IF($E42="Trend",J42*(1+Inputs!G$12),J42)))))))))))) -> 0
A43: Revenue | B43: 4 Other Miscellaneous Income | C43: 400144 | D43: 400144 Credit Card Rebates | E43: Flat | F43: Even | G43: =SUMIFS('QB Import'!$B$1:$B$600,'QB Import'!$H$1:$H$600,$C43,'QB Import'!$G$1:$G$600,1) -> 0 | H43: =IF($E43="Manual",L43,IF($E43="Flat",G43,IF($E43="Inflation",G43*(1+Inputs!D$12),IF($E43="Salary",G43*(1+Inputs!D$10),IF($E43="Benefits",G43*(1+Inputs!D$11),IF($E43="Per Student",G43*H$4/G$4*(1+Inputs!D$12),IF($E43="Enrollment",G43*H$4/G$4,IF($E43="Tuition Index",G43*H$5/G$5,IF($E43="% of Salaries",IF($G$6=0,0,$G43/$G$6*H$6),IF($E43="Debt",$G43*Inputs!D$15/12,IF($E43="Reserve Yield",Inputs!D$13*Inputs!D$16,IF($E43="Trend",IF(ISNUMBER(Trend!$Q82),Trend!$Q82,G43),G43)))))))))))) -> 0 | I43: =IF($E43="Manual",M43,IF($E43="Flat",H43,IF($E43="Inflation",H43*(1+Inputs!E$12),IF($E43="Salary",H43*(1+Inputs!E$10),IF($E43="Benefits",H43*(1+Inputs!E$11),IF($E43="Per Student",H43*I$4/H$4*(1+Inputs!E$12),IF($E43="Enrollment",H43*I$4/H$4,IF($E43="Tuition Index",H43*I$5/H$5,IF($E43="% of Salaries",IF($G$6=0,0,$G43/$G$6*I$6),IF($E43="Debt",$G43*Inputs!E$15/12,IF($E43="Reserve Yield",Inputs!E$13*Inputs!E$16,IF($E43="Trend",H43*(1+Inputs!E$12),H43)))))))))))) -> 0 | J43: =IF($E43="Manual",N43,IF($E43="Flat",I43,IF($E43="Inflation",I43*(1+Inputs!F$12),IF($E43="Salary",I43*(1+Inputs!F$10),IF($E43="Benefits",I43*(1+Inputs!F$11),IF($E43="Per Student",I43*J$4/I$4*(1+Inputs!F$12),IF($E43="Enrollment",I43*J$4/I$4,IF($E43="Tuition Index",I43*J$5/I$5,IF($E43="% of Salaries",IF($G$6=0,0,$G43/$G$6*J$6),IF($E43="Debt",$G43*Inputs!F$15/12,IF($E43="Reserve Yield",Inputs!F$13*Inputs!F$16,IF($E43="Trend",I43*(1+Inputs!F$12),I43)))))))))))) -> 0 | K43: =IF($E43="Manual",O43,IF($E43="Flat",J43,IF($E43="Inflation",J43*(1+Inputs!G$12),IF($E43="Salary",J43*(1+Inputs!G$10),IF($E43="Benefits",J43*(1+Inputs!G$11),IF($E43="Per Student",J43*K$4/J$4*(1+Inputs!G$12),IF($E43="Enrollment",J43*K$4/J$4,IF($E43="Tuition Index",J43*K$5/J$5,IF($E43="% of Salaries",IF($G$6=0,0,$G43/$G$6*K$6),IF($E43="Debt",$G43*Inputs!G$15/12,IF($E43="Reserve Yield",Inputs!G$13*Inputs!G$16,IF($E43="Trend",J43*(1+Inputs!G$12),J43)))))))))))) -> 0
A44: Revenue | B44: 4 Other Miscellaneous Income | C44: 400145 | D44: 400145 Sale of AP Textbooks | E44: Flat | F44: Even | G44: =SUMIFS('QB Import'!$B$1:$B$600,'QB Import'!$H$1:$H$600,$C44,'QB Import'!$G$1:$G$600,1) -> 0 | H44: =IF($E44="Manual",L44,IF($E44="Flat",G44,IF($E44="Inflation",G44*(1+Inputs!D$12),IF($E44="Salary",G44*(1+Inputs!D$10),IF($E44="Benefits",G44*(1+Inputs!D$11),IF($E44="Per Student",G44*H$4/G$4*(1+Inputs!D$12),IF($E44="Enrollment",G44*H$4/G$4,IF($E44="Tuition Index",G44*H$5/G$5,IF($E44="% of Salaries",IF($G$6=0,0,$G44/$G$6*H$6),IF($E44="Debt",$G44*Inputs!D$15/12,IF($E44="Reserve Yield",Inputs!D$13*Inputs!D$16,IF($E44="Trend",IF(ISNUMBER(Trend!$Q83),Trend!$Q83,G44),G44)))))))))))) -> 0 | I44: =IF($E44="Manual",M44,IF($E44="Flat",H44,IF($E44="Inflation",H44*(1+Inputs!E$12),IF($E44="Salary",H44*(1+Inputs!E$10),IF($E44="Benefits",H44*(1+Inputs!E$11),IF($E44="Per Student",H44*I$4/H$4*(1+Inputs!E$12),IF($E44="Enrollment",H44*I$4/H$4,IF($E44="Tuition Index",H44*I$5/H$5,IF($E44="% of Salaries",IF($G$6=0,0,$G44/$G$6*I$6),IF($E44="Debt",$G44*Inputs!E$15/12,IF($E44="Reserve Yield",Inputs!E$13*Inputs!E$16,IF($E44="Trend",H44*(1+Inputs!E$12),H44)))))))))))) -> 0 | J44: =IF($E44="Manual",N44,IF($E44="Flat",I44,IF($E44="Inflation",I44*(1+Inputs!F$12),IF($E44="Salary",I44*(1+Inputs!F$10),IF($E44="Benefits",I44*(1+Inputs!F$11),IF($E44="Per Student",I44*J$4/I$4*(1+Inputs!F$12),IF($E44="Enrollment",I44*J$4/I$4,IF($E44="Tuition Index",I44*J$5/I$5,IF($E44="% of Salaries",IF($G$6=0,0,$G44/$G$6*J$6),IF($E44="Debt",$G44*Inputs!F$15/12,IF($E44="Reserve Yield",Inputs!F$13*Inputs!F$16,IF($E44="Trend",I44*(1+Inputs!F$12),I44)))))))))))) -> 0 | K44: =IF($E44="Manual",O44,IF($E44="Flat",J44,IF($E44="Inflation",J44*(1+Inputs!G$12),IF($E44="Salary",J44*(1+Inputs!G$10),IF($E44="Benefits",J44*(1+Inputs!G$11),IF($E44="Per Student",J44*K$4/J$4*(1+Inputs!G$12),IF($E44="Enrollment",J44*K$4/J$4,IF($E44="Tuition Index",J44*K$5/J$5,IF($E44="% of Salaries",IF($G$6=0,0,$G44/$G$6*K$6),IF($E44="Debt",$G44*Inputs!G$15/12,IF($E44="Reserve Yield",Inputs!G$13*Inputs!G$16,IF($E44="Trend",J44*(1+Inputs!G$12),J44)))))))))))) -> 0
A45: Revenue | B45: 4 Other Miscellaneous Income | C45: 400147 | D45: 400147 Coke Machines Proceeds | E45: Flat | F45: Even | G45: =SUMIFS('QB Import'!$B$1:$B$600,'QB Import'!$H$1:$H$600,$C45,'QB Import'!$G$1:$G$600,1) -> 0 | H45: =IF($E45="Manual",L45,IF($E45="Flat",G45,IF($E45="Inflation",G45*(1+Inputs!D$12),IF($E45="Salary",G45*(1+Inputs!D$10),IF($E45="Benefits",G45*(1+Inputs!D$11),IF($E45="Per Student",G45*H$4/G$4*(1+Inputs!D$12),IF($E45="Enrollment",G45*H$4/G$4,IF($E45="Tuition Index",G45*H$5/G$5,IF($E45="% of Salaries",IF($G$6=0,0,$G45/$G$6*H$6),IF($E45="Debt",$G45*Inputs!D$15/12,IF($E45="Reserve Yield",Inputs!D$13*Inputs!D$16,IF($E45="Trend",IF(ISNUMBER(Trend!$Q84),Trend!$Q84,G45),G45)))))))))))) -> 0 | I45: =IF($E45="Manual",M45,IF($E45="Flat",H45,IF($E45="Inflation",H45*(1+Inputs!E$12),IF($E45="Salary",H45*(1+Inputs!E$10),IF($E45="Benefits",H45*(1+Inputs!E$11),IF($E45="Per Student",H45*I$4/H$4*(1+Inputs!E$12),IF($E45="Enrollment",H45*I$4/H$4,IF($E45="Tuition Index",H45*I$5/H$5,IF($E45="% of Salaries",IF($G$6=0,0,$G45/$G$6*I$6),IF($E45="Debt",$G45*Inputs!E$15/12,IF($E45="Reserve Yield",Inputs!E$13*Inputs!E$16,IF($E45="Trend",H45*(1+Inputs!E$12),H45)))))))))))) -> 0 | J45: =IF($E45="Manual",N45,IF($E45="Flat",I45,IF($E45="Inflation",I45*(1+Inputs!F$12),IF($E45="Salary",I45*(1+Inputs!F$10),IF($E45="Benefits",I45*(1+Inputs!F$11),IF($E45="Per Student",I45*J$4/I$4*(1+Inputs!F$12),IF($E45="Enrollment",I45*J$4/I$4,IF($E45="Tuition Index",I45*J$5/I$5,IF($E45="% of Salaries",IF($G$6=0,0,$G45/$G$6*J$6),IF($E45="Debt",$G45*Inputs!F$15/12,IF($E45="Reserve Yield",Inputs!F$13*Inputs!F$16,IF($E45="Trend",I45*(1+Inputs!F$12),I45)))))))))))) -> 0 | K45: =IF($E45="Manual",O45,IF($E45="Flat",J45,IF($E45="Inflation",J45*(1+Inputs!G$12),IF($E45="Salary",J45*(1+Inputs!G$10),IF($E45="Benefits",J45*(1+Inputs!G$11),IF($E45="Per Student",J45*K$4/J$4*(1+Inputs!G$12),IF($E45="Enrollment",J45*K$4/J$4,IF($E45="Tuition Index",J45*K$5/J$5,IF($E45="% of Salaries",IF($G$6=0,0,$G45/$G$6*K$6),IF($E45="Debt",$G45*Inputs!G$15/12,IF($E45="Reserve Yield",Inputs!G$13*Inputs!G$16,IF($E45="Trend",J45*(1+Inputs!G$12),J45)))))))))))) -> 0
... A188: Expense | B188: Other Expense | C188: Development Expenses | D188: Development Expenses | E188: Flat | F188: Even | G188: =SUMIFS('QB Import'!$B$1:$B$600,'QB Import'!$H$1:$H$600,$C188,'QB Import'!$G$1:$G$600,1) -> 0 | H188: =IF($E188="Manual",L188,IF($E188="Flat",G188,IF($E188="Inflation",G188*(1+Inputs!D$12),IF($E188="Salary",G188*(1+Inputs!D$10),IF($E188="Benefits",G188*(1+Inputs!D$11),IF($E188="Per Student",G188*H$4/G$4*(1+Inputs!D$12),IF($E188="Enrollment",G188*H$4/G$4,IF($E188="Tuition Index",G188*H$5/G$5,IF($E188="% of Salaries",IF($G$6=0,0,$G188/$G$6*H$6),IF($E188="Debt",$G188*Inputs!D$15/12,IF($E188="Reserve Yield",Inputs!D$13*Inputs!D$16,IF($E188="Trend",IF(ISNUMBER(Trend!$Q227),Trend!$Q227,G188),G188)))))))))))) -> 0 | I188: =IF($E188="Manual",M188,IF($E188="Flat",H188,IF($E188="Inflation",H188*(1+Inputs!E$12),IF($E188="Salary",H188*(1+Inputs!E$10),IF($E188="Benefits",H188*(1+Inputs!E$11),IF($E188="Per Student",H188*I$4/H$4*(1+Inputs!E$12),IF($E188="Enrollment",H188*I$4/H$4,IF($E188="Tuition Index",H188*I$5/H$5,IF($E188="% of Salaries",IF($G$6=0,0,$G188/$G$6*I$6),IF($E188="Debt",$G188*Inputs!E$15/12,IF($E188="Reserve Yield",Inputs!E$13*Inputs!E$16,IF($E188="Trend",H188*(1+Inputs!E$12),H188)))))))))))) -> 0 | J188: =IF($E188="Manual",N188,IF($E188="Flat",I188,IF($E188="Inflation",I188*(1+Inputs!F$12),IF($E188="Salary",I188*(1+Inputs!F$10),IF($E188="Benefits",I188*(1+Inputs!F$11),IF($E188="Per Student",I188*J$4/I$4*(1+Inputs!F$12),IF($E188="Enrollment",I188*J$4/I$4,IF($E188="Tuition Index",I188*J$5/I$5,IF($E188="% of Salaries",IF($G$6=0,0,$G188/$G$6*J$6),IF($E188="Debt",$G188*Inputs!F$15/12,IF($E188="Reserve Yield",Inputs!F$13*Inputs!F$16,IF($E188="Trend",I188*(1+Inputs!F$12),I188)))))))))))) -> 0 | K188: =IF($E188="Manual",O188,IF($E188="Flat",J188,IF($E188="Inflation",J188*(1+Inputs!G$12),IF($E188="Salary",J188*(1+Inputs!G$10),IF($E188="Benefits",J188*(1+Inputs!G$11),IF($E188="Per Student",J188*K$4/J$4*(1+Inputs!G$12),IF($E188="Enrollment",J188*K$4/J$4,IF($E188="Tuition Index",J188*K$5/J$5,IF($E188="% of Salaries",IF($G$6=0,0,$G188/$G$6*K$6),IF($E188="Debt",$G188*Inputs!G$15/12,IF($E188="Reserve Yield",Inputs!G$13*Inputs!G$16,IF($E188="Trend",J188*(1+Inputs!G$12),J188)))))))))))) -> 0
A190: To add an account: insert a row above this note (inside the table), fill columns A:F, copy G:K formulas down from the row above.

Sheet Trend
A1: PRIOR-YEAR TRENDS & RECOMMENDED BUDGET
A2: Load up to 5 years of actuals on Actuals Import. Four trend methods are computed for every account; the selected one becomes the recommendation.
A3: Years of actuals loaded | B3: =COUNT(B4:F4) -> 0 | C3: First year | D3: =IF(B3=0,"",MIN(B4:F4)) | E3: Latest year | F3: =IF(B3=0,"",MAX(B4:F4)) | G3: Target year | H3: =YEAR(Inputs!$D$5) -> 2028
A4: Fiscal year ending (from Inputs) | B4: =IF(ISNUMBER(Inputs!$C$85),Inputs!$C$85,"") | C4: =IF(ISNUMBER(Inputs!$C$86),Inputs!$C$86,"") | D4: =IF(ISNUMBER(Inputs!$C$87),Inputs!$C$87,"") | E4: =IF(ISNUMBER(Inputs!$C$88),Inputs!$C$88,"") | F4: =IF(ISNUMBER(Inputs!$C$89),Inputs!$C$89,"")
A5: Major category | B5: =IF(ISNUMBER(B$4),"FY"&RIGHT(B$4,2)&" Actual","(unused)") -> (unused) | C5: =IF(ISNUMBER(C$4),"FY"&RIGHT(C$4,2)&" Actual","(unused)") -> (unused) | D5: =IF(ISNUMBER(D$4),"FY"&RIGHT(D$4,2)&" Actual","(unused)") -> (unused) | E5: =IF(ISNUMBER(E$4),"FY"&RIGHT(E$4,2)&" Actual","(unused)") -> (unused) | F5: =IF(ISNUMBER(F$4),"FY"&RIGHT(F$4,2)&" Actual","(unused)") -> (unused) | G5: =Inputs!C$4&" Budget" -> FY27 Budget | H5: =Inputs!D$4&" Fcst" -> FY28 Fcst | I5: =Inputs!E$4&" Fcst" -> FY29 Fcst | J5: =Inputs!F$4&" Fcst" -> FY30 Fcst | K5: =Inputs!G$4&" Fcst" -> FY31 Fcst | L5: Avg annual growth (actuals) | M5: FY27 budget vs last actual
A6: 1 Tuition and Fees | B6: =IF(ISNUMBER(B$4),SUMIFS('Actuals Import'!$B$1:$B$600,'Actuals Import'!$F$1:$F$600,$A6,'Actuals Import'!$G$1:$G$600,1),"") | C6: =IF(ISNUMBER(C$4),SUMIFS('Actuals Import'!$K$1:$K$600,'Actuals Import'!$O$1:$O$600,$A6,'Actuals Import'!$P$1:$P$600,1),"") | D6: =IF(ISNUMBER(D$4),SUMIFS('Actuals Import'!$T$1:$T$600,'Actuals Import'!$X$1:$X$600,$A6,'Actuals Import'!$Y$1:$Y$600,1),"") | E6: =IF(ISNUMBER(E$4),SUMIFS('Actuals Import'!$AC$1:$AC$600,'Actuals Import'!$AG$1:$AG$600,$A6,'Actuals Import'!$AH$1:$AH$600,1),"") | F6: =IF(ISNUMBER(F$4),SUMIFS('Actuals Import'!$AL$1:$AL$600,'Actuals Import'!$AP$1:$AP$600,$A6,'Actuals Import'!$AQ$1:$AQ$600,1),"") | G6: =Summary!B11 -> 8799382 | H6: =Summary!C11 -> 9300918.4 | I6: =Summary!D11 -> 9629546.3 | J6: =Summary!E11 -> 9941469.6 | K6: =Summary!F11 -> 10246937 | L6: =IF(OR($B$3<2,$F$3=$D$3),"",IFERROR(IF(INDEX($B6:$F6,MATCH($D$3,$B$4:$F$4,0))*INDEX($B6:$F6,MATCH($F$3,$B$4:$F$4,0))>0,(INDEX($B6:$F6,MATCH($F$3,$B$4:$F$4,0))/INDEX($B6:$F6,MATCH($D$3,$B$4:$F$4,0)))^(1/($F$3-$D$3))-1,""),"")) | M6: =IF($B$3=0,"",IF(INDEX($B6:$F6,MATCH($F$3,$B$4:$F$4,0))=0,"",$G6/INDEX($B6:$F6,MATCH($F$3,$B$4:$F$4,0))-1))
A7: 2 Interest and Other Income | B7: =IF(ISNUMBER(B$4),SUMIFS('Actuals Import'!$B$1:$B$600,'Actuals Import'!$F$1:$F$600,$A7,'Actuals Import'!$G$1:$G$600,1),"") | C7: =IF(ISNUMBER(C$4),SUMIFS('Actuals Import'!$K$1:$K$600,'Actuals Import'!$O$1:$O$600,$A7,'Actuals Import'!$P$1:$P$600,1),"") | D7: =IF(ISNUMBER(D$4),SUMIFS('Actuals Import'!$T$1:$T$600,'Actuals Import'!$X$1:$X$600,$A7,'Actuals Import'!$Y$1:$Y$600,1),"") | E7: =IF(ISNUMBER(E$4),SUMIFS('Actuals Import'!$AC$1:$AC$600,'Actuals Import'!$AG$1:$AG$600,$A7,'Actuals Import'!$AH$1:$AH$600,1),"") | F7: =IF(ISNUMBER(F$4),SUMIFS('Actuals Import'!$AL$1:$AL$600,'Actuals Import'!$AP$1:$AP$600,$A7,'Actuals Import'!$AQ$1:$AQ$600,1),"") | G7: =Summary!B12 -> 445000 | H7: =Summary!C12 -> 394005.03 | I7: =Summary!D12 -> 344005.03 | J7: =Summary!E12 -> 344005.03 | K7: =Summary!F12 -> 344005.03 | L7: =IF(OR($B$3<2,$F$3=$D$3),"",IFERROR(IF(INDEX($B7:$F7,MATCH($D$3,$B$4:$F$4,0))*INDEX($B7:$F7,MATCH($F$3,$B$4:$F$4,0))>0,(INDEX($B7:$F7,MATCH($F$3,$B$4:$F$4,0))/INDEX($B7:$F7,MATCH($D$3,$B$4:$F$4,0)))^(1/($F$3-$D$3))-1,""),"")) | M7: =IF($B$3=0,"",IF(INDEX($B7:$F7,MATCH($F$3,$B$4:$F$4,0))=0,"",$G7/INDEX($B7:$F7,MATCH($F$3,$B$4:$F$4,0))-1))
A8: 4 Other Miscellaneous Income | B8: =IF(ISNUMBER(B$4),SUMIFS('Actuals Import'!$B$1:$B$600,'Actuals Import'!$F$1:$F$600,$A8,'Actuals Import'!$G$1:$G$600,1),"") | C8: =IF(ISNUMBER(C$4),SUMIFS('Actuals Import'!$K$1:$K$600,'Actuals Import'!$O$1:$O$600,$A8,'Actuals Import'!$P$1:$P$600,1),"") | D8: =IF(ISNUMBER(D$4),SUMIFS('Actuals Import'!$T$1:$T$600,'Actuals Import'!$X$1:$X$600,$A8,'Actuals Import'!$Y$1:$Y$600,1),"") | E8: =IF(ISNUMBER(E$4),SUMIFS('Actuals Import'!$AC$1:$AC$600,'Actuals Import'!$AG$1:$AG$600,$A8,'Actuals Import'!$AH$1:$AH$600,1),"") | F8: =IF(ISNUMBER(F$4),SUMIFS('Actuals Import'!$AL$1:$AL$600,'Actuals Import'!$AP$1:$AP$600,$A8,'Actuals Import'!$AQ$1:$AQ$600,1),"") | G8: =Summary!B13 -> 60000 | H8: =Summary!C13 -> 60000 | I8: =Summary!D13 -> 60000 | J8: =Summary!E13 -> 60000 | K8: =Summary!F13 -> 60000 | L8: =IF(OR($B$3<2,$F$3=$D$3),"",IFERROR(IF(INDEX($B8:$F8,MATCH($D$3,$B$4:$F$4,0))*INDEX($B8:$F8,MATCH($F$3,$B$4:$F$4,0))>0,(INDEX($B8:$F8,MATCH($F$3,$B$4:$F$4,0))/INDEX($B8:$F8,MATCH($D$3,$B$4:$F$4,0)))^(1/($F$3-$D$3))-1,""),"")) | M8: =IF($B$3=0,"",IF(INDEX($B8:$F8,MATCH($F$3,$B$4:$F$4,0))=0,"",$G8/INDEX($B8:$F8,MATCH($F$3,$B$4:$F$4,0))-1))
A9: 5 Athletic Income | B9: =IF(ISNUMBER(B$4),SUMIFS('Actuals Import'!$B$1:$B$600,'Actuals Import'!$F$1:$F$600,$A9,'Actuals Import'!$G$1:$G$600,1),"") | C9: =IF(ISNUMBER(C$4),SUMIFS('Actuals Import'!$K$1:$K$600,'Actuals Import'!$O$1:$O$600,$A9,'Actuals Import'!$P$1:$P$600,1),"") | D9: =IF(ISNUMBER(D$4),SUMIFS('Actuals Import'!$T$1:$T$600,'Actuals Import'!$X$1:$X$600,$A9,'Actuals Import'!$Y$1:$Y$600,1),"") | E9: =IF(ISNUMBER(E$4),SUMIFS('Actuals Import'!$AC$1:$AC$600,'Actuals Import'!$AG$1:$AG$600,$A9,'Actuals Import'!$AH$1:$AH$600,1),"") | F9: =IF(ISNUMBER(F$4),SUMIFS('Actuals Import'!$AL$1:$AL$600,'Actuals Import'!$AP$1:$AP$600,$A9,'Actuals Import'!$AQ$1:$AQ$600,1),"") | G9: =Summary!B14 -> 0 | H9: =Summary!C14 -> 0 | I9: =Summary!D14 -> 0 | J9: =Summary!E14 -> 0 | K9: =Summary!F14 -> 0 | L9: =IF(OR($B$3<2,$F$3=$D$3),"",IFERROR(IF(INDEX($B9:$F9,MATCH($D$3,$B$4:$F$4,0))*INDEX($B9:$F9,MATCH($F$3,$B$4:$F$4,0))>0,(INDEX($B9:$F9,MATCH($F$3,$B$4:$F$4,0))/INDEX($B9:$F9,MATCH($D$3,$B$4:$F$4,0)))^(1/($F$3-$D$3))-1,""),"")) | M9: =IF($B$3=0,"",IF(INDEX($B9:$F9,MATCH($F$3,$B$4:$F$4,0))=0,"",$G9/INDEX($B9:$F9,MATCH($F$3,$B$4:$F$4,0))-1))
A10: Total Revenue | B10: =IF(ISNUMBER(B$4),SUM(B6:B9),"") | C10: =IF(ISNUMBER(C$4),SUM(C6:C9),"") | D10: =IF(ISNUMBER(D$4),SUM(D6:D9),"") | E10: =IF(ISNUMBER(E$4),SUM(E6:E9),"") | F10: =IF(ISNUMBER(F$4),SUM(F6:F9),"") | G10: =Summary!B15 -> 9304382 | H10: =Summary!C15 -> 9754923.5 | I10: =Summary!D15 -> 10033551 | J10: =Summary!E15 -> 10345475 | K10: =Summary!F15 -> 10650942 | L10: =IF(OR($B$3<2,$F$3=$D$3),"",IFERROR(IF(INDEX($B10:$F10,MATCH($D$3,$B$4:$F$4,0))*INDEX($B10:$F10,MATCH($F$3,$B$4:$F$4,0))>0,(INDEX($B10:$F10,MATCH($F$3,$B$4:$F$4,0))/INDEX($B10:$F10,MATCH($D$3,$B$4:$F$4,0)))^(1/($F$3-$D$3))-1,""),"")) | M10: =IF($B$3=0,"",IF(INDEX($B10:$F10,MATCH($F$3,$B$4:$F$4,0))=0,"",$G10/INDEX($B10:$F10,MATCH($F$3,$B$4:$F$4,0))-1))
A11: 1 Salaries and Benefits | B11: =IF(ISNUMBER(B$4),SUMIFS('Actuals Import'!$B$1:$B$600,'Actuals Import'!$F$1:$F$600,$A11,'Actuals Import'!$G$1:$G$600,1),"") | C11: =IF(ISNUMBER(C$4),SUMIFS('Actuals Import'!$K$1:$K$600,'Actuals Import'!$O$1:$O$600,$A11,'Actuals Import'!$P$1:$P$600,1),"") | D11: =IF(ISNUMBER(D$4),SUMIFS('Actuals Import'!$T$1:$T$600,'Actuals Import'!$X$1:$X$600,$A11,'Actuals Import'!$Y$1:$Y$600,1),"") | E11: =IF(ISNUMBER(E$4),SUMIFS('Actuals Import'!$AC$1:$AC$600,'Actuals Import'!$AG$1:$AG$600,$A11,'Actuals Import'!$AH$1:$AH$600,1),"") | F11: =IF(ISNUMBER(F$4),SUMIFS('Actuals Import'!$AL$1:$AL$600,'Actuals Import'!$AP$1:$AP$600,$A11,'Actuals Import'!$AQ$1:$AQ$600,1),"") | G11: =Summary!B18 -> 6253109 | H11: =Summary!C18 -> 6455524.8 | I11: =Summary!D18 -> 6653066.2 | J11: =Summary!E18 -> 6854595.5 | K11: =Summary!F18 -> 7061481.9 | L11: =IF(OR($B$3<2,$F$3=$D$3),"",IFERROR(IF(INDEX($B11:$F11,MATCH($D$3,$B$4:$F$4,0))*INDEX($B11:$F11,MATCH($F$3,$B$4:$F$4,0))>0,(INDEX($B11:$F11,MATCH($F$3,$B$4:$F$4,0))/INDEX($B11:$F11,MATCH($D$3,$B$4:$F$4,0)))^(1/($F$3-$D$3))-1,""),"")) | M11: =IF($B$3=0,"",IF(INDEX($B11:$F11,MATCH($F$3,$B$4:$F$4,0))=0,"",$G11/INDEX($B11:$F11,MATCH($F$3,$B$4:$F$4,0))-1))
A12: 2 Instructional Expenses | B12: =IF(ISNUMBER(B$4),SUMIFS('Actuals Import'!$B$1:$B$600,'Actuals Import'!$F$1:$F$600,$A12,'Actuals Import'!$G$1:$G$600,1),"") | C12: =IF(ISNUMBER(C$4),SUMIFS('Actuals Import'!$K$1:$K$600,'Actuals Import'!$O$1:$O$600,$A12,'Actuals Import'!$P$1:$P$600,1),"") | D12: =IF(ISNUMBER(D$4),SUMIFS('Actuals Import'!$T$1:$T$600,'Actuals Import'!$X$1:$X$600,$A12,'Actuals Import'!$Y$1:$Y$600,1),"") | E12: =IF(ISNUMBER(E$4),SUMIFS('Actuals Import'!$AC$1:$AC$600,'Actuals Import'!$AG$1:$AG$600,$A12,'Actuals Import'!$AH$1:$AH$600,1),"") | F12: =IF(ISNUMBER(F$4),SUMIFS('Actuals Import'!$AL$1:$AL$600,'Actuals Import'!$AP$1:$AP$600,$A12,'Actuals Import'!$AQ$1:$AQ$600,1),"") | G12: =Summary!B19 -> 252750 | H12: =Summary!C19 -> 260332.5 | I12: =Summary!D19 -> 268142.47 | J12: =Summary!E19 -> 276186.75 | K12: =Summary!F19 -> 284472.35 | L12: =IF(OR($B$3<2,$F$3=$D$3),"",IFERROR(IF(INDEX($B12:$F12,MATCH($D$3,$B$4:$F$4,0))*INDEX($B12:$F12,MATCH($F$3,$B$4:$F$4,0))>0,(INDEX($B12:$F12,MATCH($F$3,$B$4:$F$4,0))/INDEX($B12:$F12,MATCH($D$3,$B$4:$F$4,0)))^(1/($F$3-$D$3))-1,""),"")) | M12: =IF($B$3=0,"",IF(INDEX($B12:$F12,MATCH($F$3,$B$4:$F$4,0))=0,"",$G12/INDEX($B12:$F12,MATCH($F$3,$B$4:$F$4,0))-1))
A13: 3 Operations | B13: =IF(ISNUMBER(B$4),SUMIFS('Actuals Import'!$B$1:$B$600,'Actuals Import'!$F$1:$F$600,$A13,'Actuals Import'!$G$1:$G$600,1),"") | C13: =IF(ISNUMBER(C$4),SUMIFS('Actuals Import'!$K$1:$K$600,'Actuals Import'!$O$1:$O$600,$A13,'Actuals Import'!$P$1:$P$600,1),"") | D13: =IF(ISNUMBER(D$4),SUMIFS('Actuals Import'!$T$1:$T$600,'Actuals Import'!$X$1:$X$600,$A13,'Actuals Import'!$Y$1:$Y$600,1),"") | E13: =IF(ISNUMBER(E$4),SUMIFS('Actuals Import'!$AC$1:$AC$600,'Actuals Import'!$AG$1:$AG$600,$A13,'Actuals Import'!$AH$1:$AH$600,1),"") | F13: =IF(ISNUMBER(F$4),SUMIFS('Actuals Import'!$AL$1:$AL$600,'Actuals Import'!$AP$1:$AP$600,$A13,'Actuals Import'!$AQ$1:$AQ$600,1),"") | G13: =Summary!B20 -> 1847250 | H13: =Summary!C20 -> 1914294.8 | I13: =Summary!D20 -> 1967731.6 | J13: =Summary!E20 -> 2019910.6 | K13: =Summary!F20 -> 2074861 | L13: =IF(OR($B$3<2,$F$3=$D$3),"",IFERROR(IF(INDEX($B13:$F13,MATCH($D$3,$B$4:$F$4,0))*INDEX($B13:$F13,MATCH($F$3,$B$4:$F$4,0))>0,(INDEX($B13:$F13,MATCH($F$3,$B$4:$F$4,0))/INDEX($B13:$F13,MATCH($D$3,$B$4:$F$4,0)))^(1/($F$3-$D$3))-1,""),"")) | M13: =IF($B$3=0,"",IF(INDEX($B13:$F13,MATCH($F$3,$B$4:$F$4,0))=0,"",$G13/INDEX($B13:$F13,MATCH($F$3,$B$4:$F$4,0))-1))
A14: 4 Administrative | B14: =IF(ISNUMBER(B$4),SUMIFS('Actuals Import'!$B$1:$B$600,'Actuals Import'!$F$1:$F$600,$A14,'Actuals Import'!$G$1:$G$600,1),"") | C14: =IF(ISNUMBER(C$4),SUMIFS('Actuals Import'!$K$1:$K$600,'Actuals Import'!$O$1:$O$600,$A14,'Actuals Import'!$P$1:$P$600,1),"") | D14: =IF(ISNUMBER(D$4),SUMIFS('Actuals Import'!$T$1:$T$600,'Actuals Import'!$X$1:$X$600,$A14,'Actuals Import'!$Y$1:$Y$600,1),"") | E14: =IF(ISNUMBER(E$4),SUMIFS('Actuals Import'!$AC$1:$AC$600,'Actuals Import'!$AG$1:$AG$600,$A14,'Actuals Import'!$AH$1:$AH$600,1),"") | F14: =IF(ISNUMBER(F$4),SUMIFS('Actuals Import'!$AL$1:$AL$600,'Actuals Import'!$AP$1:$AP$600,$A14,'Actuals Import'!$AQ$1:$AQ$600,1),"") | G14: =Summary!B21 -> 778368 | H14: =Summary!C21 -> 795138.74 | I14: =Summary!D21 -> 810947.37 | J14: =Summary!E21 -> 703223.52 | K14: =Summary!F21 -> 658007.96 | L14: =IF(OR($B$3<2,$F$3=$D$3),"",IFERROR(IF(INDEX($B14:$F14,MATCH($D$3,$B$4:$F$4,0))*INDEX($B14:$F14,MATCH($F$3,$B$4:$F$4,0))>0,(INDEX($B14:$F14,MATCH($F$3,$B$4:$F$4,0))/INDEX($B14:$F14,MATCH($D$3,$B$4:$F$4,0)))^(1/($F$3-$D$3))-1,""),"")) | M14: =IF($B$3=0,"",IF(INDEX($B14:$F14,MATCH($F$3,$B$4:$F$4,0))=0,"",$G14/INDEX($B14:$F14,MATCH($F$3,$B$4:$F$4,0))-1))
A15: 5 Athletic Expenses | B15: =IF(ISNUMBER(B$4),SUMIFS('Actuals Import'!$B$1:$B$600,'Actuals Import'!$F$1:$F$600,$A15,'Actuals Import'!$G$1:$G$600,1),"") | C15: =IF(ISNUMBER(C$4),SUMIFS('Actuals Import'!$K$1:$K$600,'Actuals Import'!$O$1:$O$600,$A15,'Actuals Import'!$P$1:$P$600,1),"") | D15: =IF(ISNUMBER(D$4),SUMIFS('Actuals Import'!$T$1:$T$600,'Actuals Import'!$X$1:$X$600,$A15,'Actuals Import'!$Y$1:$Y$600,1),"") | E15: =IF(ISNUMBER(E$4),SUMIFS('Actuals Import'!$AC$1:$AC$600,'Actuals Import'!$AG$1:$AG$600,$A15,'Actuals Import'!$AH$1:$AH$600,1),"") | F15: =IF(ISNUMBER(F$4),SUMIFS('Actuals Import'!$AL$1:$AL$600,'Actuals Import'!$AP$1:$AP$600,$A15,'Actuals Import'!$AQ$1:$AQ$600,1),"") | G15: =Summary!B22 -> 171263 | H15: =Summary!C22 -> 176400.89 | I15: =Summary!D22 -> 181692.92 | J15: =Summary!E22 -> 187143.7 | K15: =Summary!F22 -> 192758.02 | L15: =IF(OR($B$3<2,$F$3=$D$3),"",IFERROR(IF(INDEX($B15:$F15,MATCH($D$3,$B$4:$F$4,0))*INDEX($B15:$F15,MATCH($F$3,$B$4:$F$4,0))>0,(INDEX($B15:$F15,MATCH($F$3,$B$4:$F$4,0))/INDEX($B15:$F15,MATCH($D$3,$B$4:$F$4,0)))^(1/($F$3-$D$3))-1,""),"")) | M15: =IF($B$3=0,"",IF(INDEX($B15:$F15,MATCH($F$3,$B$4:$F$4,0))=0,"",$G15/INDEX($B15:$F15,MATCH($F$3,$B$4:$F$4,0))-1))
A16: Strategic Plan Initiatives | G16: =Summary!B23 -> 0 | H16: =Summary!C23 -> 50000 | I16: =Summary!D23 -> 100000 | J16: =Summary!E23 -> 150000 | K16: =Summary!F23 -> 200000
A17: Total Expenses | B17: =IF(ISNUMBER(B$4),SUM(B11:B15),"") | C17: =IF(ISNUMBER(C$4),SUM(C11:C15),"") | D17: =IF(ISNUMBER(D$4),SUM(D11:D15),"") | E17: =IF(ISNUMBER(E$4),SUM(E11:E15),"") | F17: =IF(ISNUMBER(F$4),SUM(F11:F15),"") | G17: =Summary!B24 -> 9302740 | H17: =Summary!C24 -> 9651691.8 | I17: =Summary!D24 -> 9981580.5 | J17: =Summary!E24 -> 10191060 | K17: =Summary!F24 -> 10471581 | L17: =IF(OR($B$3<2,$F$3=$D$3),"",IFERROR(IF(INDEX($B17:$F17,MATCH($D$3,$B$4:$F$4,0))*INDEX($B17:$F17,MATCH($F$3,$B$4:$F$4,0))>0,(INDEX($B17:$F17,MATCH($F$3,$B$4:$F$4,0))/INDEX($B17:$F17,MATCH($D$3,$B$4:$F$4,0)))^(1/($F$3-$D$3))-1,""),"")) | M17: =IF($B$3=0,"",IF(INDEX($B17:$F17,MATCH($F$3,$B$4:$F$4,0))=0,"",$G17/INDEX($B17:$F17,MATCH($F$3,$B$4:$F$4,0))-1))
A18: Net Operating Revenue | B18: =IF(ISNUMBER(B$4),B10-B17,"") | C18: =IF(ISNUMBER(C$4),C10-C17,"") | D18: =IF(ISNUMBER(D$4),D10-D17,"") | E18: =IF(ISNUMBER(E$4),E10-E17,"") | F18: =IF(ISNUMBER(F$4),F10-F17,"") | G18: =Summary!B26 -> 1642 | H18: =Summary!C26 -> 103231.68 | I18: =Summary!D26 -> 51970.772 | J18: =Summary!E26 -> 154414.65 | K18: =Summary!F26 -> 179360.91
A19: Forecast columns come from the Summary tab; forecast totals include Strategic Plan Initiatives.
A41: Chart data (do not edit) | B41: =B5 -> (unused) | C41: =C5 -> (unused) | D41: =D5 -> (unused) | E41: =E5 -> (unused) | F41: =F5 -> (unused) | G41: =G5 -> FY27 Budget | H41: =H5 -> FY28 Fcst | I41: =I5 -> FY29 Fcst | ... K41: =K5 -> FY31 Fcst
A42: Total Revenue | B42: =IF(ISNUMBER(B10),B10,NA()) -> #N/A | C42: =IF(ISNUMBER(C10),C10,NA()) -> #N/A | D42: =IF(ISNUMBER(D10),D10,NA()) -> #N/A | E42: =IF(ISNUMBER(E10),E10,NA()) -> #N/A | F42: =IF(ISNUMBER(F10),F10,NA()) -> #N/A | G42: =IF(ISNUMBER(G10),G10,NA()) -> 9304382 | H42: =IF(ISNUMBER(H10),H10,NA()) -> 9754923.5 | I42: =IF(ISNUMBER(I10),I10,NA()) -> 10033551 | ... K42: =IF(ISNUMBER(K10),K10,NA()) -> 10650942
A43: Total Expenses | B43: =IF(ISNUMBER(B17),B17,NA()) -> #N/A | C43: =IF(ISNUMBER(C17),C17,NA()) -> #N/A | D43: =IF(ISNUMBER(D17),D17,NA()) -> #N/A | E43: =IF(ISNUMBER(E17),E17,NA()) -> #N/A | F43: =IF(ISNUMBER(F17),F17,NA()) -> #N/A | G43: =IF(ISNUMBER(G17),G17,NA()) -> 9302740 | H43: =IF(ISNUMBER(H17),H17,NA()) -> 9651691.8 | I43: =IF(ISNUMBER(I17),I17,NA()) -> 9981580.5 | ... K43: =IF(ISNUMBER(K17),K17,NA()) -> 10471581
A45: Account-level trend and recommendation
A46: Description | B46: Type | C46: Key | D46: Major category | E46: =B$5 -> (unused) | F46: =C$5 -> (unused) | G46: =D$5 -> (unused) | H46: =E$5 -> (unused) | I46: =F$5 -> (unused) | J46: =Inputs!C$4&" Budget" -> FY27 Budget | K46: Last actual | L46: Average | M46: Linear trend | N46: Growth-based | O46: Override method | P46: Method used | Q46: ="Recommended "&Inputs!D$4 -> Recommended FY28 | R46: ="Model "&Inputs!D$4 -> Model FY28 | S46: Rec vs FY27 budget | T46: Flag
A47: ='Forecast Detail'!D8 -> 400186 Tuition Income | B47: ='Forecast Detail'!A8 -> Revenue | C47: ='Forecast Detail'!C8 -> 400186 | D47: ='Forecast Detail'!B8 -> 1 Tuition and Fees | E47: =IF(ISNUMBER(B$4),SUMIFS('Actuals Import'!$B$1:$B$600,'Actuals Import'!$H$1:$H$600,$C47,'Actuals Import'!$G$1:$G$600,1),"") | F47: =IF(ISNUMBER(C$4),SUMIFS('Actuals Import'!$K$1:$K$600,'Actuals Import'!$Q$1:$Q$600,$C47,'Actuals Import'!$P$1:$P$600,1),"") | G47: =IF(ISNUMBER(D$4),SUMIFS('Actuals Import'!$T$1:$T$600,'Actuals Import'!$Z$1:$Z$600,$C47,'Actuals Import'!$Y$1:$Y$600,1),"") | H47: =IF(ISNUMBER(E$4),SUMIFS('Actuals Import'!$AC$1:$AC$600,'Actuals Import'!$AI$1:$AI$600,$C47,'Actuals Import'!$AH$1:$AH$600,1),"") | I47: =IF(ISNUMBER(F$4),SUMIFS('Actuals Import'!$AL$1:$AL$600,'Actuals Import'!$AR$1:$AR$600,$C47,'Actuals Import'!$AQ$1:$AQ$600,1),"") | J47: ='Forecast Detail'!G8 -> 7858980 | K47: =IF($B$3=0,"",INDEX($E47:$I47,MATCH($F$3,$B$4:$F$4,0))) | L47: =IF($B$3=0,"",AVERAGE($E47:$I47)) | M47: =IF($B$3<3,"",IFERROR(FORECAST($H$3,$E47:$I47,$B$4:$F$4),"")) | N47: =IF($B$3<2,"",IFERROR(IF(INDEX($E47:$I47,MATCH($D$3,$B$4:$F$4,0))*K47>0,K47*(K47/INDEX($E47:$I47,MATCH($D$3,$B$4:$F$4,0)))^(($H$3-$F$3)/($F$3-$D$3)),K47),K47)) | P47: =IF(O47<>"",O47,Inputs!$C$90) -> Linear Trend | Q47: =IF($B$3=0,"",IF(Inputs!$C$91>0,ROUND(IF(ISNUMBER(IF(P47="Last Actual",K47,IF(P47="Average",L47,IF(P47="Linear Trend",M47,N47)))),IF(P47="Last Actual",K47,IF(P47="Average",L47,IF(P47="Linear Trend",M47,N47))),K47)/Inputs!$C$91,0)*Inputs!$C$91,IF(ISNUMBER(IF(P47="Last Actual",K47,IF(P47="Average",L47,IF(P47="Linear Trend",M47,N47)))),IF(P47="Last Actual",K47,IF(P47="Average",L47,IF(P47="Linear Trend",M47,N47))),K47))) | R47: ='Forecast Detail'!H8 -> 8452157.2 | S47: =IF(Q47="","",IF(J47=0,"",Q47/J47-1)) | T47: =IF(S47="","",IF(ABS(S47)>Inputs!$C$92,"REVIEW",""))
A48: ='Forecast Detail'!D9 -> 400187 Scholarship for Kids Tuition | B48: ='Forecast Detail'!A9 -> Revenue | C48: ='Forecast Detail'!C9 -> 400187 | D48: ='Forecast Detail'!B9 -> 1 Tuition and Fees | E48: =IF(ISNUMBER(B$4),SUMIFS('Actuals Import'!$B$1:$B$600,'Actuals Import'!$H$1:$H$600,$C48,'Actuals Import'!$G$1:$G$600,1),"") | F48: =IF(ISNUMBER(C$4),SUMIFS('Actuals Import'!$K$1:$K$600,'Actuals Import'!$Q$1:$Q$600,$C48,'Actuals Import'!$P$1:$P$600,1),"") | G48: =IF(ISNUMBER(D$4),SUMIFS('Actuals Import'!$T$1:$T$600,'Actuals Import'!$Z$1:$Z$600,$C48,'Actuals Import'!$Y$1:$Y$600,1),"") | H48: =IF(ISNUMBER(E$4),SUMIFS('Actuals Import'!$AC$1:$AC$600,'Actuals Import'!$AI$1:$AI$600,$C48,'Actuals Import'!$AH$1:$AH$600,1),"") | I48: =IF(ISNUMBER(F$4),SUMIFS('Actuals Import'!$AL$1:$AL$600,'Actuals Import'!$AR$1:$AR$600,$C48,'Actuals Import'!$AQ$1:$AQ$600,1),"") | J48: ='Forecast Detail'!G9 -> 410000 | K48: =IF($B$3=0,"",INDEX($E48:$I48,MATCH($F$3,$B$4:$F$4,0))) | L48: =IF($B$3=0,"",AVERAGE($E48:$I48)) | M48: =IF($B$3<3,"",IFERROR(FORECAST($H$3,$E48:$I48,$B$4:$F$4),"")) | N48: =IF($B$3<2,"",IFERROR(IF(INDEX($E48:$I48,MATCH($D$3,$B$4:$F$4,0))*K48>0,K48*(K48/INDEX($E48:$I48,MATCH($D$3,$B$4:$F$4,0)))^(($H$3-$F$3)/($F$3-$D$3)),K48),K48)) | P48: =IF(O48<>"",O48,Inputs!$C$90) -> Linear Trend | Q48: =IF($B$3=0,"",IF(Inputs!$C$91>0,ROUND(IF(ISNUMBER(IF(P48="Last Actual",K48,IF(P48="Average",L48,IF(P48="Linear Trend",M48,N48)))),IF(P48="Last Actual",K48,IF(P48="Average",L48,IF(P48="Linear Trend",M48,N48))),K48)/Inputs!$C$91,0)*Inputs!$C$91,IF(ISNUMBER(IF(P48="Last Actual",K48,IF(P48="Average",L48,IF(P48="Linear Trend",M48,N48)))),IF(P48="Last Actual",K48,IF(P48="Average",L48,IF(P48="Linear Trend",M48,N48))),K48))) | R48: ='Forecast Detail'!H9 -> 380000 | S48: =IF(Q48="","",IF(J48=0,"",Q48/J48-1)) | T48: =IF(S48="","",IF(ABS(S48)>Inputs!$C$92,"REVIEW",""))
A49: ='Forecast Detail'!D10 -> 400188 Choose Act Tuition | B49: ='Forecast Detail'!A10 -> Revenue | C49: ='Forecast Detail'!C10 -> 400188 | D49: ='Forecast Detail'!B10 -> 1 Tuition and Fees | E49: =IF(ISNUMBER(B$4),SUMIFS('Actuals Import'!$B$1:$B$600,'Actuals Import'!$H$1:$H$600,$C49,'Actuals Import'!$G$1:$G$600,1),"") | F49: =IF(ISNUMBER(C$4),SUMIFS('Actuals Import'!$K$1:$K$600,'Actuals Import'!$Q$1:$Q$600,$C49,'Actuals Import'!$P$1:$P$600,1),"") | G49: =IF(ISNUMBER(D$4),SUMIFS('Actuals Import'!$T$1:$T$600,'Actuals Import'!$Z$1:$Z$600,$C49,'Actuals Import'!$Y$1:$Y$600,1),"") | H49: =IF(ISNUMBER(E$4),SUMIFS('Actuals Import'!$AC$1:$AC$600,'Actuals Import'!$AI$1:$AI$600,$C49,'Actuals Import'!$AH$1:$AH$600,1),"") | I49: =IF(ISNUMBER(F$4),SUMIFS('Actuals Import'!$AL$1:$AL$600,'Actuals Import'!$AR$1:$AR$600,$C49,'Actuals Import'!$AQ$1:$AQ$600,1),"") | J49: ='Forecast Detail'!G10 -> 616000 | K49: =IF($B$3=0,"",INDEX($E49:$I49,MATCH($F$3,$B$4:$F$4,0))) | L49: =IF($B$3=0,"",AVERAGE($E49:$I49)) | M49: =IF($B$3<3,"",IFERROR(FORECAST($H$3,$E49:$I49,$B$4:$F$4),"")) | N49: =IF($B$3<2,"",IFERROR(IF(INDEX($E49:$I49,MATCH($D$3,$B$4:$F$4,0))*K49>0,K49*(K49/INDEX($E49:$I49,MATCH($D$3,$B$4:$F$4,0)))^(($H$3-$F$3)/($F$3-$D$3)),K49),K49)) | P49: =IF(O49<>"",O49,Inputs!$C$90) -> Linear Trend | Q49: =IF($B$3=0,"",IF(Inputs!$C$91>0,ROUND(IF(ISNUMBER(IF(P49="Last Actual",K49,IF(P49="Average",L49,IF(P49="Linear Trend",M49,N49)))),IF(P49="Last Actual",K49,IF(P49="Average",L49,IF(P49="Linear Trend",M49,N49))),K49)/Inputs!$C$91,0)*Inputs!$C$91,IF(ISNUMBER(IF(P49="Last Actual",K49,IF(P49="Average",L49,IF(P49="Linear Trend",M49,N49)))),IF(P49="Last Actual",K49,IF(P49="Average",L49,IF(P49="Linear Trend",M49,N49))),K49))) | R49: ='Forecast Detail'!H10 -> 616000 | S49: =IF(Q49="","",IF(J49=0,"",Q49/J49-1)) | T49: =IF(S49="","",IF(ABS(S49)>Inputs!$C$92,"REVIEW",""))
A50: ='Forecast Detail'!D11 -> 400189 AOSF Tuition | B50: ='Forecast Detail'!A11 -> Revenue | C50: ='Forecast Detail'!C11 -> 400189 | D50: ='Forecast Detail'!B11 -> 1 Tuition and Fees | E50: =IF(ISNUMBER(B$4),SUMIFS('Actuals Import'!$B$1:$B$600,'Actuals Import'!$H$1:$H$600,$C50,'Actuals Import'!$G$1:$G$600,1),"") | F50: =IF(ISNUMBER(C$4),SUMIFS('Actuals Import'!$K$1:$K$600,'Actuals Import'!$Q$1:$Q$600,$C50,'Actuals Import'!$P$1:$P$600,1),"") | G50: =IF(ISNUMBER(D$4),SUMIFS('Actuals Import'!$T$1:$T$600,'Actuals Import'!$Z$1:$Z$600,$C50,'Actuals Import'!$Y$1:$Y$600,1),"") | H50: =IF(ISNUMBER(E$4),SUMIFS('Actuals Import'!$AC$1:$AC$600,'Actuals Import'!$AI$1:$AI$600,$C50,'Actuals Import'!$AH$1:$AH$600,1),"") | I50: =IF(ISNUMBER(F$4),SUMIFS('Actuals Import'!$AL$1:$AL$600,'Actuals Import'!$AR$1:$AR$600,$C50,'Actuals Import'!$AQ$1:$AQ$600,1),"") | J50: ='Forecast Detail'!G11 -> 0 | K50: =IF($B$3=0,"",INDEX($E50:$I50,MATCH($F$3,$B$4:$F$4,0))) | L50: =IF($B$3=0,"",AVERAGE($E50:$I50)) | M50: =IF($B$3<3,"",IFERROR(FORECAST($H$3,$E50:$I50,$B$4:$F$4),"")) | N50: =IF($B$3<2,"",IFERROR(IF(INDEX($E50:$I50,MATCH($D$3,$B$4:$F$4,0))*K50>0,K50*(K50/INDEX($E50:$I50,MATCH($D$3,$B$4:$F$4,0)))^(($H$3-$F$3)/($F$3-$D$3)),K50),K50)) | P50: =IF(O50<>"",O50,Inputs!$C$90) -> Linear Trend | Q50: =IF($B$3=0,"",IF(Inputs!$C$91>0,ROUND(IF(ISNUMBER(IF(P50="Last Actual",K50,IF(P50="Average",L50,IF(P50="Linear Trend",M50,N50)))),IF(P50="Last Actual",K50,IF(P50="Average",L50,IF(P50="Linear Trend",M50,N50))),K50)/Inputs!$C$91,0)*Inputs!$C$91,IF(ISNUMBER(IF(P50="Last Actual",K50,IF(P50="Average",L50,IF(P50="Linear Trend",M50,N50)))),IF(P50="Last Actual",K50,IF(P50="Average",L50,IF(P50="Linear Trend",M50,N50))),K50))) | R50: ='Forecast Detail'!H11 -> 0 | S50: =IF(Q50="","",IF(J50=0,"",Q50/J50-1)) | T50: =IF(S50="","",IF(ABS(S50)>Inputs!$C$92,"REVIEW",""))
A51: ='Forecast Detail'!D12 -> 400180 Building Fees | B51: ='Forecast Detail'!A12 -> Revenue | C51: ='Forecast Detail'!C12 -> 400180 | D51: ='Forecast Detail'!B12 -> 1 Tuition and Fees | E51: =IF(ISNUMBER(B$4),SUMIFS('Actuals Import'!$B$1:$B$600,'Actuals Import'!$H$1:$H$600,$C51,'Actuals Import'!$G$1:$G$600,1),"") | F51: =IF(ISNUMBER(C$4),SUMIFS('Actuals Import'!$K$1:$K$600,'Actuals Import'!$Q$1:$Q$600,$C51,'Actuals Import'!$P$1:$P$600,1),"") | G51: =IF(ISNUMBER(D$4),SUMIFS('Actuals Import'!$T$1:$T$600,'Actuals Import'!$Z$1:$Z$600,$C51,'Actuals Import'!$Y$1:$Y$600,1),"") | H51: =IF(ISNUMBER(E$4),SUMIFS('Actuals Import'!$AC$1:$AC$600,'Actuals Import'!$AI$1:$AI$600,$C51,'Actuals Import'!$AH$1:$AH$600,1),"") | I51: =IF(ISNUMBER(F$4),SUMIFS('Actuals Import'!$AL$1:$AL$600,'Actuals Import'!$AR$1:$AR$600,$C51,'Actuals Import'!$AQ$1:$AQ$600,1),"") | J51: ='Forecast Detail'!G12 -> 35000 | K51: =IF($B$3=0,"",INDEX($E51:$I51,MATCH($F$3,$B$4:$F$4,0))) | L51: =IF($B$3=0,"",AVERAGE($E51:$I51)) | M51: =IF($B$3<3,"",IFERROR(FORECAST($H$3,$E51:$I51,$B$4:$F$4),"")) | N51: =IF($B$3<2,"",IFERROR(IF(INDEX($E51:$I51,MATCH($D$3,$B$4:$F$4,0))*K51>0,K51*(K51/INDEX($E51:$I51,MATCH($D$3,$B$4:$F$4,0)))^(($H$3-$F$3)/($F$3-$D$3)),K51),K51)) | P51: =IF(O51<>"",O51,Inputs!$C$90) -> Linear Trend | Q51: =IF($B$3=0,"",IF(Inputs!$C$91>0,ROUND(IF(ISNUMBER(IF(P51="Last Actual",K51,IF(P51="Average",L51,IF(P51="Linear Trend",M51,N51)))),IF(P51="Last Actual",K51,IF(P51="Average",L51,IF(P51="Linear Trend",M51,N51))),K51)/Inputs!$C$91,0)*Inputs!$C$91,IF(ISNUMBER(IF(P51="Last Actual",K51,IF(P51="Average",L51,IF(P51="Linear Trend",M51,N51)))),IF(P51="Last Actual",K51,IF(P51="Average",L51,IF(P51="Linear Trend",M51,N51))),K51))) | R51: ='Forecast Detail'!H12 -> 0 | S51: =IF(Q51="","",IF(J51=0,"",Q51/J51-1)) | T51: =IF(S51="","",IF(ABS(S51)>Inputs!$C$92,"REVIEW",""))
A52: ='Forecast Detail'!D13 -> 400181 Enrollment Fees | B52: ='Forecast Detail'!A13 -> Revenue | C52: ='Forecast Detail'!C13 -> 400181 | D52: ='Forecast Detail'!B13 -> 1 Tuition and Fees | E52: =IF(ISNUMBER(B$4),SUMIFS('Actuals Import'!$B$1:$B$600,'Actuals Import'!$H$1:$H$600,$C52,'Actuals Import'!$G$1:$G$600,1),"") | F52: =IF(ISNUMBER(C$4),SUMIFS('Actuals Import'!$K$1:$K$600,'Actuals Import'!$Q$1:$Q$600,$C52,'Actuals Import'!$P$1:$P$600,1),"") | G52: =IF(ISNUMBER(D$4),SUMIFS('Actuals Import'!$T$1:$T$600,'Actuals Import'!$Z$1:$Z$600,$C52,'Actuals Import'!$Y$1:$Y$600,1),"") | H52: =IF(ISNUMBER(E$4),SUMIFS('Actuals Import'!$AC$1:$AC$600,'Actuals Import'!$AI$1:$AI$600,$C52,'Actuals Import'!$AH$1:$AH$600,1),"") | I52: =IF(ISNUMBER(F$4),SUMIFS('Actuals Import'!$AL$1:$AL$600,'Actuals Import'!$AR$1:$AR$600,$C52,'Actuals Import'!$AQ$1:$AQ$600,1),"") | J52: ='Forecast Detail'!G13 -> 162300 | K52: =IF($B$3=0,"",INDEX($E52:$I52,MATCH($F$3,$B$4:$F$4,0))) | L52: =IF($B$3=0,"",AVERAGE($E52:$I52)) | M52: =IF($B$3<3,"",IFERROR(FORECAST($H$3,$E52:$I52,$B$4:$F$4),"")) | N52: =IF($B$3<2,"",IFERROR(IF(INDEX($E52:$I52,MATCH($D$3,$B$4:$F$4,0))*K52>0,K52*(K52/INDEX($E52:$I52,MATCH($D$3,$B$4:$F$4,0)))^(($H$3-$F$3)/($F$3-$D$3)),K52),K52)) | P52: =IF(O52<>"",O52,Inputs!$C$90) -> Linear Trend | Q52: =IF($B$3=0,"",IF(Inputs!$C$91>0,ROUND(IF(ISNUMBER(IF(P52="Last Actual",K52,IF(P52="Average",L52,IF(P52="Linear Trend",M52,N52)))),IF(P52="Last Actual",K52,IF(P52="Average",L52,IF(P52="Linear Trend",M52,N52))),K52)/Inputs!$C$91,0)*Inputs!$C$91,IF(ISNUMBER(IF(P52="Last Actual",K52,IF(P52="Average",L52,IF(P52="Linear Trend",M52,N52)))),IF(P52="Last Actual",K52,IF(P52="Average",L52,IF(P52="Linear Trend",M52,N52))),K52))) | R52: ='Forecast Detail'!H13 -> 164809.79 | S52: =IF(Q52="","",IF(J52=0,"",Q52/J52-1)) | T52: =IF(S52="","",IF(ABS(S52)>Inputs!$C$92,"REVIEW",""))
A53: ='Forecast Detail'!D14 -> 400183 Tuition Insurance Income | B53: ='Forecast Detail'!A14 -> Revenue | C53: ='Forecast Detail'!C14 -> 400183 | D53: ='Forecast Detail'!B14 -> 1 Tuition and Fees | E53: =IF(ISNUMBER(B$4),SUMIFS('Actuals Import'!$B$1:$B$600,'Actuals Import'!$H$1:$H$600,$C53,'Actuals Import'!$G$1:$G$600,1),"") | F53: =IF(ISNUMBER(C$4),SUMIFS('Actuals Import'!$K$1:$K$600,'Actuals Import'!$Q$1:$Q$600,$C53,'Actuals Import'!$P$1:$P$600,1),"") | G53: =IF(ISNUMBER(D$4),SUMIFS('Actuals Import'!$T$1:$T$600,'Actuals Import'!$Z$1:$Z$600,$C53,'Actuals Import'!$Y$1:$Y$600,1),"") | H53: =IF(ISNUMBER(E$4),SUMIFS('Actuals Import'!$AC$1:$AC$600,'Actuals Import'!$AI$1:$AI$600,$C53,'Actuals Import'!$AH$1:$AH$600,1),"") | I53: =IF(ISNUMBER(F$4),SUMIFS('Actuals Import'!$AL$1:$AL$600,'Actuals Import'!$AR$1:$AR$600,$C53,'Actuals Import'!$AQ$1:$AQ$600,1),"") | J53: ='Forecast Detail'!G14 -> 139000 | K53: =IF($B$3=0,"",INDEX($E53:$I53,MATCH($F$3,$B$4:$F$4,0))) | L53: =IF($B$3=0,"",AVERAGE($E53:$I53)) | M53: =IF($B$3<3,"",IFERROR(FORECAST($H$3,$E53:$I53,$B$4:$F$4),"")) | N53: =IF($B$3<2,"",IFERROR(IF(INDEX($E53:$I53,MATCH($D$3,$B$4:$F$4,0))*K53>0,K53*(K53/INDEX($E53:$I53,MATCH($D$3,$B$4:$F$4,0)))^(($H$3-$F$3)/($F$3-$D$3)),K53),K53)) | P53: =IF(O53<>"",O53,Inputs!$C$90) -> Linear Trend | Q53: =IF($B$3=0,"",IF(Inputs!$C$91>0,ROUND(IF(ISNUMBER(IF(P53="Last Actual",K53,IF(P53="Average",L53,IF(P53="Linear Trend",M53,N53)))),IF(P53="Last Actual",K53,IF(P53="Average",L53,IF(P53="Linear Trend",M53,N53))),K53)/Inputs!$C$91,0)*Inputs!$C$91,IF(ISNUMBER(IF(P53="Last Actual",K53,IF(P53="Average",L53,IF(P53="Linear Trend",M53,N53)))),IF(P53="Last Actual",K53,IF(P53="Average",L53,IF(P53="Linear Trend",M53,N53))),K53))) | R53: ='Forecast Detail'!H14 -> 141149.48 | S53: =IF(Q53="","",IF(J53=0,"",Q53/J53-1)) | T53: =IF(S53="","",IF(ABS(S53)>Inputs!$C$92,"REVIEW",""))
A54: ='Forecast Detail'!D15 -> 400184 Application Fees | B54: ='Forecast Detail'!A15 -> Revenue | C54: ='Forecast Detail'!C15 -> 400184 | D54: ='Forecast Detail'!B15 -> 1 Tuition and Fees | E54: =IF(ISNUMBER(B$4),SUMIFS('Actuals Import'!$B$1:$B$600,'Actuals Import'!$H$1:$H$600,$C54,'Actuals Import'!$G$1:$G$600,1),"") | F54: =IF(ISNUMBER(C$4),SUMIFS('Actuals Import'!$K$1:$K$600,'Actuals Import'!$Q$1:$Q$600,$C54,'Actuals Import'!$P$1:$P$600,1),"") | G54: =IF(ISNUMBER(D$4),SUMIFS('Actuals Import'!$T$1:$T$600,'Actuals Import'!$Z$1:$Z$600,$C54,'Actuals Import'!$Y$1:$Y$600,1),"") | H54: =IF(ISNUMBER(E$4),SUMIFS('Actuals Import'!$AC$1:$AC$600,'Actuals Import'!$AI$1:$AI$600,$C54,'Actuals Import'!$AH$1:$AH$600,1),"") | I54: =IF(ISNUMBER(F$4),SUMIFS('Actuals Import'!$AL$1:$AL$600,'Actuals Import'!$AR$1:$AR$600,$C54,'Actuals Import'!$AQ$1:$AQ$600,1),"") | J54: ='Forecast Detail'!G15 -> 0 | K54: =IF($B$3=0,"",INDEX($E54:$I54,MATCH($F$3,$B$4:$F$4,0))) | L54: =IF($B$3=0,"",AVERAGE($E54:$I54)) | M54: =IF($B$3<3,"",IFERROR(FORECAST($H$3,$E54:$I54,$B$4:$F$4),"")) | N54: =IF($B$3<2,"",IFERROR(IF(INDEX($E54:$I54,MATCH($D$3,$B$4:$F$4,0))*K54>0,K54*(K54/INDEX($E54:$I54,MATCH($D$3,$B$4:$F$4,0)))^(($H$3-$F$3)/($F$3-$D$3)),K54),K54)) | P54: =IF(O54<>"",O54,Inputs!$C$90) -> Linear Trend | Q54: =IF($B$3=0,"",IF(Inputs!$C$91>0,ROUND(IF(ISNUMBER(IF(P54="Last Actual",K54,IF(P54="Average",L54,IF(P54="Linear Trend",M54,N54)))),IF(P54="Last Actual",K54,IF(P54="Average",L54,IF(P54="Linear Trend",M54,N54))),K54)/Inputs!$C$91,0)*Inputs!$C$91,IF(ISNUMBER(IF(P54="Last Actual",K54,IF(P54="Average",L54,IF(P54="Linear Trend",M54,N54)))),IF(P54="Last Actual",K54,IF(P54="Average",L54,IF(P54="Linear Trend",M54,N54))),K54))) | R54: ='Forecast Detail'!H15 -> 0 | S54: =IF(Q54="","",IF(J54=0,"",Q54/J54-1)) | T54: =IF(S54="","",IF(ABS(S54)>Inputs!$C$92,"REVIEW",""))
A55: ='Forecast Detail'!D16 -> 400185 Enrollment Fee Waived - Alumni Credit | B55: ='Forecast Detail'!A16 -> Revenue | C55: ='Forecast Detail'!C16 -> 400185 | D55: ='Forecast Detail'!B16 -> 1 Tuition and Fees | E55: =IF(ISNUMBER(B$4),SUMIFS('Actuals Import'!$B$1:$B$600,'Actuals Import'!$H$1:$H$600,$C55,'Actuals Import'!$G$1:$G$600,1),"") | F55: =IF(ISNUMBER(C$4),SUMIFS('Actuals Import'!$K$1:$K$600,'Actuals Import'!$Q$1:$Q$600,$C55,'Actuals Import'!$P$1:$P$600,1),"") | G55: =IF(ISNUMBER(D$4),SUMIFS('Actuals Import'!$T$1:$T$600,'Actuals Import'!$Z$1:$Z$600,$C55,'Actuals Import'!$Y$1:$Y$600,1),"") | H55: =IF(ISNUMBER(E$4),SUMIFS('Actuals Import'!$AC$1:$AC$600,'Actuals Import'!$AI$1:$AI$600,$C55,'Actuals Import'!$AH$1:$AH$600,1),"") | I55: =IF(ISNUMBER(F$4),SUMIFS('Actuals Import'!$AL$1:$AL$600,'Actuals Import'!$AR$1:$AR$600,$C55,'Actuals Import'!$AQ$1:$AQ$600,1),"") | J55: ='Forecast Detail'!G16 -> 0 | K55: =IF($B$3=0,"",INDEX($E55:$I55,MATCH($F$3,$B$4:$F$4,0))) | L55: =IF($B$3=0,"",AVERAGE($E55:$I55)) | M55: =IF($B$3<3,"",IFERROR(FORECAST($H$3,$E55:$I55,$B$4:$F$4),"")) | N55: =IF($B$3<2,"",IFERROR(IF(INDEX($E55:$I55,MATCH($D$3,$B$4:$F$4,0))*K55>0,K55*(K55/INDEX($E55:$I55,MATCH($D$3,$B$4:$F$4,0)))^(($H$3-$F$3)/($F$3-$D$3)),K55),K55)) | P55: =IF(O55<>"",O55,Inputs!$C$90) -> Linear Trend | Q55: =IF($B$3=0,"",IF(Inputs!$C$91>0,ROUND(IF(ISNUMBER(IF(P55="Last Actual",K55,IF(P55="Average",L55,IF(P55="Linear Trend",M55,N55)))),IF(P55="Last Actual",K55,IF(P55="Average",L55,IF(P55="Linear Trend",M55,N55))),K55)/Inputs!$C$91,0)*Inputs!$C$91,IF(ISNUMBER(IF(P55="Last Actual",K55,IF(P55="Average",L55,IF(P55="Linear Trend",M55,N55)))),IF(P55="Last Actual",K55,IF(P55="Average",L55,IF(P55="Linear Trend",M55,N55))),K55))) | R55: ='Forecast Detail'!H16 -> 0 | S55: =IF(Q55="","",IF(J55=0,"",Q55/J55-1)) | T55: =IF(S55="","",IF(ABS(S55)>Inputs!$C$92,"REVIEW",""))
A56: ='Forecast Detail'!D17 -> 400199 Fee - Tuition Discount | B56: ='Forecast Detail'!A17 -> Revenue | C56: ='Forecast Detail'!C17 -> 400199 | D56: ='Forecast Detail'!B17 -> 1 Tuition and Fees | E56: =IF(ISNUMBER(B$4),SUMIFS('Actuals Import'!$B$1:$B$600,'Actuals Import'!$H$1:$H$600,$C56,'Actuals Import'!$G$1:$G$600,1),"") | F56: =IF(ISNUMBER(C$4),SUMIFS('Actuals Import'!$K$1:$K$600,'Actuals Import'!$Q$1:$Q$600,$C56,'Actuals Import'!$P$1:$P$600,1),"") | G56: =IF(ISNUMBER(D$4),SUMIFS('Actuals Import'!$T$1:$T$600,'Actuals Import'!$Z$1:$Z$600,$C56,'Actuals Import'!$Y$1:$Y$600,1),"") | H56: =IF(ISNUMBER(E$4),SUMIFS('Actuals Import'!$AC$1:$AC$600,'Actuals Import'!$AI$1:$AI$600,$C56,'Actuals Import'!$AH$1:$AH$600,1),"") | I56: =IF(ISNUMBER(F$4),SUMIFS('Actuals Import'!$AL$1:$AL$600,'Actuals Import'!$AR$1:$AR$600,$C56,'Actuals Import'!$AQ$1:$AQ$600,1),"") | J56: ='Forecast Detail'!G17 -> 0 | K56: =IF($B$3=0,"",INDEX($E56:$I56,MATCH($F$3,$B$4:$F$4,0))) | L56: =IF($B$3=0,"",AVERAGE($E56:$I56)) | M56: =IF($B$3<3,"",IFERROR(FORECAST($H$3,$E56:$I56,$B$4:$F$4),"")) | N56: =IF($B$3<2,"",IFERROR(IF(INDEX($E56:$I56,MATCH($D$3,$B$4:$F$4,0))*K56>0,K56*(K56/INDEX($E56:$I56,MATCH($D$3,$B$4:$F$4,0)))^(($H$3-$F$3)/($F$3-$D$3)),K56),K56)) | P56: =IF(O56<>"",O56,Inputs!$C$90) -> Linear Trend | Q56: =IF($B$3=0,"",IF(Inputs!$C$91>0,ROUND(IF(ISNUMBER(IF(P56="Last Actual",K56,IF(P56="Average",L56,IF(P56="Linear Trend",M56,N56)))),IF(P56="Last Actual",K56,IF(P56="Average",L56,IF(P56="Linear Trend",M56,N56))),K56)/Inputs!$C$91,0)*Inputs!$C$91,IF(ISNUMBER(IF(P56="Last Actual",K56,IF(P56="Average",L56,IF(P56="Linear Trend",M56,N56)))),IF(P56="Last Actual",K56,IF(P56="Average",L56,IF(P56="Linear Trend",M56,N56))),K56))) | R56: ='Forecast Detail'!H17 -> 0 | S56: =IF(Q56="","",IF(J56=0,"",Q56/J56-1)) | T56: =IF(S56="","",IF(ABS(S56)>Inputs!$C$92,"REVIEW",""))
A57: ='Forecast Detail'!D18 -> 400201 Referral Fee - Tuition Discount | B57: ='Forecast Detail'!A18 -> Revenue | C57: ='Forecast Detail'!C18 -> 400201 | D57: ='Forecast Detail'!B18 -> 1 Tuition and Fees | E57: =IF(ISNUMBER(B$4),SUMIFS('Actuals Import'!$B$1:$B$600,'Actuals Import'!$H$1:$H$600,$C57,'Actuals Import'!$G$1:$G$600,1),"") | F57: =IF(ISNUMBER(C$4),SUMIFS('Actuals Import'!$K$1:$K$600,'Actuals Import'!$Q$1:$Q$600,$C57,'Actuals Import'!$P$1:$P$600,1),"") | G57: =IF(ISNUMBER(D$4),SUMIFS('Actuals Import'!$T$1:$T$600,'Actuals Import'!$Z$1:$Z$600,$C57,'Actuals Import'!$Y$1:$Y$600,1),"") | H57: =IF(ISNUMBER(E$4),SUMIFS('Actuals Import'!$AC$1:$AC$600,'Actuals Import'!$AI$1:$AI$600,$C57,'Actuals Import'!$AH$1:$AH$600,1),"") | I57: =IF(ISNUMBER(F$4),SUMIFS('Actuals Import'!$AL$1:$AL$600,'Actuals Import'!$AR$1:$AR$600,$C57,'Actuals Import'!$AQ$1:$AQ$600,1),"") | J57: ='Forecast Detail'!G18 -> 0 | K57: =IF($B$3=0,"",INDEX($E57:$I57,MATCH($F$3,$B$4:$F$4,0))) | L57: =IF($B$3=0,"",AVERAGE($E57:$I57)) | M57: =IF($B$3<3,"",IFERROR(FORECAST($H$3,$E57:$I57,$B$4:$F$4),"")) | N57: =IF($B$3<2,"",IFERROR(IF(INDEX($E57:$I57,MATCH($D$3,$B$4:$F$4,0))*K57>0,K57*(K57/INDEX($E57:$I57,MATCH($D$3,$B$4:$F$4,0)))^(($H$3-$F$3)/($F$3-$D$3)),K57),K57)) | P57: =IF(O57<>"",O57,Inputs!$C$90) -> Linear Trend | Q57: =IF($B$3=0,"",IF(Inputs!$C$91>0,ROUND(IF(ISNUMBER(IF(P57="Last Actual",K57,IF(P57="Average",L57,IF(P57="Linear Trend",M57,N57)))),IF(P57="Last Actual",K57,IF(P57="Average",L57,IF(P57="Linear Trend",M57,N57))),K57)/Inputs!$C$91,0)*Inputs!$C$91,IF(ISNUMBER(IF(P57="Last Actual",K57,IF(P57="Average",L57,IF(P57="Linear Trend",M57,N57)))),IF(P57="Last Actual",K57,IF(P57="Average",L57,IF(P57="Linear Trend",M57,N57))),K57))) | R57: ='Forecast Detail'!H18 -> 0 | S57: =IF(Q57="","",IF(J57=0,"",Q57/J57-1)) | T57: =IF(S57="","",IF(ABS(S57)>Inputs!$C$92,"REVIEW",""))
A58: ='Forecast Detail'!D19 -> 400126 Late Fees | B58: ='Forecast Detail'!A19 -> Revenue | C58: ='Forecast Detail'!C19 -> 400126 | D58: ='Forecast Detail'!B19 -> 1 Tuition and Fees | E58: =IF(ISNUMBER(B$4),SUMIFS('Actuals Import'!$B$1:$B$600,'Actuals Import'!$H$1:$H$600,$C58,'Actuals Import'!$G$1:$G$600,1),"") | F58: =IF(ISNUMBER(C$4),SUMIFS('Actuals Import'!$K$1:$K$600,'Actuals Import'!$Q$1:$Q$600,$C58,'Actuals Import'!$P$1:$P$600,1),"") | G58: =IF(ISNUMBER(D$4),SUMIFS('Actuals Import'!$T$1:$T$600,'Actuals Import'!$Z$1:$Z$600,$C58,'Actuals Import'!$Y$1:$Y$600,1),"") | H58: =IF(ISNUMBER(E$4),SUMIFS('Actuals Import'!$AC$1:$AC$600,'Actuals Import'!$AI$1:$AI$600,$C58,'Actuals Import'!$AH$1:$AH$600,1),"") | I58: =IF(ISNUMBER(F$4),SUMIFS('Actuals Import'!$AL$1:$AL$600,'Actuals Import'!$AR$1:$AR$600,$C58,'Actuals Import'!$AQ$1:$AQ$600,1),"") | J58: ='Forecast Detail'!G19 -> 9300 | K58: =IF($B$3=0,"",INDEX($E58:$I58,MATCH($F$3,$B$4:$F$4,0))) | L58: =IF($B$3=0,"",AVERAGE($E58:$I58)) | M58: =IF($B$3<3,"",IFERROR(FORECAST($H$3,$E58:$I58,$B$4:$F$4),"")) | N58: =IF($B$3<2,"",IFERROR(IF(INDEX($E58:$I58,MATCH($D$3,$B$4:$F$4,0))*K58>0,K58*(K58/INDEX($E58:$I58,MATCH($D$3,$B$4:$F$4,0)))^(($H$3-$F$3)/($F$3-$D$3)),K58),K58)) | P58: =IF(O58<>"",O58,Inputs!$C$90) -> Linear Trend | Q58: =IF($B$3=0,"",IF(Inputs!$C$91>0,ROUND(IF(ISNUMBER(IF(P58="Last Actual",K58,IF(P58="Average",L58,IF(P58="Linear Trend",M58,N58)))),IF(P58="Last Actual",K58,IF(P58="Average",L58,IF(P58="Linear Trend",M58,N58))),K58)/Inputs!$C$91,0)*Inputs!$C$91,IF(ISNUMBER(IF(P58="Last Actual",K58,IF(P58="Average",L58,IF(P58="Linear Trend",M58,N58)))),IF(P58="Last Actual",K58,IF(P58="Average",L58,IF(P58="Linear Trend",M58,N58))),K58))) | R58: ='Forecast Detail'!H19 -> 3000 | S58: =IF(Q58="","",IF(J58=0,"",Q58/J58-1)) | T58: =IF(S58="","",IF(ABS(S58)>Inputs!$C$92,"REVIEW",""))
... A227: ='Forecast Detail'!D188 -> Development Expenses | B227: ='Forecast Detail'!A188 -> Expense | C227: ='Forecast Detail'!C188 -> Development Expenses | D227: ='Forecast Detail'!B188 -> Other Expense | E227: =IF(ISNUMBER(B$4),SUMIFS('Actuals Import'!$B$1:$B$600,'Actuals Import'!$H$1:$H$600,$C227,'Actuals Import'!$G$1:$G$600,1),"") | F227: =IF(ISNUMBER(C$4),SUMIFS('Actuals Import'!$K$1:$K$600,'Actuals Import'!$Q$1:$Q$600,$C227,'Actuals Import'!$P$1:$P$600,1),"") | G227: =IF(ISNUMBER(D$4),SUMIFS('Actuals Import'!$T$1:$T$600,'Actuals Import'!$Z$1:$Z$600,$C227,'Actuals Import'!$Y$1:$Y$600,1),"") | H227: =IF(ISNUMBER(E$4),SUMIFS('Actuals Import'!$AC$1:$AC$600,'Actuals Import'!$AI$1:$AI$600,$C227,'Actuals Import'!$AH$1:$AH$600,1),"") | I227: =IF(ISNUMBER(F$4),SUMIFS('Actuals Import'!$AL$1:$AL$600,'Actuals Import'!$AR$1:$AR$600,$C227,'Actuals Import'!$AQ$1:$AQ$600,1),"") | J227: ='Forecast Detail'!G188 -> 0 | K227: =IF($B$3=0,"",INDEX($E227:$I227,MATCH($F$3,$B$4:$F$4,0))) | L227: =IF($B$3=0,"",AVERAGE($E227:$I227)) | M227: =IF($B$3<3,"",IFERROR(FORECAST($H$3,$E227:$I227,$B$4:$F$4),"")) | N227: =IF($B$3<2,"",IFERROR(IF(INDEX($E227:$I227,MATCH($D$3,$B$4:$F$4,0))*K227>0,K227*(K227/INDEX($E227:$I227,MATCH($D$3,$B$4:$F$4,0)))^(($H$3-$F$3)/($F$3-$D$3)),K227),K227)) | P227: =IF(O227<>"",O227,Inputs!$C$90) -> Linear Trend | Q227: =IF($B$3=0,"",IF(Inputs!$C$91>0,ROUND(IF(ISNUMBER(IF(P227="Last Actual",K227,IF(P227="Average",L227,IF(P227="Linear Trend",M227,N227)))),IF(P227="Last Actual",K227,IF(P227="Average",L227,IF(P227="Linear Trend",M227,N227))),K227)/Inputs!$C$91,0)*Inputs!$C$91,IF(ISNUMBER(IF(P227="Last Actual",K227,IF(P227="Average",L227,IF(P227="Linear Trend",M227,N227)))),IF(P227="Last Actual",K227,IF(P227="Average",L227,IF(P227="Linear Trend",M227,N227))),K227))) | R227: ='Forecast Detail'!H188 -> 0 | S227: =IF(Q227="","",IF(J227=0,"",Q227/J227-1)) | T227: =IF(S227="","",IF(ABS(S227)>Inputs!$C$92,"REVIEW",""))

Sheet Cash Flow
A1: MONTHLY CASH FLOW - 5 YEARS
A2: Month ending | B2: =EOMONTH(Inputs!$C$6,0) -> 46234 | C2: =EOMONTH(B2,1) -> 46265 | D2: =EOMONTH(C2,1) -> 46295 | E2: =EOMONTH(D2,1) -> 46326 | F2: =EOMONTH(E2,1) -> 46356 | G2: =EOMONTH(F2,1) -> 46387 | H2: =EOMONTH(G2,1) -> 46418 | I2: =EOMONTH(H2,1) -> 46446 | J2: =EOMONTH(I2,1) -> 46477 | ... BI2: =EOMONTH(BH2,1) -> 48029
A3: Fiscal year # | B3: 1 | C3: 1 | D3: 1 | E3: 1 | F3: 1 | G3: 1 | H3: 1 | I3: 1 | J3: 1 | K3: 1 | L3: 1 | M3: 1 | N3: 2 | O3: 2 | P3: 2 | Q3: 2 | R3: 2 | S3: 2 | T3: 2 | U3: 2 | V3: 2 | W3: 2 | X3: 2 | Y3: 2 | Z3: 3 | AA3: 3 | AB3: 3 | AC3: 3 | AD3: 3 | AE3: 3 | AF3: 3 | AG3: 3 | AH3: 3 | AI3: 3 | AJ3: 3 | AK3: 3 | AL3: 4 | AM3: 4 | AN3: 4 | AO3: 4 | AP3: 4 | AQ3: 4 | AR3: 4 | AS3: 4 | AT3: 4 | AU3: 4 | AV3: 4 | AW3: 4 | AX3: 5 | AY3: 5 | AZ3: 5 | BA3: 5 | BB3: 5 | BC3: 5 | BD3: 5 | BE3: 5 | BF3: 5 | BG3: 5 | BH3: 5 | BI3: 5
A4: Fiscal month # (1 = July) | B4: 1 | C4: 2 | D4: 3 | E4: 4 | F4: 5 | G4: 6 | H4: 7 | I4: 8 | J4: 9 | K4: 10 | L4: 11 | M4: 12 | N4: 1 | O4: 2 | P4: 3 | Q4: 4 | R4: 5 | S4: 6 | T4: 7 | U4: 8 | V4: 9 | W4: 10 | X4: 11 | Y4: 12 | Z4: 1 | AA4: 2 | AB4: 3 | AC4: 4 | AD4: 5 | AE4: 6 | AF4: 7 | AG4: 8 | AH4: 9 | AI4: 10 | AJ4: 11 | AK4: 12 | AL4: 1 | AM4: 2 | AN4: 3 | AO4: 4 | AP4: 5 | AQ4: 6 | AR4: 7 | AS4: 8 | AT4: 9 | AU4: 10 | AV4: 11 | AW4: 12 | AX4: 1 | AY4: 2 | AZ4: 3 | BA4: 4 | BB4: 5 | BC4: 6 | BD4: 7 | BE4: 8 | BF4: 9 | BG4: 10 | BH4: 11 | BI4: 12
A5: Fiscal year | B5: ="FY"&TEXT(INDEX(Inputs!$C$5:$G$5,B$3),"yy") -> FY27 | C5: ="FY"&TEXT(INDEX(Inputs!$C$5:$G$5,C$3),"yy") -> FY27 | D5: ="FY"&TEXT(INDEX(Inputs!$C$5:$G$5,D$3),"yy") -> FY27 | E5: ="FY"&TEXT(INDEX(Inputs!$C$5:$G$5,E$3),"yy") -> FY27 | F5: ="FY"&TEXT(INDEX(Inputs!$C$5:$G$5,F$3),"yy") -> FY27 | G5: ="FY"&TEXT(INDEX(Inputs!$C$5:$G$5,G$3),"yy") -> FY27 | H5: ="FY"&TEXT(INDEX(Inputs!$C$5:$G$5,H$3),"yy") -> FY27 | I5: ="FY"&TEXT(INDEX(Inputs!$C$5:$G$5,I$3),"yy") -> FY27 | ... BI5: ="FY"&TEXT(INDEX(Inputs!$C$5:$G$5,BI$3),"yy") -> FY31
A7: CASH RECEIPTS (by timing profile)
A8: Tuition Plan | B8: =INDEX('CF Summary'!$B$22:$G$22,B$3)*INDEX(Inputs!$B$76:$O$76,B$4+2)+IF(B$4=11,INDEX('CF Summary'!$B$22:$G$22,B$3+1)*INDEX(Inputs!$B$76:$O$76,1),0)+IF(B$4=12,INDEX('CF Summary'!$B$22:$G$22,B$3+1)*INDEX(Inputs!$B$76:$O$76,2),0) -> 479452.33 | C8: =INDEX('CF Summary'!$B$22:$G$22,C$3)*INDEX(Inputs!$B$76:$O$76,C$4+2)+IF(C$4=11,INDEX('CF Summary'!$B$22:$G$22,C$3+1)*INDEX(Inputs!$B$76:$O$76,1),0)+IF(C$4=12,INDEX('CF Summary'!$B$22:$G$22,C$3+1)*INDEX(Inputs!$B$76:$O$76,2),0) -> 838107.58 | D8: =INDEX('CF Summary'!$B$22:$G$22,D$3)*INDEX(Inputs!$B$76:$O$76,D$4+2)+IF(D$4=11,INDEX('CF Summary'!$B$22:$G$22,D$3+1)*INDEX(Inputs!$B$76:$O$76,1),0)+IF(D$4=12,INDEX('CF Summary'!$B$22:$G$22,D$3+1)*INDEX(Inputs!$B$76:$O$76,2),0) -> 479452.33 | E8: =INDEX('CF Summary'!$B$22:$G$22,E$3)*INDEX(Inputs!$B$76:$O$76,E$4+2)+IF(E$4=11,INDEX('CF Summary'!$B$22:$G$22,E$3+1)*INDEX(Inputs!$B$76:$O$76,1),0)+IF(E$4=12,INDEX('CF Summary'!$B$22:$G$22,E$3+1)*INDEX(Inputs!$B$76:$O$76,2),0) -> 479452.33 | F8: =INDEX('CF Summary'!$B$22:$G$22,F$3)*INDEX(Inputs!$B$76:$O$76,F$4+2)+IF(F$4=11,INDEX('CF Summary'!$B$22:$G$22,F$3+1)*INDEX(Inputs!$B$76:$O$76,1),0)+IF(F$4=12,INDEX('CF Summary'!$B$22:$G$22,F$3+1)*INDEX(Inputs!$B$76:$O$76,2),0) -> 838107.58 | G8: =INDEX('CF Summary'!$B$22:$G$22,G$3)*INDEX(Inputs!$B$76:$O$76,G$4+2)+IF(G$4=11,INDEX('CF Summary'!$B$22:$G$22,G$3+1)*INDEX(Inputs!$B$76:$O$76,1),0)+IF(G$4=12,INDEX('CF Summary'!$B$22:$G$22,G$3+1)*INDEX(Inputs!$B$76:$O$76,2),0) -> 479452.33 | H8: =INDEX('CF Summary'!$B$22:$G$22,H$3)*INDEX(Inputs!$B$76:$O$76,H$4+2)+IF(H$4=11,INDEX('CF Summary'!$B$22:$G$22,H$3+1)*INDEX(Inputs!$B$76:$O$76,1),0)+IF(H$4=12,INDEX('CF Summary'!$B$22:$G$22,H$3+1)*INDEX(Inputs!$B$76:$O$76,2),0) -> 479452.33 | I8: =INDEX('CF Summary'!$B$22:$G$22,I$3)*INDEX(Inputs!$B$76:$O$76,I$4+2)+IF(I$4=11,INDEX('CF Summary'!$B$22:$G$22,I$3+1)*INDEX(Inputs!$B$76:$O$76,1),0)+IF(I$4=12,INDEX('CF Summary'!$B$22:$G$22,I$3+1)*INDEX(Inputs!$B$76:$O$76,2),0) -> 838107.58 | ... BI8: =INDEX('CF Summary'!$B$22:$G$22,BI$3)*INDEX(Inputs!$B$76:$O$76,BI$4+2)+IF(BI$4=11,INDEX('CF Summary'!$B$22:$G$22,BI$3+1)*INDEX(Inputs!$B$76:$O$76,1),0)+IF(BI$4=12,INDEX('CF Summary'!$B$22:$G$22,BI$3+1)*INDEX(Inputs!$B$76:$O$76,2),0) -> 2299271.6
A9: Even | B9: =INDEX('CF Summary'!$B$23:$G$23,B$3)*INDEX(Inputs!$B$77:$O$77,B$4+2)+IF(B$4=11,INDEX('CF Summary'!$B$23:$G$23,B$3+1)*INDEX(Inputs!$B$77:$O$77,1),0)+IF(B$4=12,INDEX('CF Summary'!$B$23:$G$23,B$3+1)*INDEX(Inputs!$B$77:$O$77,2),0) -> 12441.667 | C9: =INDEX('CF Summary'!$B$23:$G$23,C$3)*INDEX(Inputs!$B$77:$O$77,C$4+2)+IF(C$4=11,INDEX('CF Summary'!$B$23:$G$23,C$3+1)*INDEX(Inputs!$B$77:$O$77,1),0)+IF(C$4=12,INDEX('CF Summary'!$B$23:$G$23,C$3+1)*INDEX(Inputs!$B$77:$O$77,2),0) -> 12441.667 | D9: =INDEX('CF Summary'!$B$23:$G$23,D$3)*INDEX(Inputs!$B$77:$O$77,D$4+2)+IF(D$4=11,INDEX('CF Summary'!$B$23:$G$23,D$3+1)*INDEX(Inputs!$B$77:$O$77,1),0)+IF(D$4=12,INDEX('CF Summary'!$B$23:$G$23,D$3+1)*INDEX(Inputs!$B$77:$O$77,2),0) -> 12441.667 | E9: =INDEX('CF Summary'!$B$23:$G$23,E$3)*INDEX(Inputs!$B$77:$O$77,E$4+2)+IF(E$4=11,INDEX('CF Summary'!$B$23:$G$23,E$3+1)*INDEX(Inputs!$B$77:$O$77,1),0)+IF(E$4=12,INDEX('CF Summary'!$B$23:$G$23,E$3+1)*INDEX(Inputs!$B$77:$O$77,2),0) -> 12441.667 | F9: =INDEX('CF Summary'!$B$23:$G$23,F$3)*INDEX(Inputs!$B$77:$O$77,F$4+2)+IF(F$4=11,INDEX('CF Summary'!$B$23:$G$23,F$3+1)*INDEX(Inputs!$B$77:$O$77,1),0)+IF(F$4=12,INDEX('CF Summary'!$B$23:$G$23,F$3+1)*INDEX(Inputs!$B$77:$O$77,2),0) -> 12441.667 | G9: =INDEX('CF Summary'!$B$23:$G$23,G$3)*INDEX(Inputs!$B$77:$O$77,G$4+2)+IF(G$4=11,INDEX('CF Summary'!$B$23:$G$23,G$3+1)*INDEX(Inputs!$B$77:$O$77,1),0)+IF(G$4=12,INDEX('CF Summary'!$B$23:$G$23,G$3+1)*INDEX(Inputs!$B$77:$O$77,2),0) -> 12441.667 | H9: =INDEX('CF Summary'!$B$23:$G$23,H$3)*INDEX(Inputs!$B$77:$O$77,H$4+2)+IF(H$4=11,INDEX('CF Summary'!$B$23:$G$23,H$3+1)*INDEX(Inputs!$B$77:$O$77,1),0)+IF(H$4=12,INDEX('CF Summary'!$B$23:$G$23,H$3+1)*INDEX(Inputs!$B$77:$O$77,2),0) -> 12441.667 | I9: =INDEX('CF Summary'!$B$23:$G$23,I$3)*INDEX(Inputs!$B$77:$O$77,I$4+2)+IF(I$4=11,INDEX('CF Summary'!$B$23:$G$23,I$3+1)*INDEX(Inputs!$B$77:$O$77,1),0)+IF(I$4=12,INDEX('CF Summary'!$B$23:$G$23,I$3+1)*INDEX(Inputs!$B$77:$O$77,2),0) -> 12441.667 | ... BI9: =INDEX('CF Summary'!$B$23:$G$23,BI$3)*INDEX(Inputs!$B$77:$O$77,BI$4+2)+IF(BI$4=11,INDEX('CF Summary'!$B$23:$G$23,BI$3+1)*INDEX(Inputs!$B$77:$O$77,1),0)+IF(BI$4=12,INDEX('CF Summary'!$B$23:$G$23,BI$3+1)*INDEX(Inputs!$B$77:$O$77,2),0) -> 11833.753
A10: Jul Lump | B10: =INDEX('CF Summary'!$B$24:$G$24,B$3)*INDEX(Inputs!$B$78:$O$78,B$4+2)+IF(B$4=11,INDEX('CF Summary'!$B$24:$G$24,B$3+1)*INDEX(Inputs!$B$78:$O$78,1),0)+IF(B$4=12,INDEX('CF Summary'!$B$24:$G$24,B$3+1)*INDEX(Inputs!$B$78:$O$78,2),0) -> 562300 | C10: =INDEX('CF Summary'!$B$24:$G$24,C$3)*INDEX(Inputs!$B$78:$O$78,C$4+2)+IF(C$4=11,INDEX('CF Summary'!$B$24:$G$24,C$3+1)*INDEX(Inputs!$B$78:$O$78,1),0)+IF(C$4=12,INDEX('CF Summary'!$B$24:$G$24,C$3+1)*INDEX(Inputs!$B$78:$O$78,2),0) -> 0 | D10: =INDEX('CF Summary'!$B$24:$G$24,D$3)*INDEX(Inputs!$B$78:$O$78,D$4+2)+IF(D$4=11,INDEX('CF Summary'!$B$24:$G$24,D$3+1)*INDEX(Inputs!$B$78:$O$78,1),0)+IF(D$4=12,INDEX('CF Summary'!$B$24:$G$24,D$3+1)*INDEX(Inputs!$B$78:$O$78,2),0) -> 0 | E10: =INDEX('CF Summary'!$B$24:$G$24,E$3)*INDEX(Inputs!$B$78:$O$78,E$4+2)+IF(E$4=11,INDEX('CF Summary'!$B$24:$G$24,E$3+1)*INDEX(Inputs!$B$78:$O$78,1),0)+IF(E$4=12,INDEX('CF Summary'!$B$24:$G$24,E$3+1)*INDEX(Inputs!$B$78:$O$78,2),0) -> 0 | F10: =INDEX('CF Summary'!$B$24:$G$24,F$3)*INDEX(Inputs!$B$78:$O$78,F$4+2)+IF(F$4=11,INDEX('CF Summary'!$B$24:$G$24,F$3+1)*INDEX(Inputs!$B$78:$O$78,1),0)+IF(F$4=12,INDEX('CF Summary'!$B$24:$G$24,F$3+1)*INDEX(Inputs!$B$78:$O$78,2),0) -> 0 | G10: =INDEX('CF Summary'!$B$24:$G$24,G$3)*INDEX(Inputs!$B$78:$O$78,G$4+2)+IF(G$4=11,INDEX('CF Summary'!$B$24:$G$24,G$3+1)*INDEX(Inputs!$B$78:$O$78,1),0)+IF(G$4=12,INDEX('CF Summary'!$B$24:$G$24,G$3+1)*INDEX(Inputs!$B$78:$O$78,2),0) -> 0 | H10: =INDEX('CF Summary'!$B$24:$G$24,H$3)*INDEX(Inputs!$B$78:$O$78,H$4+2)+IF(H$4=11,INDEX('CF Summary'!$B$24:$G$24,H$3+1)*INDEX(Inputs!$B$78:$O$78,1),0)+IF(H$4=12,INDEX('CF Summary'!$B$24:$G$24,H$3+1)*INDEX(Inputs!$B$78:$O$78,2),0) -> 0 | I10: =INDEX('CF Summary'!$B$24:$G$24,I$3)*INDEX(Inputs!$B$78:$O$78,I$4+2)+IF(I$4=11,INDEX('CF Summary'!$B$24:$G$24,I$3+1)*INDEX(Inputs!$B$78:$O$78,1),0)+IF(I$4=12,INDEX('CF Summary'!$B$24:$G$24,I$3+1)*INDEX(Inputs!$B$78:$O$78,2),0) -> 0 | ... BI10: =INDEX('CF Summary'!$B$24:$G$24,BI$3)*INDEX(Inputs!$B$78:$O$78,BI$4+2)+IF(BI$4=11,INDEX('CF Summary'!$B$24:$G$24,BI$3+1)*INDEX(Inputs!$B$78:$O$78,1),0)+IF(BI$4=12,INDEX('CF Summary'!$B$24:$G$24,BI$3+1)*INDEX(Inputs!$B$78:$O$78,2),0) -> 0
A11: Custom A | B11: =INDEX('CF Summary'!$B$25:$G$25,B$3)*INDEX(Inputs!$B$79:$O$79,B$4+2)+IF(B$4=11,INDEX('CF Summary'!$B$25:$G$25,B$3+1)*INDEX(Inputs!$B$79:$O$79,1),0)+IF(B$4=12,INDEX('CF Summary'!$B$25:$G$25,B$3+1)*INDEX(Inputs!$B$79:$O$79,2),0) -> 0 | C11: =INDEX('CF Summary'!$B$25:$G$25,C$3)*INDEX(Inputs!$B$79:$O$79,C$4+2)+IF(C$4=11,INDEX('CF Summary'!$B$25:$G$25,C$3+1)*INDEX(Inputs!$B$79:$O$79,1),0)+IF(C$4=12,INDEX('CF Summary'!$B$25:$G$25,C$3+1)*INDEX(Inputs!$B$79:$O$79,2),0) -> 0 | D11: =INDEX('CF Summary'!$B$25:$G$25,D$3)*INDEX(Inputs!$B$79:$O$79,D$4+2)+IF(D$4=11,INDEX('CF Summary'!$B$25:$G$25,D$3+1)*INDEX(Inputs!$B$79:$O$79,1),0)+IF(D$4=12,INDEX('CF Summary'!$B$25:$G$25,D$3+1)*INDEX(Inputs!$B$79:$O$79,2),0) -> 0 | E11: =INDEX('CF Summary'!$B$25:$G$25,E$3)*INDEX(Inputs!$B$79:$O$79,E$4+2)+IF(E$4=11,INDEX('CF Summary'!$B$25:$G$25,E$3+1)*INDEX(Inputs!$B$79:$O$79,1),0)+IF(E$4=12,INDEX('CF Summary'!$B$25:$G$25,E$3+1)*INDEX(Inputs!$B$79:$O$79,2),0) -> 0 | F11: =INDEX('CF Summary'!$B$25:$G$25,F$3)*INDEX(Inputs!$B$79:$O$79,F$4+2)+IF(F$4=11,INDEX('CF Summary'!$B$25:$G$25,F$3+1)*INDEX(Inputs!$B$79:$O$79,1),0)+IF(F$4=12,INDEX('CF Summary'!$B$25:$G$25,F$3+1)*INDEX(Inputs!$B$79:$O$79,2),0) -> 0 | G11: =INDEX('CF Summary'!$B$25:$G$25,G$3)*INDEX(Inputs!$B$79:$O$79,G$4+2)+IF(G$4=11,INDEX('CF Summary'!$B$25:$G$25,G$3+1)*INDEX(Inputs!$B$79:$O$79,1),0)+IF(G$4=12,INDEX('CF Summary'!$B$25:$G$25,G$3+1)*INDEX(Inputs!$B$79:$O$79,2),0) -> 0 | H11: =INDEX('CF Summary'!$B$25:$G$25,H$3)*INDEX(Inputs!$B$79:$O$79,H$4+2)+IF(H$4=11,INDEX('CF Summary'!$B$25:$G$25,H$3+1)*INDEX(Inputs!$B$79:$O$79,1),0)+IF(H$4=12,INDEX('CF Summary'!$B$25:$G$25,H$3+1)*INDEX(Inputs!$B$79:$O$79,2),0) -> 0 | I11: =INDEX('CF Summary'!$B$25:$G$25,I$3)*INDEX(Inputs!$B$79:$O$79,I$4+2)+IF(I$4=11,INDEX('CF Summary'!$B$25:$G$25,I$3+1)*INDEX(Inputs!$B$79:$O$79,1),0)+IF(I$4=12,INDEX('CF Summary'!$B$25:$G$25,I$3+1)*INDEX(Inputs!$B$79:$O$79,2),0) -> 0 | ... BI11: =INDEX('CF Summary'!$B$25:$G$25,BI$3)*INDEX(Inputs!$B$79:$O$79,BI$4+2)+IF(BI$4=11,INDEX('CF Summary'!$B$25:$G$25,BI$3+1)*INDEX(Inputs!$B$79:$O$79,1),0)+IF(BI$4=12,INDEX('CF Summary'!$B$25:$G$25,BI$3+1)*INDEX(Inputs!$B$79:$O$79,2),0) -> 0
A12: Custom B | B12: =INDEX('CF Summary'!$B$26:$G$26,B$3)*INDEX(Inputs!$B$80:$O$80,B$4+2)+IF(B$4=11,INDEX('CF Summary'!$B$26:$G$26,B$3+1)*INDEX(Inputs!$B$80:$O$80,1),0)+IF(B$4=12,INDEX('CF Summary'!$B$26:$G$26,B$3+1)*INDEX(Inputs!$B$80:$O$80,2),0) -> 0 | C12: =INDEX('CF Summary'!$B$26:$G$26,C$3)*INDEX(Inputs!$B$80:$O$80,C$4+2)+IF(C$4=11,INDEX('CF Summary'!$B$26:$G$26,C$3+1)*INDEX(Inputs!$B$80:$O$80,1),0)+IF(C$4=12,INDEX('CF Summary'!$B$26:$G$26,C$3+1)*INDEX(Inputs!$B$80:$O$80,2),0) -> 0 | D12: =INDEX('CF Summary'!$B$26:$G$26,D$3)*INDEX(Inputs!$B$80:$O$80,D$4+2)+IF(D$4=11,INDEX('CF Summary'!$B$26:$G$26,D$3+1)*INDEX(Inputs!$B$80:$O$80,1),0)+IF(D$4=12,INDEX('CF Summary'!$B$26:$G$26,D$3+1)*INDEX(Inputs!$B$80:$O$80,2),0) -> 0 | E12: =INDEX('CF Summary'!$B$26:$G$26,E$3)*INDEX(Inputs!$B$80:$O$80,E$4+2)+IF(E$4=11,INDEX('CF Summary'!$B$26:$G$26,E$3+1)*INDEX(Inputs!$B$80:$O$80,1),0)+IF(E$4=12,INDEX('CF Summary'!$B$26:$G$26,E$3+1)*INDEX(Inputs!$B$80:$O$80,2),0) -> 0 | F12: =INDEX('CF Summary'!$B$26:$G$26,F$3)*INDEX(Inputs!$B$80:$O$80,F$4+2)+IF(F$4=11,INDEX('CF Summary'!$B$26:$G$26,F$3+1)*INDEX(Inputs!$B$80:$O$80,1),0)+IF(F$4=12,INDEX('CF Summary'!$B$26:$G$26,F$3+1)*INDEX(Inputs!$B$80:$O$80,2),0) -> 0 | G12: =INDEX('CF Summary'!$B$26:$G$26,G$3)*INDEX(Inputs!$B$80:$O$80,G$4+2)+IF(G$4=11,INDEX('CF Summary'!$B$26:$G$26,G$3+1)*INDEX(Inputs!$B$80:$O$80,1),0)+IF(G$4=12,INDEX('CF Summary'!$B$26:$G$26,G$3+1)*INDEX(Inputs!$B$80:$O$80,2),0) -> 0 | H12: =INDEX('CF Summary'!$B$26:$G$26,H$3)*INDEX(Inputs!$B$80:$O$80,H$4+2)+IF(H$4=11,INDEX('CF Summary'!$B$26:$G$26,H$3+1)*INDEX(Inputs!$B$80:$O$80,1),0)+IF(H$4=12,INDEX('CF Summary'!$B$26:$G$26,H$3+1)*INDEX(Inputs!$B$80:$O$80,2),0) -> 0 | I12: =INDEX('CF Summary'!$B$26:$G$26,I$3)*INDEX(Inputs!$B$80:$O$80,I$4+2)+IF(I$4=11,INDEX('CF Summary'!$B$26:$G$26,I$3+1)*INDEX(Inputs!$B$80:$O$80,1),0)+IF(I$4=12,INDEX('CF Summary'!$B$26:$G$26,I$3+1)*INDEX(Inputs!$B$80:$O$80,2),0) -> 0 | ... BI12: =INDEX('CF Summary'!$B$26:$G$26,BI$3)*INDEX(Inputs!$B$80:$O$80,BI$4+2)+IF(BI$4=11,INDEX('CF Summary'!$B$26:$G$26,BI$3+1)*INDEX(Inputs!$B$80:$O$80,1),0)+IF(BI$4=12,INDEX('CF Summary'!$B$26:$G$26,BI$3+1)*INDEX(Inputs!$B$80:$O$80,2),0) -> 0
A13: Total receipts | B13: =SUM(B8:B12) -> 1054194 | C13: =SUM(C8:C12) -> 850549.24 | D13: =SUM(D8:D12) -> 491894 | E13: =SUM(E8:E12) -> 491894 | F13: =SUM(F8:F12) -> 850549.24 | G13: =SUM(G8:G12) -> 491894 | H13: =SUM(H8:H12) -> 491894 | I13: =SUM(I8:I12) -> 850549.24 | ... BI13: =SUM(BI8:BI12) -> 2311105.3
A15: CASH DISBURSEMENTS (by timing profile)
A16: Tuition Plan | B16: =-(INDEX('CF Summary'!$B$29:$G$29,B$3)*INDEX(Inputs!$B$76:$O$76,B$4+2)+IF(B$4=11,INDEX('CF Summary'!$B$29:$G$29,B$3+1)*INDEX(Inputs!$B$76:$O$76,1),0)+IF(B$4=12,INDEX('CF Summary'!$B$29:$G$29,B$3+1)*INDEX(Inputs!$B$76:$O$76,2),0)) -> 0 | C16: =-(INDEX('CF Summary'!$B$29:$G$29,C$3)*INDEX(Inputs!$B$76:$O$76,C$4+2)+IF(C$4=11,INDEX('CF Summary'!$B$29:$G$29,C$3+1)*INDEX(Inputs!$B$76:$O$76,1),0)+IF(C$4=12,INDEX('CF Summary'!$B$29:$G$29,C$3+1)*INDEX(Inputs!$B$76:$O$76,2),0)) -> 0 | D16: =-(INDEX('CF Summary'!$B$29:$G$29,D$3)*INDEX(Inputs!$B$76:$O$76,D$4+2)+IF(D$4=11,INDEX('CF Summary'!$B$29:$G$29,D$3+1)*INDEX(Inputs!$B$76:$O$76,1),0)+IF(D$4=12,INDEX('CF Summary'!$B$29:$G$29,D$3+1)*INDEX(Inputs!$B$76:$O$76,2),0)) -> 0 | E16: =-(INDEX('CF Summary'!$B$29:$G$29,E$3)*INDEX(Inputs!$B$76:$O$76,E$4+2)+IF(E$4=11,INDEX('CF Summary'!$B$29:$G$29,E$3+1)*INDEX(Inputs!$B$76:$O$76,1),0)+IF(E$4=12,INDEX('CF Summary'!$B$29:$G$29,E$3+1)*INDEX(Inputs!$B$76:$O$76,2),0)) -> 0 | F16: =-(INDEX('CF Summary'!$B$29:$G$29,F$3)*INDEX(Inputs!$B$76:$O$76,F$4+2)+IF(F$4=11,INDEX('CF Summary'!$B$29:$G$29,F$3+1)*INDEX(Inputs!$B$76:$O$76,1),0)+IF(F$4=12,INDEX('CF Summary'!$B$29:$G$29,F$3+1)*INDEX(Inputs!$B$76:$O$76,2),0)) -> 0 | G16: =-(INDEX('CF Summary'!$B$29:$G$29,G$3)*INDEX(Inputs!$B$76:$O$76,G$4+2)+IF(G$4=11,INDEX('CF Summary'!$B$29:$G$29,G$3+1)*INDEX(Inputs!$B$76:$O$76,1),0)+IF(G$4=12,INDEX('CF Summary'!$B$29:$G$29,G$3+1)*INDEX(Inputs!$B$76:$O$76,2),0)) -> 0 | H16: =-(INDEX('CF Summary'!$B$29:$G$29,H$3)*INDEX(Inputs!$B$76:$O$76,H$4+2)+IF(H$4=11,INDEX('CF Summary'!$B$29:$G$29,H$3+1)*INDEX(Inputs!$B$76:$O$76,1),0)+IF(H$4=12,INDEX('CF Summary'!$B$29:$G$29,H$3+1)*INDEX(Inputs!$B$76:$O$76,2),0)) -> 0 | I16: =-(INDEX('CF Summary'!$B$29:$G$29,I$3)*INDEX(Inputs!$B$76:$O$76,I$4+2)+IF(I$4=11,INDEX('CF Summary'!$B$29:$G$29,I$3+1)*INDEX(Inputs!$B$76:$O$76,1),0)+IF(I$4=12,INDEX('CF Summary'!$B$29:$G$29,I$3+1)*INDEX(Inputs!$B$76:$O$76,2),0)) -> 0 | ... BI16: =-(INDEX('CF Summary'!$B$29:$G$29,BI$3)*INDEX(Inputs!$B$76:$O$76,BI$4+2)+IF(BI$4=11,INDEX('CF Summary'!$B$29:$G$29,BI$3+1)*INDEX(Inputs!$B$76:$O$76,1),0)+IF(BI$4=12,INDEX('CF Summary'!$B$29:$G$29,BI$3+1)*INDEX(Inputs!$B$76:$O$76,2),0)) -> 0
A17: Even | B17: =-(INDEX('CF Summary'!$B$30:$G$30,B$3)*INDEX(Inputs!$B$77:$O$77,B$4+2)+IF(B$4=11,INDEX('CF Summary'!$B$30:$G$30,B$3+1)*INDEX(Inputs!$B$77:$O$77,1),0)+IF(B$4=12,INDEX('CF Summary'!$B$30:$G$30,B$3+1)*INDEX(Inputs!$B$77:$O$77,2),0)) -> -775228.33 | C17: =-(INDEX('CF Summary'!$B$30:$G$30,C$3)*INDEX(Inputs!$B$77:$O$77,C$4+2)+IF(C$4=11,INDEX('CF Summary'!$B$30:$G$30,C$3+1)*INDEX(Inputs!$B$77:$O$77,1),0)+IF(C$4=12,INDEX('CF Summary'!$B$30:$G$30,C$3+1)*INDEX(Inputs!$B$77:$O$77,2),0)) -> -775228.33 | D17: =-(INDEX('CF Summary'!$B$30:$G$30,D$3)*INDEX(Inputs!$B$77:$O$77,D$4+2)+IF(D$4=11,INDEX('CF Summary'!$B$30:$G$30,D$3+1)*INDEX(Inputs!$B$77:$O$77,1),0)+IF(D$4=12,INDEX('CF Summary'!$B$30:$G$30,D$3+1)*INDEX(Inputs!$B$77:$O$77,2),0)) -> -775228.33 | E17: =-(INDEX('CF Summary'!$B$30:$G$30,E$3)*INDEX(Inputs!$B$77:$O$77,E$4+2)+IF(E$4=11,INDEX('CF Summary'!$B$30:$G$30,E$3+1)*INDEX(Inputs!$B$77:$O$77,1),0)+IF(E$4=12,INDEX('CF Summary'!$B$30:$G$30,E$3+1)*INDEX(Inputs!$B$77:$O$77,2),0)) -> -775228.33 | F17: =-(INDEX('CF Summary'!$B$30:$G$30,F$3)*INDEX(Inputs!$B$77:$O$77,F$4+2)+IF(F$4=11,INDEX('CF Summary'!$B$30:$G$30,F$3+1)*INDEX(Inputs!$B$77:$O$77,1),0)+IF(F$4=12,INDEX('CF Summary'!$B$30:$G$30,F$3+1)*INDEX(Inputs!$B$77:$O$77,2),0)) -> -775228.33 | G17: =-(INDEX('CF Summary'!$B$30:$G$30,G$3)*INDEX(Inputs!$B$77:$O$77,G$4+2)+IF(G$4=11,INDEX('CF Summary'!$B$30:$G$30,G$3+1)*INDEX(Inputs!$B$77:$O$77,1),0)+IF(G$4=12,INDEX('CF Summary'!$B$30:$G$30,G$3+1)*INDEX(Inputs!$B$77:$O$77,2),0)) -> -775228.33 | H17: =-(INDEX('CF Summary'!$B$30:$G$30,H$3)*INDEX(Inputs!$B$77:$O$77,H$4+2)+IF(H$4=11,INDEX('CF Summary'!$B$30:$G$30,H$3+1)*INDEX(Inputs!$B$77:$O$77,1),0)+IF(H$4=12,INDEX('CF Summary'!$B$30:$G$30,H$3+1)*INDEX(Inputs!$B$77:$O$77,2),0)) -> -775228.33 | I17: =-(INDEX('CF Summary'!$B$30:$G$30,I$3)*INDEX(Inputs!$B$77:$O$77,I$4+2)+IF(I$4=11,INDEX('CF Summary'!$B$30:$G$30,I$3+1)*INDEX(Inputs!$B$77:$O$77,1),0)+IF(I$4=12,INDEX('CF Summary'!$B$30:$G$30,I$3+1)*INDEX(Inputs!$B$77:$O$77,2),0)) -> -775228.33 | ... BI17: =-(INDEX('CF Summary'!$B$30:$G$30,BI$3)*INDEX(Inputs!$B$77:$O$77,BI$4+2)+IF(BI$4=11,INDEX('CF Summary'!$B$30:$G$30,BI$3+1)*INDEX(Inputs!$B$77:$O$77,1),0)+IF(BI$4=12,INDEX('CF Summary'!$B$30:$G$30,BI$3+1)*INDEX(Inputs!$B$77:$O$77,2),0)) -> -855965.1
A18: Jul Lump | B18: =-(INDEX('CF Summary'!$B$31:$G$31,B$3)*INDEX(Inputs!$B$78:$O$78,B$4+2)+IF(B$4=11,INDEX('CF Summary'!$B$31:$G$31,B$3+1)*INDEX(Inputs!$B$78:$O$78,1),0)+IF(B$4=12,INDEX('CF Summary'!$B$31:$G$31,B$3+1)*INDEX(Inputs!$B$78:$O$78,2),0)) -> 0 | C18: =-(INDEX('CF Summary'!$B$31:$G$31,C$3)*INDEX(Inputs!$B$78:$O$78,C$4+2)+IF(C$4=11,INDEX('CF Summary'!$B$31:$G$31,C$3+1)*INDEX(Inputs!$B$78:$O$78,1),0)+IF(C$4=12,INDEX('CF Summary'!$B$31:$G$31,C$3+1)*INDEX(Inputs!$B$78:$O$78,2),0)) -> 0 | D18: =-(INDEX('CF Summary'!$B$31:$G$31,D$3)*INDEX(Inputs!$B$78:$O$78,D$4+2)+IF(D$4=11,INDEX('CF Summary'!$B$31:$G$31,D$3+1)*INDEX(Inputs!$B$78:$O$78,1),0)+IF(D$4=12,INDEX('CF Summary'!$B$31:$G$31,D$3+1)*INDEX(Inputs!$B$78:$O$78,2),0)) -> 0 | E18: =-(INDEX('CF Summary'!$B$31:$G$31,E$3)*INDEX(Inputs!$B$78:$O$78,E$4+2)+IF(E$4=11,INDEX('CF Summary'!$B$31:$G$31,E$3+1)*INDEX(Inputs!$B$78:$O$78,1),0)+IF(E$4=12,INDEX('CF Summary'!$B$31:$G$31,E$3+1)*INDEX(Inputs!$B$78:$O$78,2),0)) -> 0 | F18: =-(INDEX('CF Summary'!$B$31:$G$31,F$3)*INDEX(Inputs!$B$78:$O$78,F$4+2)+IF(F$4=11,INDEX('CF Summary'!$B$31:$G$31,F$3+1)*INDEX(Inputs!$B$78:$O$78,1),0)+IF(F$4=12,INDEX('CF Summary'!$B$31:$G$31,F$3+1)*INDEX(Inputs!$B$78:$O$78,2),0)) -> 0 | G18: =-(INDEX('CF Summary'!$B$31:$G$31,G$3)*INDEX(Inputs!$B$78:$O$78,G$4+2)+IF(G$4=11,INDEX('CF Summary'!$B$31:$G$31,G$3+1)*INDEX(Inputs!$B$78:$O$78,1),0)+IF(G$4=12,INDEX('CF Summary'!$B$31:$G$31,G$3+1)*INDEX(Inputs!$B$78:$O$78,2),0)) -> 0 | H18: =-(INDEX('CF Summary'!$B$31:$G$31,H$3)*INDEX(Inputs!$B$78:$O$78,H$4+2)+IF(H$4=11,INDEX('CF Summary'!$B$31:$G$31,H$3+1)*INDEX(Inputs!$B$78:$O$78,1),0)+IF(H$4=12,INDEX('CF Summary'!$B$31:$G$31,H$3+1)*INDEX(Inputs!$B$78:$O$78,2),0)) -> 0 | I18: =-(INDEX('CF Summary'!$B$31:$G$31,I$3)*INDEX(Inputs!$B$78:$O$78,I$4+2)+IF(I$4=11,INDEX('CF Summary'!$B$31:$G$31,I$3+1)*INDEX(Inputs!$B$78:$O$78,1),0)+IF(I$4=12,INDEX('CF Summary'!$B$31:$G$31,I$3+1)*INDEX(Inputs!$B$78:$O$78,2),0)) -> 0 | ... BI18: =-(INDEX('CF Summary'!$B$31:$G$31,BI$3)*INDEX(Inputs!$B$78:$O$78,BI$4+2)+IF(BI$4=11,INDEX('CF Summary'!$B$31:$G$31,BI$3+1)*INDEX(Inputs!$B$78:$O$78,1),0)+IF(BI$4=12,INDEX('CF Summary'!$B$31:$G$31,BI$3+1)*INDEX(Inputs!$B$78:$O$78,2),0)) -> 0
A19: Custom A | B19: =-(INDEX('CF Summary'!$B$32:$G$32,B$3)*INDEX(Inputs!$B$79:$O$79,B$4+2)+IF(B$4=11,INDEX('CF Summary'!$B$32:$G$32,B$3+1)*INDEX(Inputs!$B$79:$O$79,1),0)+IF(B$4=12,INDEX('CF Summary'!$B$32:$G$32,B$3+1)*INDEX(Inputs!$B$79:$O$79,2),0)) -> 0 | C19: =-(INDEX('CF Summary'!$B$32:$G$32,C$3)*INDEX(Inputs!$B$79:$O$79,C$4+2)+IF(C$4=11,INDEX('CF Summary'!$B$32:$G$32,C$3+1)*INDEX(Inputs!$B$79:$O$79,1),0)+IF(C$4=12,INDEX('CF Summary'!$B$32:$G$32,C$3+1)*INDEX(Inputs!$B$79:$O$79,2),0)) -> 0 | D19: =-(INDEX('CF Summary'!$B$32:$G$32,D$3)*INDEX(Inputs!$B$79:$O$79,D$4+2)+IF(D$4=11,INDEX('CF Summary'!$B$32:$G$32,D$3+1)*INDEX(Inputs!$B$79:$O$79,1),0)+IF(D$4=12,INDEX('CF Summary'!$B$32:$G$32,D$3+1)*INDEX(Inputs!$B$79:$O$79,2),0)) -> 0 | E19: =-(INDEX('CF Summary'!$B$32:$G$32,E$3)*INDEX(Inputs!$B$79:$O$79,E$4+2)+IF(E$4=11,INDEX('CF Summary'!$B$32:$G$32,E$3+1)*INDEX(Inputs!$B$79:$O$79,1),0)+IF(E$4=12,INDEX('CF Summary'!$B$32:$G$32,E$3+1)*INDEX(Inputs!$B$79:$O$79,2),0)) -> 0 | F19: =-(INDEX('CF Summary'!$B$32:$G$32,F$3)*INDEX(Inputs!$B$79:$O$79,F$4+2)+IF(F$4=11,INDEX('CF Summary'!$B$32:$G$32,F$3+1)*INDEX(Inputs!$B$79:$O$79,1),0)+IF(F$4=12,INDEX('CF Summary'!$B$32:$G$32,F$3+1)*INDEX(Inputs!$B$79:$O$79,2),0)) -> 0 | G19: =-(INDEX('CF Summary'!$B$32:$G$32,G$3)*INDEX(Inputs!$B$79:$O$79,G$4+2)+IF(G$4=11,INDEX('CF Summary'!$B$32:$G$32,G$3+1)*INDEX(Inputs!$B$79:$O$79,1),0)+IF(G$4=12,INDEX('CF Summary'!$B$32:$G$32,G$3+1)*INDEX(Inputs!$B$79:$O$79,2),0)) -> 0 | H19: =-(INDEX('CF Summary'!$B$32:$G$32,H$3)*INDEX(Inputs!$B$79:$O$79,H$4+2)+IF(H$4=11,INDEX('CF Summary'!$B$32:$G$32,H$3+1)*INDEX(Inputs!$B$79:$O$79,1),0)+IF(H$4=12,INDEX('CF Summary'!$B$32:$G$32,H$3+1)*INDEX(Inputs!$B$79:$O$79,2),0)) -> 0 | I19: =-(INDEX('CF Summary'!$B$32:$G$32,I$3)*INDEX(Inputs!$B$79:$O$79,I$4+2)+IF(I$4=11,INDEX('CF Summary'!$B$32:$G$32,I$3+1)*INDEX(Inputs!$B$79:$O$79,1),0)+IF(I$4=12,INDEX('CF Summary'!$B$32:$G$32,I$3+1)*INDEX(Inputs!$B$79:$O$79,2),0)) -> 0 | ... BI19: =-(INDEX('CF Summary'!$B$32:$G$32,BI$3)*INDEX(Inputs!$B$79:$O$79,BI$4+2)+IF(BI$4=11,INDEX('CF Summary'!$B$32:$G$32,BI$3+1)*INDEX(Inputs!$B$79:$O$79,1),0)+IF(BI$4=12,INDEX('CF Summary'!$B$32:$G$32,BI$3+1)*INDEX(Inputs!$B$79:$O$79,2),0)) -> 0
A20: Custom B | B20: =-(INDEX('CF Summary'!$B$33:$G$33,B$3)*INDEX(Inputs!$B$80:$O$80,B$4+2)+IF(B$4=11,INDEX('CF Summary'!$B$33:$G$33,B$3+1)*INDEX(Inputs!$B$80:$O$80,1),0)+IF(B$4=12,INDEX('CF Summary'!$B$33:$G$33,B$3+1)*INDEX(Inputs!$B$80:$O$80,2),0)) -> 0 | C20: =-(INDEX('CF Summary'!$B$33:$G$33,C$3)*INDEX(Inputs!$B$80:$O$80,C$4+2)+IF(C$4=11,INDEX('CF Summary'!$B$33:$G$33,C$3+1)*INDEX(Inputs!$B$80:$O$80,1),0)+IF(C$4=12,INDEX('CF Summary'!$B$33:$G$33,C$3+1)*INDEX(Inputs!$B$80:$O$80,2),0)) -> 0 | D20: =-(INDEX('CF Summary'!$B$33:$G$33,D$3)*INDEX(Inputs!$B$80:$O$80,D$4+2)+IF(D$4=11,INDEX('CF Summary'!$B$33:$G$33,D$3+1)*INDEX(Inputs!$B$80:$O$80,1),0)+IF(D$4=12,INDEX('CF Summary'!$B$33:$G$33,D$3+1)*INDEX(Inputs!$B$80:$O$80,2),0)) -> 0 | E20: =-(INDEX('CF Summary'!$B$33:$G$33,E$3)*INDEX(Inputs!$B$80:$O$80,E$4+2)+IF(E$4=11,INDEX('CF Summary'!$B$33:$G$33,E$3+1)*INDEX(Inputs!$B$80:$O$80,1),0)+IF(E$4=12,INDEX('CF Summary'!$B$33:$G$33,E$3+1)*INDEX(Inputs!$B$80:$O$80,2),0)) -> 0 | F20: =-(INDEX('CF Summary'!$B$33:$G$33,F$3)*INDEX(Inputs!$B$80:$O$80,F$4+2)+IF(F$4=11,INDEX('CF Summary'!$B$33:$G$33,F$3+1)*INDEX(Inputs!$B$80:$O$80,1),0)+IF(F$4=12,INDEX('CF Summary'!$B$33:$G$33,F$3+1)*INDEX(Inputs!$B$80:$O$80,2),0)) -> 0 | G20: =-(INDEX('CF Summary'!$B$33:$G$33,G$3)*INDEX(Inputs!$B$80:$O$80,G$4+2)+IF(G$4=11,INDEX('CF Summary'!$B$33:$G$33,G$3+1)*INDEX(Inputs!$B$80:$O$80,1),0)+IF(G$4=12,INDEX('CF Summary'!$B$33:$G$33,G$3+1)*INDEX(Inputs!$B$80:$O$80,2),0)) -> 0 | H20: =-(INDEX('CF Summary'!$B$33:$G$33,H$3)*INDEX(Inputs!$B$80:$O$80,H$4+2)+IF(H$4=11,INDEX('CF Summary'!$B$33:$G$33,H$3+1)*INDEX(Inputs!$B$80:$O$80,1),0)+IF(H$4=12,INDEX('CF Summary'!$B$33:$G$33,H$3+1)*INDEX(Inputs!$B$80:$O$80,2),0)) -> 0 | I20: =-(INDEX('CF Summary'!$B$33:$G$33,I$3)*INDEX(Inputs!$B$80:$O$80,I$4+2)+IF(I$4=11,INDEX('CF Summary'!$B$33:$G$33,I$3+1)*INDEX(Inputs!$B$80:$O$80,1),0)+IF(I$4=12,INDEX('CF Summary'!$B$33:$G$33,I$3+1)*INDEX(Inputs!$B$80:$O$80,2),0)) -> 0 | ... BI20: =-(INDEX('CF Summary'!$B$33:$G$33,BI$3)*INDEX(Inputs!$B$80:$O$80,BI$4+2)+IF(BI$4=11,INDEX('CF Summary'!$B$33:$G$33,BI$3+1)*INDEX(Inputs!$B$80:$O$80,1),0)+IF(BI$4=12,INDEX('CF Summary'!$B$33:$G$33,BI$3+1)*INDEX(Inputs!$B$80:$O$80,2),0)) -> 0
A21: Strategic plan initiatives - operating, net | B21: =-INDEX(Inputs!$E$31:$I$31,B$3)/12 -> 0 | C21: =-INDEX(Inputs!$E$31:$I$31,C$3)/12 -> 0 | D21: =-INDEX(Inputs!$E$31:$I$31,D$3)/12 -> 0 | E21: =-INDEX(Inputs!$E$31:$I$31,E$3)/12 -> 0 | F21: =-INDEX(Inputs!$E$31:$I$31,F$3)/12 -> 0 | G21: =-INDEX(Inputs!$E$31:$I$31,G$3)/12 -> 0 | H21: =-INDEX(Inputs!$E$31:$I$31,H$3)/12 -> 0 | I21: =-INDEX(Inputs!$E$31:$I$31,I$3)/12 -> 0 | ... BI21: =-INDEX(Inputs!$E$31:$I$31,BI$3)/12 -> -16666.667
A22: Total operating disbursements | B22: =SUM(B16:B21) -> -775228.33 | C22: =SUM(C16:C21) -> -775228.33 | D22: =SUM(D16:D21) -> -775228.33 | E22: =SUM(E16:E21) -> -775228.33 | F22: =SUM(F16:F21) -> -775228.33 | G22: =SUM(G16:G21) -> -775228.33 | H22: =SUM(H16:H21) -> -775228.33 | I22: =SUM(I16:I21) -> -775228.33 | ... BI22: =SUM(BI16:BI21) -> -872631.77
A23: NET OPERATING CASH FLOW | B23: =B13+B22 -> 278965.66 | C23: =C13+C22 -> 75320.911 | D23: =D13+D22 -> -283334.34 | E23: =E13+E22 -> -283334.34 | F23: =F13+F22 -> 75320.911 | G23: =G13+G22 -> -283334.34 | H23: =H13+H22 -> -283334.34 | I23: =I13+I22 -> 75320.911 | ... BI23: =BI13+BI22 -> 1438473.6
A25: Capital projects & capital initiatives | B25: =-(SUMPRODUCT((Inputs!$B$20:$B$29="Capital")*(Inputs!$C$20:$C$29="Y")*(INDEX(Inputs!$E$20:$I$29,0,B$3)-INDEX(Inputs!$J$20:$N$29,0,B$3))*((Inputs!$D$20:$D$29=B$4)+(Inputs!$D$20:$D$29=0)/12))+SUMPRODUCT(INDEX(Inputs!$C$36:$G$41,0,B$3)*((Inputs!$B$36:$B$41=B$4)+(Inputs!$B$36:$B$41=0)/12))) -> 0 | C25: =-(SUMPRODUCT((Inputs!$B$20:$B$29="Capital")*(Inputs!$C$20:$C$29="Y")*(INDEX(Inputs!$E$20:$I$29,0,C$3)-INDEX(Inputs!$J$20:$N$29,0,C$3))*((Inputs!$D$20:$D$29=C$4)+(Inputs!$D$20:$D$29=0)/12))+SUMPRODUCT(INDEX(Inputs!$C$36:$G$41,0,C$3)*((Inputs!$B$36:$B$41=C$4)+(Inputs!$B$36:$B$41=0)/12))) -> 0 | D25: =-(SUMPRODUCT((Inputs!$B$20:$B$29="Capital")*(Inputs!$C$20:$C$29="Y")*(INDEX(Inputs!$E$20:$I$29,0,D$3)-INDEX(Inputs!$J$20:$N$29,0,D$3))*((Inputs!$D$20:$D$29=D$4)+(Inputs!$D$20:$D$29=0)/12))+SUMPRODUCT(INDEX(Inputs!$C$36:$G$41,0,D$3)*((Inputs!$B$36:$B$41=D$4)+(Inputs!$B$36:$B$41=0)/12))) -> 0 | E25: =-(SUMPRODUCT((Inputs!$B$20:$B$29="Capital")*(Inputs!$C$20:$C$29="Y")*(INDEX(Inputs!$E$20:$I$29,0,E$3)-INDEX(Inputs!$J$20:$N$29,0,E$3))*((Inputs!$D$20:$D$29=E$4)+(Inputs!$D$20:$D$29=0)/12))+SUMPRODUCT(INDEX(Inputs!$C$36:$G$41,0,E$3)*((Inputs!$B$36:$B$41=E$4)+(Inputs!$B$36:$B$41=0)/12))) -> 0 | F25: =-(SUMPRODUCT((Inputs!$B$20:$B$29="Capital")*(Inputs!$C$20:$C$29="Y")*(INDEX(Inputs!$E$20:$I$29,0,F$3)-INDEX(Inputs!$J$20:$N$29,0,F$3))*((Inputs!$D$20:$D$29=F$4)+(Inputs!$D$20:$D$29=0)/12))+SUMPRODUCT(INDEX(Inputs!$C$36:$G$41,0,F$3)*((Inputs!$B$36:$B$41=F$4)+(Inputs!$B$36:$B$41=0)/12))) -> 0 | G25: =-(SUMPRODUCT((Inputs!$B$20:$B$29="Capital")*(Inputs!$C$20:$C$29="Y")*(INDEX(Inputs!$E$20:$I$29,0,G$3)-INDEX(Inputs!$J$20:$N$29,0,G$3))*((Inputs!$D$20:$D$29=G$4)+(Inputs!$D$20:$D$29=0)/12))+SUMPRODUCT(INDEX(Inputs!$C$36:$G$41,0,G$3)*((Inputs!$B$36:$B$41=G$4)+(Inputs!$B$36:$B$41=0)/12))) -> 0 | H25: =-(SUMPRODUCT((Inputs!$B$20:$B$29="Capital")*(Inputs!$C$20:$C$29="Y")*(INDEX(Inputs!$E$20:$I$29,0,H$3)-INDEX(Inputs!$J$20:$N$29,0,H$3))*((Inputs!$D$20:$D$29=H$4)+(Inputs!$D$20:$D$29=0)/12))+SUMPRODUCT(INDEX(Inputs!$C$36:$G$41,0,H$3)*((Inputs!$B$36:$B$41=H$4)+(Inputs!$B$36:$B$41=0)/12))) -> 0 | I25: =-(SUMPRODUCT((Inputs!$B$20:$B$29="Capital")*(Inputs!$C$20:$C$29="Y")*(INDEX(Inputs!$E$20:$I$29,0,I$3)-INDEX(Inputs!$J$20:$N$29,0,I$3))*((Inputs!$D$20:$D$29=I$4)+(Inputs!$D$20:$D$29=0)/12))+SUMPRODUCT(INDEX(Inputs!$C$36:$G$41,0,I$3)*((Inputs!$B$36:$B$41=I$4)+(Inputs!$B$36:$B$41=0)/12))) -> 0 | ... BI25: =-(SUMPRODUCT((Inputs!$B$20:$B$29="Capital")*(Inputs!$C$20:$C$29="Y")*(INDEX(Inputs!$E$20:$I$29,0,BI$3)-INDEX(Inputs!$J$20:$N$29,0,BI$3))*((Inputs!$D$20:$D$29=BI$4)+(Inputs!$D$20:$D$29=0)/12))+SUMPRODUCT(INDEX(Inputs!$C$36:$G$41,0,BI$3)*((Inputs!$B$36:$B$41=BI$4)+(Inputs!$B$36:$B$41=0)/12))) -> 0
A26: Transfers to reserves | B26: =-(INDEX(Inputs!$C$46:$G$46,B$3)*((Inputs!$B$46=B$4)+(Inputs!$B$46=0)/12)+INDEX(Inputs!$C$47:$G$47,B$3)*((Inputs!$B$47=B$4)+(Inputs!$B$47=0)/12)) -> 0 | C26: =-(INDEX(Inputs!$C$46:$G$46,C$3)*((Inputs!$B$46=C$4)+(Inputs!$B$46=0)/12)+INDEX(Inputs!$C$47:$G$47,C$3)*((Inputs!$B$47=C$4)+(Inputs!$B$47=0)/12)) -> 0 | D26: =-(INDEX(Inputs!$C$46:$G$46,D$3)*((Inputs!$B$46=D$4)+(Inputs!$B$46=0)/12)+INDEX(Inputs!$C$47:$G$47,D$3)*((Inputs!$B$47=D$4)+(Inputs!$B$47=0)/12)) -> 0 | E26: =-(INDEX(Inputs!$C$46:$G$46,E$3)*((Inputs!$B$46=E$4)+(Inputs!$B$46=0)/12)+INDEX(Inputs!$C$47:$G$47,E$3)*((Inputs!$B$47=E$4)+(Inputs!$B$47=0)/12)) -> 0 | F26: =-(INDEX(Inputs!$C$46:$G$46,F$3)*((Inputs!$B$46=F$4)+(Inputs!$B$46=0)/12)+INDEX(Inputs!$C$47:$G$47,F$3)*((Inputs!$B$47=F$4)+(Inputs!$B$47=0)/12)) -> 0 | G26: =-(INDEX(Inputs!$C$46:$G$46,G$3)*((Inputs!$B$46=G$4)+(Inputs!$B$46=0)/12)+INDEX(Inputs!$C$47:$G$47,G$3)*((Inputs!$B$47=G$4)+(Inputs!$B$47=0)/12)) -> 0 | H26: =-(INDEX(Inputs!$C$46:$G$46,H$3)*((Inputs!$B$46=H$4)+(Inputs!$B$46=0)/12)+INDEX(Inputs!$C$47:$G$47,H$3)*((Inputs!$B$47=H$4)+(Inputs!$B$47=0)/12)) -> 0 | I26: =-(INDEX(Inputs!$C$46:$G$46,I$3)*((Inputs!$B$46=I$4)+(Inputs!$B$46=0)/12)+INDEX(Inputs!$C$47:$G$47,I$3)*((Inputs!$B$47=I$4)+(Inputs!$B$47=0)/12)) -> 0 | ... BI26: =-(INDEX(Inputs!$C$46:$G$46,BI$3)*((Inputs!$B$46=BI$4)+(Inputs!$B$46=0)/12)+INDEX(Inputs!$C$47:$G$47,BI$3)*((Inputs!$B$47=BI$4)+(Inputs!$B$47=0)/12)) -> 0
A28: Operating cash - beginning | B28: =Inputs!$D$58 -> 1163777.8 | C28: =B31 -> 1442743.5 | D28: =C31 -> 1518064.4 | E28: =D31 -> 1234730 | F28: =E31 -> 951395.71 | G28: =F31 -> 1026716.6 | H28: =G31 -> 743382.28 | I28: =H31 -> 460047.94 | J28: =I31 -> 535368.85 | ... BI28: =BH31 -> 815645.63
A29: Net operating cash flow | B29: =B23 -> 278965.66 | C29: =C23 -> 75320.911 | D29: =D23 -> -283334.34 | E29: =E23 -> -283334.34 | F29: =F23 -> 75320.911 | G29: =G23 -> -283334.34 | H29: =H23 -> -283334.34 | I29: =I23 -> 75320.911 | ... BI29: =BI23 -> 1438473.6
A30: Capital & reserve transfers | B30: =B25+B26 -> 0 | C30: =C25+C26 -> 0 | D30: =D25+D26 -> 0 | E30: =E25+E26 -> 0 | F30: =F25+F26 -> 0 | G30: =G25+G26 -> 0 | H30: =H25+H26 -> 0 | I30: =I25+I26 -> 0 | ... BI30: =BI25+BI26 -> 0
A31: Operating cash - ending | B31: =B28+B29+B30 -> 1442743.5 | C31: =C28+C29+C30 -> 1518064.4 | D31: =D28+D29+D30 -> 1234730 | E31: =E28+E29+E30 -> 951395.71 | F31: =F28+F29+F30 -> 1026716.6 | G31: =G28+G29+G30 -> 743382.28 | H31: =H28+H29+H30 -> 460047.94 | I31: =I28+I29+I30 -> 535368.85 | ... BI31: =BI28+BI29+BI30 -> 2254119.2
A33: Reserves & restricted - beginning | B33: =Inputs!$D$59 -> 1042606.2 | C33: =B35 -> 1042606.2 | D33: =C35 -> 1042606.2 | E33: =D35 -> 1042606.2 | F33: =E35 -> 1042606.2 | G33: =F35 -> 1042606.2 | H33: =G35 -> 1042606.2 | I33: =H35 -> 1042606.2 | J33: =I35 -> 1042606.2 | ... BI33: =BH35 -> 1042606.2
A34: Transfers in | B34: =-B26 -> 0 | C34: =-C26 -> 0 | D34: =-D26 -> 0 | E34: =-E26 -> 0 | F34: =-F26 -> 0 | G34: =-G26 -> 0 | H34: =-H26 -> 0 | I34: =-I26 -> 0 | ... BI34: =-BI26 -> 0
A35: Reserves & restricted - ending | B35: =B33+B34 -> 1042606.2 | C35: =C33+C34 -> 1042606.2 | D35: =D33+D34 -> 1042606.2 | E35: =E33+E34 -> 1042606.2 | F35: =F33+F34 -> 1042606.2 | G35: =G33+G34 -> 1042606.2 | H35: =H33+H34 -> 1042606.2 | I35: =I33+I34 -> 1042606.2 | ... BI35: =BI33+BI34 -> 1042606.2
A37: TOTAL CASH & RESERVES - ending | B37: =B31+B35 -> 2485349.6 | C37: =C31+C35 -> 2560670.6 | D37: =D31+D35 -> 2277336.2 | E37: =E31+E35 -> 1994001.9 | F37: =F31+F35 -> 2069322.8 | G37: =G31+G35 -> 1785988.5 | H37: =H31+H35 -> 1502654.1 | I37: =I31+I35 -> 1577975 | ... BI37: =BI31+BI35 -> 3296725.4
A38: Operating cash below zero? | B38: =IF(B31<0,"SHORTFALL","") | C38: =IF(C31<0,"SHORTFALL","") | D38: =IF(D31<0,"SHORTFALL","") | E38: =IF(E31<0,"SHORTFALL","") | F38: =IF(F31<0,"SHORTFALL","") | G38: =IF(G31<0,"SHORTFALL","") | H38: =IF(H31<0,"SHORTFALL","") | I38: =IF(I31<0,"SHORTFALL","") | ... BI38: =IF(BI31<0,"SHORTFALL","")

Sheet CF Summary
A1: CASH FLOW SUMMARY (annual)
A3: Fiscal year | B3: =Inputs!C$4 -> FY27 | C3: =Inputs!D$4 -> FY28 | D3: =Inputs!E$4 -> FY29 | E3: =Inputs!F$4 -> FY30 | F3: =Inputs!G$4 -> FY31
A4: Operating cash - beginning of year | B4: =INDEX('Cash Flow'!$B$28:$BI$28,1) -> 1163777.8 | C4: =INDEX('Cash Flow'!$B$28:$BI$28,13) -> 1336601.6 | D4: =INDEX('Cash Flow'!$B$28:$BI$28,25) -> 1544211.4 | E4: =INDEX('Cash Flow'!$B$28:$BI$28,37) -> 1695444.8 | F4: =INDEX('Cash Flow'!$B$28:$BI$28,49) -> 1946988.5
A5: Cash receipts | B5: =SUM(INDEX('Cash Flow'!$B$13:$BI$13,1):INDEX('Cash Flow'!$B$13:$BI$13,12)) -> 9475563.7 | C5: =SUM(INDEX('Cash Flow'!$B$13:$BI$13,13):INDEX('Cash Flow'!$B$13:$BI$13,24)) -> 9859301.6 | D5: =SUM(INDEX('Cash Flow'!$B$13:$BI$13,25):INDEX('Cash Flow'!$B$13:$BI$13,36)) -> 10132814 | E5: =SUM(INDEX('Cash Flow'!$B$13:$BI$13,37):INDEX('Cash Flow'!$B$13:$BI$13,48)) -> 10442604 | F5: =SUM(INDEX('Cash Flow'!$B$13:$BI$13,49):INDEX('Cash Flow'!$B$13:$BI$13,60)) -> 10778712
A6: Operating disbursements (incl. strategic plan) | B6: =SUM(INDEX('Cash Flow'!$B$22:$BI$22,1):INDEX('Cash Flow'!$B$22:$BI$22,12)) -> -9302740 | C6: =SUM(INDEX('Cash Flow'!$B$22:$BI$22,13):INDEX('Cash Flow'!$B$22:$BI$22,24)) -> -9651691.8 | D6: =SUM(INDEX('Cash Flow'!$B$22:$BI$22,25):INDEX('Cash Flow'!$B$22:$BI$22,36)) -> -9981580.5 | E6: =SUM(INDEX('Cash Flow'!$B$22:$BI$22,37):INDEX('Cash Flow'!$B$22:$BI$22,48)) -> -10191060 | F6: =SUM(INDEX('Cash Flow'!$B$22:$BI$22,49):INDEX('Cash Flow'!$B$22:$BI$22,60)) -> -10471581
A7: Net operating cash flow | B7: =B5+B6 -> 172823.75 | C7: =C5+C6 -> 207609.83 | D7: =D5+D6 -> 151233.44 | E7: =E5+E6 -> 251543.68 | F7: =F5+F6 -> 307130.7
A8: Capital projects & capital initiatives | B8: =SUM(INDEX('Cash Flow'!$B$25:$BI$25,1):INDEX('Cash Flow'!$B$25:$BI$25,12)) -> 0 | C8: =SUM(INDEX('Cash Flow'!$B$25:$BI$25,13):INDEX('Cash Flow'!$B$25:$BI$25,24)) -> 0 | D8: =SUM(INDEX('Cash Flow'!$B$25:$BI$25,25):INDEX('Cash Flow'!$B$25:$BI$25,36)) -> 0 | E8: =SUM(INDEX('Cash Flow'!$B$25:$BI$25,37):INDEX('Cash Flow'!$B$25:$BI$25,48)) -> 0 | F8: =SUM(INDEX('Cash Flow'!$B$25:$BI$25,49):INDEX('Cash Flow'!$B$25:$BI$25,60)) -> 0
A9: Transfers to reserves | B9: =SUM(INDEX('Cash Flow'!$B$26:$BI$26,1):INDEX('Cash Flow'!$B$26:$BI$26,12)) -> 0 | C9: =SUM(INDEX('Cash Flow'!$B$26:$BI$26,13):INDEX('Cash Flow'!$B$26:$BI$26,24)) -> 0 | D9: =SUM(INDEX('Cash Flow'!$B$26:$BI$26,25):INDEX('Cash Flow'!$B$26:$BI$26,36)) -> 0 | E9: =SUM(INDEX('Cash Flow'!$B$26:$BI$26,37):INDEX('Cash Flow'!$B$26:$BI$26,48)) -> 0 | F9: =SUM(INDEX('Cash Flow'!$B$26:$BI$26,49):INDEX('Cash Flow'!$B$26:$BI$26,60)) -> 0
A10: Operating cash - end of year | B10: =INDEX('Cash Flow'!$B$31:$BI$31,12) -> 1336601.6 | C10: =INDEX('Cash Flow'!$B$31:$BI$31,24) -> 1544211.4 | D10: =INDEX('Cash Flow'!$B$31:$BI$31,36) -> 1695444.8 | E10: =INDEX('Cash Flow'!$B$31:$BI$31,48) -> 1946988.5 | F10: =INDEX('Cash Flow'!$B$31:$BI$31,60) -> 2254119.2
A11: Reserves & restricted - end of year | B11: =INDEX('Cash Flow'!$B$35:$BI$35,12) -> 1042606.2 | C11: =INDEX('Cash Flow'!$B$35:$BI$35,24) -> 1042606.2 | D11: =INDEX('Cash Flow'!$B$35:$BI$35,36) -> 1042606.2 | E11: =INDEX('Cash Flow'!$B$35:$BI$35,48) -> 1042606.2 | F11: =INDEX('Cash Flow'!$B$35:$BI$35,60) -> 1042606.2
A12: Total cash & reserves - end of year | B12: =B10+B11 -> 2379207.7 | C12: =C10+C11 -> 2586817.6 | D12: =D10+D11 -> 2738051 | E12: =E10+E11 -> 2989594.7 | F12: =F10+F11 -> 3296725.4
A13: Lowest month-end operating cash | B13: =MIN(INDEX('Cash Flow'!$B$31:$BI$31,1):INDEX('Cash Flow'!$B$31:$BI$31,12)) -> -31299.821 | C13: =MIN(INDEX('Cash Flow'!$B$31:$BI$31,13):INDEX('Cash Flow'!$B$31:$BI$31,24)) -> 131306.32 | D13: =MIN(INDEX('Cash Flow'!$B$31:$BI$31,25):INDEX('Cash Flow'!$B$31:$BI$31,36)) -> 238258.55 | E13: =MIN(INDEX('Cash Flow'!$B$31:$BI$31,37):INDEX('Cash Flow'!$B$31:$BI$31,48)) -> 427586.45 | F13: =MIN(INDEX('Cash Flow'!$B$31:$BI$31,49):INDEX('Cash Flow'!$B$31:$BI$31,60)) -> 653700.89
A14: Month of low point | B14: =INDEX('Cash Flow'!$B$2:$BI$2,0+MATCH(B13,INDEX('Cash Flow'!$B$31:$BI$31,1):INDEX('Cash Flow'!$B$31:$BI$31,12),0)) -> 46507 | C14: =INDEX('Cash Flow'!$B$2:$BI$2,12+MATCH(C13,INDEX('Cash Flow'!$B$31:$BI$31,13):INDEX('Cash Flow'!$B$31:$BI$31,24),0)) -> 46873 | D14: =INDEX('Cash Flow'!$B$2:$BI$2,24+MATCH(D13,INDEX('Cash Flow'!$B$31:$BI$31,25):INDEX('Cash Flow'!$B$31:$BI$31,36),0)) -> 47238 | E14: =INDEX('Cash Flow'!$B$2:$BI$2,36+MATCH(E13,INDEX('Cash Flow'!$B$31:$BI$31,37):INDEX('Cash Flow'!$B$31:$BI$31,48),0)) -> 47603 | F14: =INDEX('Cash Flow'!$B$2:$BI$2,48+MATCH(F13,INDEX('Cash Flow'!$B$31:$BI$31,49):INDEX('Cash Flow'!$B$31:$BI$31,60),0)) -> 47968
A15: Days cash on hand (total cash / daily expenses) | B15: =IF(Summary!B$24=0,0,B12/(Summary!B$24/365)) -> 93.350004 | C15: =IF(Summary!C$24=0,0,C12/(Summary!C$24/365)) -> 97.826208 | D15: =IF(Summary!D$24=0,0,D12/(Summary!D$24/365)) -> 100.12328 | E15: =IF(Summary!E$24=0,0,E12/(Summary!E$24/365)) -> 107.07444 | F15: =IF(Summary!F$24=0,0,F12/(Summary!F$24/365)) -> 114.91147
A17: Cash flow is on a cash basis: tuition follows the payment-plan profile, prepayments for next year (May/June) are included.
A19: Supporting calculation: annual amounts by cash-timing profile (feeds the monthly Cash Flow tab)
A20: Revenue lines | B20: =B3 -> FY27 | C20: =C3 -> FY28 | D20: =D3 -> FY29 | E20: =E3 -> FY30 | F20: =F3 -> FY31 | G20: Next FY (est.)
A21: (FY32 is estimated from FY31 x growth; only used for May/June prepayments in the final year)
A22: Tuition Plan | B22: =SUMIFS('Forecast Detail'!G$8:G$400,'Forecast Detail'!$A$8:$A$400,"Revenue",'Forecast Detail'!$F$8:$F$400,"Tuition Plan") -> 8592782 | C22: =SUMIFS('Forecast Detail'!H$8:H$400,'Forecast Detail'!$A$8:$A$400,"Revenue",'Forecast Detail'!$F$8:$F$400,"Tuition Plan") -> 9133108.6 | D22: =SUMIFS('Forecast Detail'!I$8:I$400,'Forecast Detail'!$A$8:$A$400,"Revenue",'Forecast Detail'!$F$8:$F$400,"Tuition Plan") -> 9462573.1 | E22: =SUMIFS('Forecast Detail'!J$8:J$400,'Forecast Detail'!$A$8:$A$400,"Revenue",'Forecast Detail'!$F$8:$F$400,"Tuition Plan") -> 9775890.8 | F22: =SUMIFS('Forecast Detail'!K$8:K$400,'Forecast Detail'!$A$8:$A$400,"Revenue",'Forecast Detail'!$F$8:$F$400,"Tuition Plan") -> 10082474 | G22: =F22*(1+Inputs!$G$9) -> 10485773
A23: Even | B23: =SUMIFS('Forecast Detail'!G$8:G$400,'Forecast Detail'!$A$8:$A$400,"Revenue",'Forecast Detail'!$F$8:$F$400,"Even") -> 149300 | C23: =SUMIFS('Forecast Detail'!H$8:H$400,'Forecast Detail'!$A$8:$A$400,"Revenue",'Forecast Detail'!$F$8:$F$400,"Even") -> 142005.03 | D23: =SUMIFS('Forecast Detail'!I$8:I$400,'Forecast Detail'!$A$8:$A$400,"Revenue",'Forecast Detail'!$F$8:$F$400,"Even") -> 142005.03 | E23: =SUMIFS('Forecast Detail'!J$8:J$400,'Forecast Detail'!$A$8:$A$400,"Revenue",'Forecast Detail'!$F$8:$F$400,"Even") -> 142005.03 | F23: =SUMIFS('Forecast Detail'!K$8:K$400,'Forecast Detail'!$A$8:$A$400,"Revenue",'Forecast Detail'!$F$8:$F$400,"Even") -> 142005.03 | G23: =F23*(1+Inputs!$G$9) -> 147685.23
A24: Jul Lump | B24: =SUMIFS('Forecast Detail'!G$8:G$400,'Forecast Detail'!$A$8:$A$400,"Revenue",'Forecast Detail'!$F$8:$F$400,"Jul Lump") -> 562300 | C24: =SUMIFS('Forecast Detail'!H$8:H$400,'Forecast Detail'!$A$8:$A$400,"Revenue",'Forecast Detail'!$F$8:$F$400,"Jul Lump") -> 479809.79 | D24: =SUMIFS('Forecast Detail'!I$8:I$400,'Forecast Detail'!$A$8:$A$400,"Revenue",'Forecast Detail'!$F$8:$F$400,"Jul Lump") -> 428973.2 | E24: =SUMIFS('Forecast Detail'!J$8:J$400,'Forecast Detail'!$A$8:$A$400,"Revenue",'Forecast Detail'!$F$8:$F$400,"Jul Lump") -> 427578.87 | F24: =SUMIFS('Forecast Detail'!K$8:K$400,'Forecast Detail'!$A$8:$A$400,"Revenue",'Forecast Detail'!$F$8:$F$400,"Jul Lump") -> 426463.4 | G24: =F24*(1+Inputs!$G$9) -> 443521.94
